Workbook
Name ActiveScenario: "'Scenario Engine'!B3"
Name BaseWACC: "'Sensitivity Analysis'!B5"
Name IntrinsicValue: "'WACC & DCF Valuation'!B81"
Name SharesOutstanding: "'WACC & DCF Valuation'!B80"
Name TerminalGrowth: "'WACC & DCF Valuation'!B56"
Name WACC: "'WACC & DCF Valuation'!B32"

Sheet Navigation
B2: Jindal Coke Ltd. — Financial Model Navigation Index
B3: Model Version: EXP v2.0 | Last Updated: Apr 2026 | Prepared by: Divyanshu Vatsa
B5: # | C5: Sheet Name | D5: Purpose | E5: Key Outputs
B6: 1 | C6: Model Checks | D6: Automated integrity validation | E6: 47+ PASS/FAIL tests (BS balance, cash, debt, dep)
B7: 2 | C7: Scenario Engine | D7: Bull / Base / Bear assumption toggle | E7: Active scenario drives all projections & DCF
B8: 3 | C8: Dashboard | D8: Executive summary with charts | E8: Key metrics, valuation, covenant tracker, thesis
B9: 4 | C9: Historical FS | D9: 10-year cleaned financials (FY16–FY25) | E9: P&L, BS, CF with formula references
B10: 5 | C10: Ratio Analysis | D10: 35+ ratios with interpretations | E10: Growth, profitability, leverage, efficiency
B11: 6 | C11: Common Size Statements | D11: Percentage-of-total analysis | E11: Structural composition trends
B12: 7 | C12: Assumptions & Drivers | D12: All projection inputs & cost drivers | E12: Revenue, COGS decomposition, WC, capex, debt, tax
B13: 8 | C13: The 3-Statement Projection | D13: Integrated P&L, BS, CF (FY25A–FY33E) | E13: Core financial outputs + balance checks
B14: 9 | C14: WACC & DCF Valuation | D14: DCF model with WACC build | E14: ="Intrinsic value per share (₹"&TEXT('WACC & DCF Valuation'!B81,"0")&")" -> Intrinsic value per share (₹515)
B15: 10 | C15: Sensitivity Analysis | D15: 2-way WACC × Terminal g table | E15: ="Valuation range ₹"&TEXT(MIN('Sensitivity Analysis'!B11:F15),"#,##0")&"–₹"&TEXT(MAX('Sensitivity Analysis'!B11:F15),"#,##0") -> Valuation range ₹466–₹747
B16: 11 | C16: Comparable Company Analysis | D16: EV/EBITDA comps (Sandur Manganese) | E16: Blended valuation cross-check
B17: 12 | C17: Production & Offtake | D17: Bottom-up volume × price build | E17: Revenue reconciliation to mentor benchmark
B18: 13 | C18: Depreciation Schedule | D18: Book SL + IT WDV by asset class | E18: Feeds P&L depreciation and Tax Working
B19: 14 | C19: Tax Working | D19: CIT vs MAT dual test | E19: Tax expense + DTL movement
B20: 15 | C20: Debt Schedule | D20: TL + BC + WC + Revolver roll-forward | E20: Interest expense + debt balances
B21: 16 | C21: Working Capital Schedule | D21: Tandon-style MPBF calculation | E21: WC gap + bank finance limit
B22: 17 | C22: DSCR Covenant Tracker | D22: Lender covenant compliance | E22: DSCR, ISCR, FACR status checks
B24: COLOR CODING LEGEND
B25: ■ Blue Text = Hardcoded Assumption (Editable Input)
B26: ■ Black Text = Formula / Derived Calculation (Do Not Edit)
B27: ■ Green Text = Cross-Sheet Link (References another tab)
B28: ■ Red Text = External Link (References another workbook)
B29: ■ Yellow Background = Key Assumption Needing Attention

Sheet Model Checks
B1: Jindal Coke Ltd. — Model Integrity Checks
B2: Automated PASS / FAIL tests. Red = requires attention.
A4: # | B4: Check Description | C4: Status | D4: Detail / Formula
B5: 1. BALANCE SHEET CHECKS
A6: 1 | B6: BS Balance: Total Assets = Total E+L (FY24A) | C6: =IF(ABS('The 3-Statement Projection'!B105)<0.05,"PASS","FAIL") -> PASS | D6: ='The 3-Statement Projection'!B105 -> 0
A7: 2 | B7: BS Balance: Total Assets = Total E+L (FY25A) | C7: =IF(ABS('The 3-Statement Projection'!C105)<0.05,"PASS","FAIL") -> PASS | D7: ='The 3-Statement Projection'!C105 -> 0
A8: 3 | B8: BS Balance: Total Assets = Total E+L (FY26E) | C8: =IF(ABS('The 3-Statement Projection'!D105)<0.05,"PASS","FAIL") -> PASS | D8: ='The 3-Statement Projection'!D105 -> 0
A9: 4 | B9: BS Balance: Total Assets = Total E+L (FY27E) | C9: =IF(ABS('The 3-Statement Projection'!E105)<0.05,"PASS","FAIL") -> PASS | D9: ='The 3-Statement Projection'!E105 -> 0
A10: 5 | B10: BS Balance: Total Assets = Total E+L (FY28E) | C10: =IF(ABS('The 3-Statement Projection'!F105)<0.05,"PASS","FAIL") -> PASS | D10: ='The 3-Statement Projection'!F105 -> 0
A11: 6 | B11: BS Balance: Total Assets = Total E+L (FY29E) | C11: =IF(ABS('The 3-Statement Projection'!G105)<0.05,"PASS","FAIL") -> PASS | D11: ='The 3-Statement Projection'!G105 -> 0
A12: 7 | B12: BS Balance: Historical FS FY25A (Assets - E+L) | C12: =IF(ABS('Historical FS'!L96-'Historical FS'!L74)<0.1,"PASS","FAIL") -> PASS | D12: ='Historical FS'!L96-'Historical FS'!L74 -> 0
B14: 2. CASH FLOW CHECKS
A15: 10 | B15: Historical CF: Closing Cash = BS Cash (FY25A) | C15: =IF(ABS('Historical FS'!L141-'Historical FS'!L91)<0.1,"PASS","FAIL") -> PASS | D15: ='Historical FS'!L141-'Historical FS'!L91 -> 0
A16: 11 | B16: 3-Stmt CF: Closing Cash = BS Cash (FY26E) | C16: =IF(ABS('The 3-Statement Projection'!D102-'The 3-Statement Projection'!D67)<0.05,"PASS","FAIL") -> PASS | D16: ='The 3-Statement Projection'!D102-'The 3-Statement Projection'!D67 -> 0
A17: 12 | B17: 3-Stmt CF: Closing Cash = BS Cash (FY27E) | C17: =IF(ABS('The 3-Statement Projection'!E102-'The 3-Statement Projection'!E67)<0.05,"PASS","FAIL") -> PASS | D17: ='The 3-Statement Projection'!E102-'The 3-Statement Projection'!E67 -> 0
A18: 13 | B18: 3-Stmt CF: Closing Cash = BS Cash (FY28E) | C18: =IF(ABS('The 3-Statement Projection'!F102-'The 3-Statement Projection'!F67)<0.05,"PASS","FAIL") -> PASS | D18: ='The 3-Statement Projection'!F102-'The 3-Statement Projection'!F67 -> 0
A19: 14 | B19: 3-Stmt CF: Closing Cash = BS Cash (FY29E) | C19: =IF(ABS('The 3-Statement Projection'!G102-'The 3-Statement Projection'!G67)<0.05,"PASS","FAIL") -> PASS | D19: ='The 3-Statement Projection'!G102-'The 3-Statement Projection'!G67 -> 0
B21: 3. DEBT SCHEDULE CHECKS
A22: 17 | B22: Debt Roll-Forward: TL Opening + Draw = Closing (FY25A) | C22: =IF(ABS('The 3-Statement Projection'!C109)<0.05,"PASS","FAIL") -> PASS | D22: ='The 3-Statement Projection'!C109 -> 0
A23: 18 | B23: Debt Roll-Forward: TL Opening + Draw = Closing (FY26E) | C23: =IF(ABS('The 3-Statement Projection'!D109)<0.05,"PASS","FAIL") -> PASS | D23: ='The 3-Statement Projection'!D109 -> 0
A24: 19 | B24: Debt Roll-Forward: TL Opening + Draw = Closing (FY27E) | C24: =IF(ABS('The 3-Statement Projection'!E109)<0.05,"PASS","FAIL") -> PASS | D24: ='The 3-Statement Projection'!E109 -> 0
A25: 20 | B25: Debt Roll-Forward: TL Opening + Draw = Closing (FY28E) | C25: =IF(ABS('The 3-Statement Projection'!F109)<0.05,"PASS","FAIL") -> PASS | D25: ='The 3-Statement Projection'!F109 -> 0
A26: 21 | B26: Debt Roll-Forward: TL Opening + Draw = Closing (FY29E) | C26: =IF(ABS('The 3-Statement Projection'!G109)<0.05,"PASS","FAIL") -> PASS | D26: ='The 3-Statement Projection'!G109 -> 0
A27: 22 | B27: Revolver Roll-Forward (FY26E) | C27: =IF(ABS('The 3-Statement Projection'!D110)<0.05,"PASS","FAIL") -> PASS | D27: ='The 3-Statement Projection'!D110 -> 0
A28: 23 | B28: Revolver Roll-Forward (FY27E) | C28: =IF(ABS('The 3-Statement Projection'!E110)<0.05,"PASS","FAIL") -> PASS | D28: ='The 3-Statement Projection'!E110 -> 0
A29: 24 | B29: Revolver Roll-Forward (FY28E) | C29: =IF(ABS('The 3-Statement Projection'!F110)<0.05,"PASS","FAIL") -> PASS | D29: ='The 3-Statement Projection'!F110 -> 0
A30: 25 | B30: Revolver Roll-Forward (FY29E) | C30: =IF(ABS('The 3-Statement Projection'!G110)<0.05,"PASS","FAIL") -> PASS | D30: ='The 3-Statement Projection'!G110 -> 0
B32: 4. DEPRECIATION LINKAGE
A33: 28 | B33: Depreciation: Schedule = 3-Stmt P&L (FY26E) | C33: =IF(ABS('Depreciation Schedule'!E21-'The 3-Statement Projection'!D18)<0.05,"PASS","FAIL") -> PASS | D33: ='Depreciation Schedule'!E21-'The 3-Statement Projection'!D18 -> 0
A34: 29 | B34: Depreciation: Schedule = 3-Stmt P&L (FY27E) | C34: =IF(ABS('Depreciation Schedule'!F21-'The 3-Statement Projection'!E18)<0.05,"PASS","FAIL") -> PASS | D34: ='Depreciation Schedule'!F21-'The 3-Statement Projection'!E18 -> 0
A35: 30 | B35: Depreciation: Schedule = 3-Stmt P&L (FY28E) | C35: =IF(ABS('Depreciation Schedule'!G21-'The 3-Statement Projection'!F18)<0.05,"PASS","FAIL") -> PASS | D35: ='Depreciation Schedule'!G21-'The 3-Statement Projection'!F18 -> 0
A36: 31 | B36: Depreciation: Schedule = 3-Stmt P&L (FY29E) | C36: =IF(ABS('Depreciation Schedule'!H21-'The 3-Statement Projection'!G18)<0.05,"PASS","FAIL") -> PASS | D36: ='Depreciation Schedule'!H21-'The 3-Statement Projection'!G18 -> 0
B38: 5. REVENUE CONSISTENCY
A39: 34 | B39: Revenue: Dashboard = 3-Stmt (FY25A) | C39: =IF(ABS(Dashboard!D6-'The 3-Statement Projection'!C6)<0.01,"PASS","FAIL") -> PASS | D39: =Dashboard!D6-'The 3-Statement Projection'!C6 -> 0
A40: 35 | B40: Revenue: Dashboard = 3-Stmt (FY26E) | C40: =IF(ABS(Dashboard!E6-'The 3-Statement Projection'!D6)<0.01,"PASS","FAIL") -> PASS | D40: =Dashboard!E6-'The 3-Statement Projection'!D6 -> 0
A41: 36 | B41: Revenue: Dashboard = 3-Stmt (FY27E) | C41: =IF(ABS(Dashboard!F6-'The 3-Statement Projection'!E6)<0.01,"PASS","FAIL") -> PASS | D41: =Dashboard!F6-'The 3-Statement Projection'!E6 -> 0
A42: 37 | B42: Revenue: Dashboard = 3-Stmt (FY28E) | C42: =IF(ABS(Dashboard!G6-'The 3-Statement Projection'!F6)<0.01,"PASS","FAIL") -> PASS | D42: =Dashboard!G6-'The 3-Statement Projection'!F6 -> 0
A43: 38 | B43: Revenue: Dashboard = 3-Stmt (FY29E) | C43: =IF(ABS(Dashboard!H6-'The 3-Statement Projection'!G6)<0.01,"PASS","FAIL") -> PASS | D43: =Dashboard!H6-'The 3-Statement Projection'!G6 -> 0
B45: 6. INTEREST EXPENSE LINKAGE
A46: 41 | B46: Interest: Debt Schedule = 3-Stmt (FY26E) | C46: =IF(ABS('Debt Schedule'!E25-'The 3-Statement Projection'!D21)<0.05,"PASS","FAIL") -> PASS | D46: ='Debt Schedule'!E25-'The 3-Statement Projection'!D21 -> 0
A47: 42 | B47: Interest: Debt Schedule = 3-Stmt (FY27E) | C47: =IF(ABS('Debt Schedule'!F25-'The 3-Statement Projection'!E21)<0.05,"PASS","FAIL") -> PASS | D47: ='Debt Schedule'!F25-'The 3-Statement Projection'!E21 -> 0
A48: 43 | B48: Interest: Debt Schedule = 3-Stmt (FY28E) | C48: =IF(ABS('Debt Schedule'!G25-'The 3-Statement Projection'!F21)<0.05,"PASS","FAIL") -> PASS | D48: ='Debt Schedule'!G25-'The 3-Statement Projection'!F21 -> 0
A49: 44 | B49: Interest: Debt Schedule = 3-Stmt (FY29E) | C49: =IF(ABS('Debt Schedule'!H25-'The 3-Statement Projection'!G21)<0.05,"PASS","FAIL") -> PASS | D49: ='Debt Schedule'!H25-'The 3-Statement Projection'!G21 -> 0
B51: 7. FORECAST CONTINUITY
A52: 47 | B52: FY25A→FY26E Revenue growth is reasonable (<50%) | C52: =IF(ABS('The 3-Statement Projection'!D7)<0.5,"PASS","FAIL") -> PASS | D52: ='The 3-Statement Projection'!D7 -> 0.11210268
A53: 48 | B53: FY26E EBITDA margin within 5-30% range | C53: =IF(AND('The 3-Statement Projection'!D16>0.05,'The 3-Statement Projection'!D16<0.3),"PASS","FAIL") -> PASS | D53: ='The 3-Statement Projection'!D16 -> 0.18247245
B56: Note: Open in Excel → select column C → apply Conditional Formatting: "PASS" = green, "FAIL" = red.
B57: 8. EXTENDED FORECAST CHECKS (FY30E–FY33E)
A58: 8 | B58: BS Balance: Total Assets = Total E+L (FY30E) | C58: =IF(ABS('The 3-Statement Projection'!H105)<0.05,"PASS","FAIL") -> PASS | D58: ='The 3-Statement Projection'!H105 -> 0
A59: 9 | B59: BS Balance: Total Assets = Total E+L (FY31E) | C59: =IF(ABS('The 3-Statement Projection'!I105)<0.05,"PASS","FAIL") -> PASS | D59: ='The 3-Statement Projection'!I105 -> 0
A60: 10 | B60: BS Balance: Total Assets = Total E+L (FY32E) | C60: =IF(ABS('The 3-Statement Projection'!J105)<0.05,"PASS","FAIL") -> PASS | D60: ='The 3-Statement Projection'!J105 -> 0
A61: 11 | B61: BS Balance: Total Assets = Total E+L (FY33E) | C61: =IF(ABS('The 3-Statement Projection'!K105)<0.05,"PASS","FAIL") -> PASS | D61: ='The 3-Statement Projection'!K105 -> 0
B62: Cash Flow:
A63: 12 | B63: 3-Stmt CF: Closing Cash = BS Cash (FY30E) | C63: =IF(ABS('The 3-Statement Projection'!H102-'The 3-Statement Projection'!H67)<0.05,"PASS","FAIL") -> PASS | D63: ='The 3-Statement Projection'!H102-'The 3-Statement Projection'!H67 -> 0
A64: 13 | B64: 3-Stmt CF: Closing Cash = BS Cash (FY31E) | C64: =IF(ABS('The 3-Statement Projection'!I102-'The 3-Statement Projection'!I67)<0.05,"PASS","FAIL") -> PASS | D64: ='The 3-Statement Projection'!I102-'The 3-Statement Projection'!I67 -> 0
A65: 14 | B65: 3-Stmt CF: Closing Cash = BS Cash (FY32E) | C65: =IF(ABS('The 3-Statement Projection'!J102-'The 3-Statement Projection'!J67)<0.05,"PASS","FAIL") -> PASS | D65: ='The 3-Statement Projection'!J102-'The 3-Statement Projection'!J67 -> 0
A66: 15 | B66: 3-Stmt CF: Closing Cash = BS Cash (FY33E) | C66: =IF(ABS('The 3-Statement Projection'!K102-'The 3-Statement Projection'!K67)<0.05,"PASS","FAIL") -> PASS | D66: ='The 3-Statement Projection'!K102-'The 3-Statement Projection'!K67 -> 0
B67: Depreciation:
A68: 16 | B68: Depreciation: Schedule = 3-Stmt P&L (FY30E) | C68: =IF(ABS('Depreciation Schedule'!I21-'The 3-Statement Projection'!H18)<0.05,"PASS","FAIL") -> PASS | D68: ='Depreciation Schedule'!I21-'The 3-Statement Projection'!H18 -> 0
A69: 17 | B69: Depreciation: Schedule = 3-Stmt P&L (FY31E) | C69: =IF(ABS('Depreciation Schedule'!J21-'The 3-Statement Projection'!I18)<0.05,"PASS","FAIL") -> PASS | D69: ='Depreciation Schedule'!J21-'The 3-Statement Projection'!I18 -> 0
A70: 18 | B70: Depreciation: Schedule = 3-Stmt P&L (FY32E) | C70: =IF(ABS('Depreciation Schedule'!K21-'The 3-Statement Projection'!J18)<0.05,"PASS","FAIL") -> PASS | D70: ='Depreciation Schedule'!K21-'The 3-Statement Projection'!J18 -> 0
A71: 19 | B71: Depreciation: Schedule = 3-Stmt P&L (FY33E) | C71: =IF(ABS('Depreciation Schedule'!L21-'The 3-Statement Projection'!K18)<0.05,"PASS","FAIL") -> PASS | D71: ='Depreciation Schedule'!L21-'The 3-Statement Projection'!K18 -> 0
B73: Cross-Model Consistency:
A74: 20 | B74: Revenue: Production = 3-Stmt Net Sales (FY26E) | C74: =IF(ABS('Production & Offtake'!E33-'The 3-Statement Projection'!D6)<0.05,"PASS","FAIL") -> PASS | D74: ='Production & Offtake'!E33-'The 3-Statement Projection'!D6 -> 0
A75: 21 | B75: Revenue: Production = 3-Stmt Net Sales (FY27E) | C75: =IF(ABS('Production & Offtake'!F33-'The 3-Statement Projection'!E6)<0.05,"PASS","FAIL") -> PASS | D75: ='Production & Offtake'!F33-'The 3-Statement Projection'!E6 -> 0
A76: 22 | B76: NWC: Working Capital = DCF NWC (FY26E) | C76: =IF(ABS('Working Capital Schedule'!E15-'WACC & DCF Valuation'!D43)<0.05,"PASS","FAIL") -> PASS | D76: ='Working Capital Schedule'!E15-'WACC & DCF Valuation'!D43 -> 0
A77: 23 | B77: NWC: Working Capital = DCF NWC (FY27E) | C77: =IF(ABS('Working Capital Schedule'!F15-'WACC & DCF Valuation'!E43)<0.05,"PASS","FAIL") -> PASS | D77: ='Working Capital Schedule'!F15-'WACC & DCF Valuation'!E43 -> 0
B79: Sanity Checks:
A80: 24 | B80: DSCR Covenant ≥ 1.20x all projection years | C80: =IF(MIN('DSCR Covenant Tracker'!D19:K19)>=1.2,"PASS","FAIL") -> PASS | D80: =MIN('DSCR Covenant Tracker'!D19:K19) -> 1.3530565
A81: 25 | B81: No negative cash balance in any projection year | C81: =IF(MIN('The 3-Statement Projection'!D67:K67)>=0,"PASS","FAIL") -> PASS | D81: =MIN('The 3-Statement Projection'!D67:K67) -> 20
A82: 26 | B82: Total Assets = Total Equity + Liabilities (FY26E) | C82: =IF(ABS('The 3-Statement Projection'!D72-'The 3-Statement Projection'!D52)<0.05,"PASS","FAIL") -> PASS | D82: ='The 3-Statement Projection'!D72-'The 3-Statement Projection'!D52 -> 0

Sheet Scenario Engine
A1: Scenario Engine
A2: Select a scenario below. All projection sheets, DCF, and Dashboard cascade automatically.
A3: Active Scenario: | B3: Base | C3: ← Change this cell (dropdown)
A5: 1. COST & PROFITABILITY DRIVERS
A6: Driver | B6: Bull | C6: Base | D6: Bear | E6: Rationale
A7: COGS (% of Net Sales) | B7: 0.79 | C7: 0.82 | D7: 0.85 | E7: Bull: favorable coal spreads; Bear: input cost squeeze
A8: Employee Benefit Exp (% Sales) | B8: 0.0088 | C8: 0.0093 | D8: 0.01 | E8: Operating leverage on employee costs
A9: SG&A Expenses (% Sales) | B9: 0.035 | C9: 0.0374 | D9: 0.04 | E9: Fixed cost dilution at scale vs. cost inflation
A10: Assumed USD/INR Rate | B10: 82 | C10: 85 | D10: 91 | E10: Bull: strong INR; Bear: 5-7% depreciation from base
A11: Coking Coal (USD/MT) | B11: 150 | C11: 170 | D11: 210 | E11: Bull: low coal cost ($150); Base: mid-cycle ($170); Bear: squeeze ($210/MT)
A12: Consumption Ratio (MT coal / MT coke) | B12: 1.4 | C12: 1.4 | D12: 1.4 | E12: Industry standard: ~1.35-1.45x yield loss in coke conversion
A13: Domestic Processing Cost (₹/MT) | B13: 8000 | C13: 8470 | D13: 9000 | E13: Bull: efficient ops (₹8,000/MT); Base: ₹8,470/MT; Bear: cost inflation (₹9,000/MT)
A14: Domestic Cost Inflation (%) | B14: 0.02 | C14: 0.03243 | D14: 0.04 | E14: Annual escalation on domestic conversion, power, freight costs
A16: 2. WORKING CAPITAL DRIVERS
A17: Driver | B17: Bull | C17: Base | D17: Bear | E17: Rationale
A18: Debtor Days | B18: 30 | C18: 35 | D18: 45 | E18: Bull: JSL group collections faster; Bear: delayed payments
A19: Inventory Days | B19: 40 | C19: 45 | D19: 55 | E19: Bear: coal supply chain disruptions, longer buffer needed
A20: Payable Days | B20: 45 | C20: 40 | D20: 35 | E20: Bull: better supplier terms; Bear: tighter credit
A22: 3. CAPEX & DEPRECIATION
A23: Driver | B23: Bull | C23: Base | D23: Bear | E23: Rationale
A25: 4. FINANCING DRIVERS
A26: Driver | B26: Bull | C26: Base | D26: Bear | E26: Rationale
A27: Interest Rate on Debt (%) | B27: 0.085 | C27: 0.09 | D27: 0.1 | E27: Bull: rate easing (RBI cuts); Bear: tighter credit
A29: 5. DCF / WACC ASSUMPTIONS
A30: Driver | B30: Bull | C30: Base | D30: Bear | E30: Rationale
A31: Terminal Growth Rate (g) | B31: 0.02 | C31: 0 | D31: 0 | E31: Bull: secular India growth; Bear: global steel downcycle
A32: Unlevered Beta (βu) | B32: 0.8 | C32: 0.85 | D32: 0.95 | E32: Bear: higher systematic risk in downcycle
A33: Pre-tax Cost of Debt | B33: =B27 -> 0.085 | C33: =C27 -> 0.09 | D33: =D27 -> 0.1 | E33: Same as financing driver above — flows to WACC
A35: LIVE OUTPUT (cascaded from active scenario)
A36: WACC | B36: ='WACC & DCF Valuation'!B32 -> 0.12514351 | C36: Implied EV (₹ Cr) | D36: ='WACC & DCF Valuation'!B65 -> 2114.246
A37: Terminal g | B37: ='WACC & DCF Valuation'!B56 -> 0 | C37: Equity Value (₹ Cr) | D37: ='WACC & DCF Valuation'!B76 -> 1669.346
A38: Net Sales FY25A | B38: ='Assumptions & Drivers'!D10 -> 1680.3612 | C38: Intrinsic Value / Share (₹) | D38: ='WACC & DCF Valuation'!B81 -> 514.75362
A40: 7. MENTOR-ALIGNED DRIVERS (added Nov 2025)
A41: Driver | B41: Bull | C41: Base | D41: Bear | E41: Rationale
A42: COB-1 Installed Capacity (MT) | B42: 429000 | C42: 429000 | D42: 429000 | E42: Fixed existing battery capacity (0.429 MTPA)
A43: COB-2 Installed Capacity (MT) | B43: 350000 | C43: 350000 | D43: 350000
A44: COB-1 Utilization % (flat) | B44: 0.92 | C44: 0.911766 | D44: 0.85
A45: COB-2 Util FY25A | B45: 0.5 | C45: 0.35 | D45: 0.25 | E45: New battery commissioning ramp-up
A46: COB-2 Util FY26E | B46: 0.8 | C46: 0.7 | D46: 0.55
A47: COB-2 Util FY27E | B47: 0.85 | C47: 0.8 | D47: 0.7
A48: COB-2 Util FY28E/29E | B48: 0.85 | C48: 0.8 | D48: 0.75
A49: Coke Realization (₹/MT) | B49: 30000 | C49: 27000 | D49: 24000 | E49: Mentor base ₹27,000 (conservative, post FY22/23 peak). Was ₹35,000 in prior model
A50: Coke Price Growth (YoY %) | B50: 0.03 | C50: 0 | D50: 0 | E50: Base case: flat realization per mentor benchmark. Bull: 3% escalation for inflation pass-through. Bear: 0% (same as base — no pricing power in downcycle).
A51: Flat Revenue After Full Ramp (Y/N) | B51: N | C51: N | D51: Y | E51: Bear case: Revenue flattens after full COB-2 ramp-up per mentor benchmark — tests downside if no pricing power exists
A52: COG Yield (Nm³ / MT coke) | B52: 222 | C52: 222 | D52: 200 | E52: Coke oven gas by-product yield. Mentor implied ~222 Nm³/MT
A53: COG Price (₹/Nm³) | B53: 20 | C53: 19.44 | D53: 18 | E53: Mentor: ₹19.44/Nm³
A54: Coal Tar Yield (% of coke) | B54: 0.0378 | C54: 0.0378 | D54: 0.035 | E54: Mentor: 3.78% yield
A55: Coal Tar Price (₹/MT) | B55: 40000 | C55: 37000 | D55: 33000
A56: CDQ Cost Saving (₹ Cr/year, steady) | B56: 50 | C56: 45.6 | D56: 35 | E56: Mentor: 12 MW captive power benefit. 57 Cr theoretical, used at ~80%
A57: Buyers Credit Opening (₹ Cr) | B57: 100 | C57: 147 | D57: 200 | E57: FY24 closing buyers credit balance from BSS
A58: IT Depreciation Rate - P&M (%) | B58: 0.15 | C58: 0.15 | D58: 0.15 | E58: Income Tax WDV rate on plant & machinery (Section 32)
A59: FY26E Buyback Amount (₹ Cr) | B59: 179.95 | C59: 179.95 | D59: 0 | E59: Mentor: ₹179.95 Cr lump-sum equity buyback from JSL in FY26E. Bear: no buyback (liquidity conservation).
A60: IT Depreciation Rate - Buildings (%) | B60: 0.1 | C60: 0.1 | D60: 0.1 | E60: Income Tax WDV rate on buildings
A61: MAT Rate (%) | B61: 0.17472 | C61: 0.17472 | D61: 0.17472 | E61: MAT @ 15% + 10% surcharge + 4% H&E cess = 17.472%
A62: Opening Unabsorbed Depreciation (₹ Cr) | B62: 0 | C62: 36.26 | D62: 0 | E62: Set to 0 unless JCL has opening tax losses. Mentor uses 36.26
A64: 8. ANNUAL TAPER RATES (drive COGS% and WC Days cascade in Assumptions)
A65: Driver | B65: Bull | C65: Base | D65: Bear | E65: Rationale
A66: COGS% Taper — FY26 (coal pricing benefit) | B66: -0.03 | C66: -0.03 | D66: -0.01 | E66: FY26E RM%=75% (favorable coal pricing for new COB-2). Large drop reflects mentor's cost structure.
A67: COGS% Taper — FY27 (RM normalization) | B67: 0.015 | C67: 0.02 | D67: 0.035 | E67: FY27E RM% normalizes to 80.5% (higher coal consumption on full COB-2 ramp). COGS% rises from FY26E low.
A68: COGS% Taper — FY28+ (steady-state) | B68: -0.004 | C68: -0.002 | D68: -0.001 | E68: Gradual improvement from operating leverage. Applied from FY28E onward to terminal.
A69: Debtor Days — Annual Taper | B69: -2 | C69: -1 | D69: 1 | E69: Bull: group collection discipline; Bear: slippage
A70: Inventory Days — Annual Taper | B70: -3 | C70: -2 | D70: 1 | E70: Bull: supply chain optimization; Bear: longer buffer
A71: Debtor Days — Floor | B71: 25 | C71: 30 | D71: 35 | E71: Minimum collection period floor
A72: Inventory Days — Floor | B72: 35 | C72: 40 | D72: 45 | E72: Minimum inventory buffer floor
A74: 9. SCENARIO VALIDATION GUARDRAILS
A75: Check | B75: Status
A76: Active Scenario Valid? | B76: =IF(OR(B3="Bull",B3="Base",B3="Bear"),"✓ Valid","✗ Invalid") -> ✓ Valid
A77: COGS% Bull < Base < Bear? | B77: =IF(AND(B7<C7,C7<D7),"✓ Correct ordering","✗ Check values") -> ✓ Correct ordering
A78: Interest Rate Bull ≤ Base ≤ Bear? | B78: =IF(AND(B27<=C27,C27<=D27),"✓ Correct ordering","✗ Check values") -> ✓ Correct ordering
A79: Terminal g Bull ≥ Base ≥ Bear? | B79: =IF(AND(B31>=C31,C31>=D31),"✓ Correct ordering","✗ Check values") -> ✓ Correct ordering
A81: 10. WACC & VALUATION GOVERNANCE (single source of truth — referenced by 'WACC & DCF Valuation' & 'Sensitivity Analysis')
A82: Driver | B82: Bull | C82: Base | D82: Bear | E82: Rationale / Source
A83: Risk-free Rate (Rf, 10-yr G-Sec) | B83: 0.065 | C83: 0.07 | D83: 0.075 | E83: 10-yr Indian G-Sec yield. Bull = lower-rate environment, Bear = inflation-driven repricing.
A84: Equity Risk Premium (ERP) | B84: 0.07 | C84: 0.0725 | D84: 0.075 | E84: Damodaran India ERP (mature equity premium + India CRP).
A85: Preference Capital — Outstanding (₹ Cr) | B85: 109.26 | C85: 109.26 | D85: 109.26 | E85: 10.926 Cr × ₹10 face value pref shares (FY25A close per Balance Sheet Summary).
A86: Cost of Preference Capital (Kp) | B86: 0.085 | C86: 0.09 | D86: 0.095 | E86: Coupon on cumulative redeemable preference shares.
A87: Target Debt-to-Equity (D/E) | B87: 0.6 | C87: 0.82 | D87: 1 | E87: Target capital structure for WACC weights (deleveraging case = lower D/E).
A88: Equity Shares Outstanding (Crore) | B88: 3.243 | C88: 3.243 | D88: 3.243 | E88: Paid-up equity capital ₹32.43 Cr ÷ ₹10 face value = 3.243 Cr shares.
A89: Lender / Conservative WACC | B89: 0.13 | C89: 0.141 | D89: 0.15 | E89: Lender-view discount rate for credit/downside valuation. Mentor benchmark = 14.10%.

Sheet Dashboard
B1: ="Jindal Coke Ltd. — Executive Dashboard | Model v2.0 | Scenario: "&'Scenario Engine'!B3&" | "&TEXT(TODAY(),"dd-mmm-yyyy") -> Jindal Coke Ltd. — Executive Dashboard | Model v2.0 | Scenario: Base | 29-May-2026
B2: All figures in ₹ Crores unless stated otherwise | FY ends March 31
B4: 1. KEY FINANCIAL SUMMARY
B5: Metric | C5: FY24A | D5: FY25A | E5: FY26E | F5: FY27E | G5: FY28E | H5: FY29E | I5: FY30E | J5: FY31E | K5: FY32E | L5: FY33E
B6: Net Sales (₹ Cr) | C6: ='The 3-Statement Projection'!B6 -> 1572.8 | D6: ='The 3-Statement Projection'!C6 -> 1871.33 | E6: ='The 3-Statement Projection'!D6 -> 2081.1111 | F6: ='The 3-Statement Projection'!E6 -> 2195.6111 | G6: ='The 3-Statement Projection'!F6 -> 2195.6111 | H6: ='The 3-Statement Projection'!G6 -> 2195.6111 | I6: ='The 3-Statement Projection'!H6 -> 2195.6111 | J6: ='The 3-Statement Projection'!I6 -> 2195.6111 | ... L6: ='The 3-Statement Projection'!K6 -> 2195.6111
B7: EBITDA Margin (%) | C7: ='The 3-Statement Projection'!B16 -> 0.10350966 | D7: ='The 3-Statement Projection'!C16 -> 0.10711099 | E7: ='The 3-Statement Projection'!D16 -> 0.18247245 | F7: ='The 3-Statement Projection'!E16 -> 0.16406871 | G7: ='The 3-Statement Projection'!F16 -> 0.16606871 | H7: ='The 3-Statement Projection'!G16 -> 0.16806871 | I7: ='The 3-Statement Projection'!H16 -> 0.16806871 | J7: ='The 3-Statement Projection'!I16 -> 0.16806871 | ... L7: ='The 3-Statement Projection'!K16 -> 0.16806871
B8: Net Profit (₹ Cr) | C8: ='The 3-Statement Projection'!B27 -> 95.89 | D8: ='The 3-Statement Projection'!C27 -> 114.6 | E8: ='The 3-Statement Projection'!D27 -> 225.81068 | F8: ='The 3-Statement Projection'!E27 -> 199.77612 | G8: ='The 3-Statement Projection'!F27 -> 210.34615 | H8: ='The 3-Statement Projection'!G27 -> 215.82119 | I8: ='The 3-Statement Projection'!H27 -> 217.875 | J8: ='The 3-Statement Projection'!I27 -> 219.89403 | ... L8: ='The 3-Statement Projection'!K27 -> 223.85558
B9: Total Debt (₹ Cr) | C9: ='The 3-Statement Projection'!B39+'The 3-Statement Projection'!B45+'The 3-Statement Projection'!B46 -> 324.82 | D9: ='The 3-Statement Projection'!C39+'The 3-Statement Projection'!C45+'The 3-Statement Projection'!C46 -> 545.82 | E9: ='The 3-Statement Projection'!D39+'The 3-Statement Projection'!D45+'The 3-Statement Projection'!D46 -> 613.1 | F9: ='The 3-Statement Projection'!E39+'The 3-Statement Projection'!E45+'The 3-Statement Projection'!E46 -> 419.11871 | G9: ='The 3-Statement Projection'!F39+'The 3-Statement Projection'!F45+'The 3-Statement Projection'!F46 -> 351.8 | H9: ='The 3-Statement Projection'!G39+'The 3-Statement Projection'!G45+'The 3-Statement Projection'!G46 -> 306.5 | I9: ='The 3-Statement Projection'!H39+'The 3-Statement Projection'!H45+'The 3-Statement Projection'!H46 -> 261.5 | J9: ='The 3-Statement Projection'!I39+'The 3-Statement Projection'!I45+'The 3-Statement Projection'!I46 -> 216.5 | ... L9: ='The 3-Statement Projection'!K39+'The 3-Statement Projection'!K45+'The 3-Statement Projection'!K46 -> 126.5
B10: ROCE (%) | C10: ='The 3-Statement Projection'!B19/('The 3-Statement Projection'!B36+'The 3-Statement Projection'!B42) -> 0.11487105 | D10: ='The 3-Statement Projection'!C19/('The 3-Statement Projection'!C36+'The 3-Statement Projection'!C42) -> 0.12937162 | E10: ='The 3-Statement Projection'!D19/('The 3-Statement Projection'!D36+'The 3-Statement Projection'!D42) -> 0.26225183 | F10: ='The 3-Statement Projection'!E19/('The 3-Statement Projection'!E36+'The 3-Statement Projection'!E42) -> 0.22886099 | G10: ='The 3-Statement Projection'!F19/('The 3-Statement Projection'!F36+'The 3-Statement Projection'!F42) -> 0.21680431 | H10: ='The 3-Statement Projection'!G19/('The 3-Statement Projection'!G36+'The 3-Statement Projection'!G42) -> 0.20579064 | I10: ='The 3-Statement Projection'!H19/('The 3-Statement Projection'!H36+'The 3-Statement Projection'!H42) -> 0.19323932 | J10: ='The 3-Statement Projection'!I19/('The 3-Statement Projection'!I36+'The 3-Statement Projection'!I42) -> 0.18196167 | ... L10: ='The 3-Statement Projection'!K19/('The 3-Statement Projection'!K36+'The 3-Statement Projection'!K42) -> 0.16249584
B12: 1b. MACRO & FOREX SENSITIVITY
B13: Assumed USD/INR Rate | C13: n/a | D13: ='Assumptions & Drivers'!D15 -> 85 | E13: ='Assumptions & Drivers'!E15 -> 85 | F13: ='Assumptions & Drivers'!F15 -> 85 | G13: ='Assumptions & Drivers'!G15 -> 85 | H13: ='Assumptions & Drivers'!H15 -> 85 | I13: ='Assumptions & Drivers'!I15 -> 85 | J13: ='Assumptions & Drivers'!J15 -> 85 | K13: ='Assumptions & Drivers'!K15 -> 85 | L13: ='Assumptions & Drivers'!L15 -> 85
B14: Coking Coal (USD/MT) | C14: n/a | D14: ='Assumptions & Drivers'!D16 -> 170 | E14: ='Assumptions & Drivers'!E16 -> 170 | F14: ='Assumptions & Drivers'!F16 -> 170 | G14: ='Assumptions & Drivers'!G16 -> 170 | H14: ='Assumptions & Drivers'!H16 -> 170 | I14: ='Assumptions & Drivers'!I16 -> 170 | J14: ='Assumptions & Drivers'!J16 -> 170 | K14: ='Assumptions & Drivers'!K16 -> 170 | L14: ='Assumptions & Drivers'!L16 -> 170
B16: 2. PERFORMANCE CHARTS
A19: Base Case (WACC = 12.5%, g = 0.0%)
B51: 3. DCF VALUATION OUTPUT
B52: Implied Intrinsic Value per Share | C52: ='WACC & DCF Valuation'!B81 -> 514.75362 | E52: WACC: | F52: ='WACC & DCF Valuation'!B32 -> 0.12514351 | G52: Terminal g: | H52: ='WACC & DCF Valuation'!B56 -> 0
B53: Conservative Value per Share (WACC 14.1%) | C53: ='WACC & DCF Valuation'!B149 -> 458.75388 | E53: WACC: | F53: ='WACC & DCF Valuation'!B108 -> 0.141
B54: CHART DATA — DO NOT EDIT
B56: Chart 1: Revenue & Growth
C57: FY24A | D57: FY25A | E57: FY26E | F57: FY27E | G57: FY28E | H57: FY29E | I57: FY30E | J57: FY31E | K57: FY32E | L57: FY33E
B58: Revenue (₹ Cr) | C58: =C6 -> 1572.8 | D58: =D6 -> 1871.33 | E58: =E6 -> 2081.1111 | F58: =F6 -> 2195.6111 | G58: =G6 -> 2195.6111 | H58: =H6 -> 2195.6111 | I58: =I6 -> 2195.6111 | J58: =J6 -> 2195.6111 | ... L58: =L6 -> 2195.6111
B59: YoY Growth (%) | D59: ='The 3-Statement Projection'!C7 -> 0.18980799 | E59: ='The 3-Statement Projection'!D7 -> 0.11210268 | F59: ='The 3-Statement Projection'!E7 -> 0.055018677 | G59: ='The 3-Statement Projection'!F7 -> 0 | H59: ='The 3-Statement Projection'!G7 -> 0 | I59: ='The 3-Statement Projection'!H7 -> 0 | J59: ='The 3-Statement Projection'!I7 -> 0 | K59: ='The 3-Statement Projection'!J7 -> 0 | L59: ='The 3-Statement Projection'!K7 -> 0
B62: Chart 2: Margin Expansion
C63: FY24A | D63: FY25A | E63: FY26E | F63: FY27E | G63: FY28E | H63: FY29E | I63: FY30E | J63: FY31E | K63: FY32E | L63: FY33E
B64: Gross Margin | C64: ='The 3-Statement Projection'!B10/'The 3-Statement Projection'!B6 -> 0.15022889 | D64: ='The 3-Statement Projection'!C10/'The 3-Statement Projection'!C6 -> 0.15809077 | E64: ='The 3-Statement Projection'!D10/'The 3-Statement Projection'!D6 -> 0.22917245 | F64: ='The 3-Statement Projection'!E10/'The 3-Statement Projection'!E6 -> 0.21076871 | G64: ='The 3-Statement Projection'!F10/'The 3-Statement Projection'!F6 -> 0.21276871 | H64: ='The 3-Statement Projection'!G10/'The 3-Statement Projection'!G6 -> 0.21476871 | I64: ='The 3-Statement Projection'!H10/'The 3-Statement Projection'!H6 -> 0.21476871 | J64: ='The 3-Statement Projection'!I10/'The 3-Statement Projection'!I6 -> 0.21476871 | ... L64: ='The 3-Statement Projection'!K10/'The 3-Statement Projection'!K6 -> 0.21476871
B65: EBITDA Margin | C65: =C7 -> 0.10350966 | D65: =D7 -> 0.10711099 | E65: =E7 -> 0.18247245 | F65: =F7 -> 0.16406871 | G65: =G7 -> 0.16606871 | H65: =H7 -> 0.16806871 | I65: =I7 -> 0.16806871 | J65: =J7 -> 0.16806871 | ... L65: =L7 -> 0.16806871
B66: Net Margin | C66: ='The 3-Statement Projection'!B28 -> 0.060967701 | D66: ='The 3-Statement Projection'!C28 -> 0.061239867 | E66: ='The 3-Statement Projection'!D28 -> 0.10850486 | F66: ='The 3-Statement Projection'!E28 -> 0.090988844 | G66: ='The 3-Statement Projection'!F28 -> 0.095803008 | H66: ='The 3-Statement Projection'!G28 -> 0.098296639 | I66: ='The 3-Statement Projection'!H28 -> 0.099232054 | J66: ='The 3-Statement Projection'!I28 -> 0.10015163 | ... L66: ='The 3-Statement Projection'!K28 -> 0.10195593
B69: Chart 3: Debt vs Cash (Deleveraging)
C70: FY24A | D70: FY25A | E70: FY26E | F70: FY27E | G70: FY28E | H70: FY29E | I70: FY30E | J70: FY31E | K70: FY32E | L70: FY33E
B71: Total Debt | C71: =C9 -> 324.82 | D71: =D9 -> 545.82 | E71: =E9 -> 613.1 | F71: =F9 -> 419.11871 | G71: =G9 -> 351.8 | H71: =H9 -> 306.5 | I71: =I9 -> 261.5 | J71: =J9 -> 216.5 | ... L71: =L9 -> 126.5
B72: Cash & Bank Balance | C72: ='The 3-Statement Projection'!B67 -> 74.8 | D72: ='The 3-Statement Projection'!C67 -> 210.18 | E72: ='The 3-Statement Projection'!D67 -> 32.122825 | F72: ='The 3-Statement Projection'!E67 -> 20 | G72: ='The 3-Statement Projection'!F67 -> 298.26036 | H72: ='The 3-Statement Projection'!G67 -> 447.28284 | I72: ='The 3-Statement Projection'!H67 -> 591.82165 | J72: ='The 3-Statement Projection'!I67 -> 734.66564 | ... L72: ='The 3-Statement Projection'!K67 -> 980.69601
B73: Net Debt | C73: =C71-C72 -> 250.02 | D73: =D71-D72 -> 335.64 | E73: =E71-E72 -> 580.97717 | F73: =F71-F72 -> 399.11871 | G73: =G71-G72 -> 53.539645 | H73: =H71-H72 -> -140.78284 | I73: =I71-I72 -> -330.32165 | J73: =J71-J72 -> -518.16564 | ... L73: =L71-L72 -> -854.19601
B76: Chart 4: Valuation Football Field
C77: Low (₹) | D77: Base - Low | E77: High - Base
B78: Bear (WACC+1%, g 0%) | C78: ='Sensitivity Analysis'!B15 -> 465.82131 | D78: ='Sensitivity Analysis'!D15-'Sensitivity Analysis'!B15 -> 42.875385 | E78: ='Sensitivity Analysis'!F15-'Sensitivity Analysis'!D15 -> 60.900948
B79: Moderate Bear | C79: ='Sensitivity Analysis'!B14 -> 489.35898 | D79: ='Sensitivity Analysis'!D14-'Sensitivity Analysis'!B14 -> 48.004449 | E79: ='Sensitivity Analysis'!F14-'Sensitivity Analysis'!D14 -> 69.305793
B80: Base Case | C80: ='Sensitivity Analysis'!B13 -> 514.75362 | D80: ='Sensitivity Analysis'!D13-'Sensitivity Analysis'!B13 -> 53.94508 | E80: ='Sensitivity Analysis'!F13-'Sensitivity Analysis'!D13 -> 79.288212
B81: Moderate Bull | C81: ='Sensitivity Analysis'!B12 -> 542.23561 | D81: ='Sensitivity Analysis'!D12-'Sensitivity Analysis'!B12 -> 60.863831 | E81: ='Sensitivity Analysis'!F12-'Sensitivity Analysis'!D12 -> 91.241254
B82: Bull (WACC-1%, g 4%) | C82: ='Sensitivity Analysis'!B11 -> 572.07529 | D82: ='Sensitivity Analysis'!D11-'Sensitivity Analysis'!B11 -> 68.970618 | E82: ='Sensitivity Analysis'!F11-'Sensitivity Analysis'!D11 -> 105.6847
B83: Lender/Conservative (WACC 14.1%) | C83: ='WACC & DCF Valuation'!F156 -> 458.75388 | D83: =C80-C83 -> 55.999734 | E83: 0
B85: 4. SCENARIO TOGGLE
B86: Active Scenario: | C86: ='Scenario Engine'!B3 -> Base | D86: ← Change via dropdown on 'Scenario Engine' sheet → cell B3
B87: Bull = Optimistic assumptions | Base = Current model | Bear = Conservative / downside
B89: How it works:
B90: 1. The 'Scenario Engine' sheet contains Bull / Base / Bear values for all key drivers (capacity utilization, COGS %, realization, capex, terminal growth, beta, etc.).
B91: 2. The 'Assumptions & Drivers' sheet reads the active scenario via INDEX/MATCH formulas linked to the Scenario Engine toggle.
B93: 5. INVESTMENT THESIS
B95: The Capacity Story
B96: JCL has completed a transformative capacity expansion, nearly doubling met coke production from 0.43 MTPA (COB-1 only) to 0.779 MTPA (COB-1 + COB-2). The ₹433 Cr brownfield project was capitalised in FY25A (CWIP → Net Fixed Assets). COB-1 runs at 91.2% utilisation producing ~391,148 MT/year, while COB-2 ramps from 35% (FY25A) to 80% by FY28E. At full ramp, total sales volume reaches ~671,148 MT. This positions JCL as one of the larger standalone met coke producers in India, directly plugged into structural demand from the domestic steel sector.
B98: The Efficiency Story
B99: After extreme margin volatility through the commodity supercycle (EBITDA margin peaked at 30% in FY22, troughed at 10% in FY24–FY25), the model projects a sharp recovery to 18.2% in FY26E as the lower COGS% (79%, driven by favourable coal pricing for COB-2 commissioning) kicks in. Margins then normalise to ~16.3–16.7% from FY27E onwards as raw material costs revert to 80.5–80.8% of revenue. CDQ heat recovery adds ~₹40–46 Cr/year in cost savings (200bps margin lift). The V-shaped COGS% trajectory — 82% (FY25A) → 79% (FY26E) → 81% (FY27E) → 80.5% steady state — mirrors the mentor's cost structure. The 8-year explicit forecast (FY26E–FY33E) captures the full ramp-up and normalisation cycle.
B101: The Deleveraging Story
B102: FY25A total debt stands at ~₹546 Cr (Bank TL ₹285 + Buyers Credit ₹261). A TL refinancing in FY26E draws +₹146 Cr (gross TL → ₹431 Cr) but Buyers Credit starts running off: ₹152 Cr (FY26) → ₹5 Cr (FY27) → ₹0 (FY28). Bank TL then amortises ₹34–45 Cr/year through FY33E. The FY26E ₹180 Cr share buyback compresses cash to ~₹32 Cr, but the strong cash generation trajectory (PAT ₹230+ Cr/year) rebuilds cash rapidly. Net Debt turns negative by FY29E as cash exceeds total borrowings. By FY33E, total debt drops to ~₹127 Cr. ISCR improves from 6.0x (FY25A) to 23.6x by FY33E; Net Debt/EBITDA from 1.7x to –2.2x. The conditional revolver draws only when cash falls below ₹50 Cr, reflecting disciplined liquidity management.
B104: Scenario-Specific Risk Commentary
B105: =IF('Scenario Engine'!B3="Bear",_xlfn._LONGTEXT("⚠️ BEAR CASE: Deleveraging is delayed due to FX-driven margin compression and higher working capital friction. Imported coal costs rise sharply (USD/INR at ₹91, coal at $210/MT), squeezing gross margins. EBITDA margins pressured below 14%. Revenue flatten","s after FY27E (mentor-aligned flat-revenue toggle). Equity value is significantly discounted."),IF('Scenario Engine'!B3="Bull",_xlfn._LONGTEXT("✅ BULL CASE: Favourable FX (USD/INR at ₹82) and lower coal prices ($150/MT) support margin stability. EBITDA margins hold at ~17-19%. Working capital normalises rapidly, freeing cash for accelerated deleveraging. Higher terminal growth (g=4%) lifts valuat","ion."),"📊 BASE CASE: Mid-cycle assumptions — USD/INR at ₹85, coal at $170/MT. EBITDA margins improve from "&TEXT('The 3-Statement Projection'!C16,"0.0%")&" to "&TEXT('The 3-Statement Projection'!K16,"0.0%")&" through FY33E. 8-year explicit forecast (FY26E–FY33E) with "&TEXT(-SUM('Debt Schedule'!E7:L7),"#,##0")&" Cr cumulative TL amortization. FY26E includes ₹180 Cr share buyback.")) -> 📊 BASE CASE: Mid-cycle assumptions — USD/INR at ₹85, coal at $170/MT. EBITDA margins improve from 10.7% to 16.8% through FY33E. 8-year explicit forecast (FY26E–FY33E) with 159 Cr cumulative TL amortization. FY26E includes ₹180 Cr share buyback.
B106: Revenue Bridge Note & Model Metadata
B107: 6. LENDER-STYLE COVENANT METRICS (Added Nov 2025)
B108: Note: FY25A Net Sales of ₹1,871 Cr includes ₹191 Cr of realization premium vs the ₹27,000/MT mentor benchmark. FY26E+ projections are rebased to the mentor benchmark. The apparent FY25A→FY26E growth of 13.1% understates true volume-driven growth of ~25.9%.
B109: Metric | C109: Covenant | D109: FY25A | E109: FY26E | F109: FY27E | G109: FY28E | H109: FY29E | I109: FY30E | J109: FY31E | K109: FY32E | L109: FY33E
B110: DSCR (Gross) | C110: ≥ 1.20x | D110: =('The 3-Statement Projection'!C15-'Tax Working'!D23)/('The 3-Statement Projection'!C21+MAX(0,-'Debt Schedule'!D7)) -> 2.3936446 | E110: =('The 3-Statement Projection'!D15-'Tax Working'!E23)/('The 3-Statement Projection'!D21+MAX(0,-'Debt Schedule'!E7)) -> 5.1501108 | F110: =('The 3-Statement Projection'!E15-'Tax Working'!F23)/('The 3-Statement Projection'!E21+MAX(0,-'Debt Schedule'!F7)) -> 3.6368754 | G110: =('The 3-Statement Projection'!F15-'Tax Working'!G23)/('The 3-Statement Projection'!F21+MAX(0,-'Debt Schedule'!G7)) -> 3.645845 | H110: =('The 3-Statement Projection'!G15-'Tax Working'!H23)/('The 3-Statement Projection'!G21+MAX(0,-'Debt Schedule'!H7)) -> 3.8571718 | I110: =('The 3-Statement Projection'!H15-'Tax Working'!I23)/('The 3-Statement Projection'!H21+MAX(0,-'Debt Schedule'!I7)) -> 4.0685497 | J110: =('The 3-Statement Projection'!I15-'Tax Working'!J23)/('The 3-Statement Projection'!I21+MAX(0,-'Debt Schedule'!J7)) -> 4.2889692 | K110: =('The 3-Statement Projection'!J15-'Tax Working'!K23)/('The 3-Statement Projection'!J21+MAX(0,-'Debt Schedule'!K7)) -> 4.5387608 | L110: =('The 3-Statement Projection'!K15-'Tax Working'!L23)/('The 3-Statement Projection'!K21+MAX(0,-'Debt Schedule'!L7)) -> 4.8236634
B111: ISCR (EBITDA / Interest) | C111: ≥ 3.0x | D111: ='The 3-Statement Projection'!C15/'The 3-Statement Projection'!C21 -> 5.9814981 | E111: ='The 3-Statement Projection'!D15/'The 3-Statement Projection'!D21 -> 6.3980673 | F111: ='The 3-Statement Projection'!E15/'The 3-Statement Projection'!E21 -> 7.776223 | G111: ='The 3-Statement Projection'!F15/'The 3-Statement Projection'!F21 -> 10.318866 | H111: ='The 3-Statement Projection'!G15/'The 3-Statement Projection'!G21 -> 11.856427 | I111: ='The 3-Statement Projection'!H15/'The 3-Statement Projection'!H21 -> 13.636863 | J111: ='The 3-Statement Projection'!I15/'The 3-Statement Projection'!I21 -> 16.037093 | K111: ='The 3-Statement Projection'!J15/'The 3-Statement Projection'!J21 -> 19.462738 | L111: ='The 3-Statement Projection'!K15/'The 3-Statement Projection'!K21 -> 24.749397
B112: FACR (Net Block / Secured Debt) | C112: ≥ 1.25x | D112: ='The 3-Statement Projection'!C57/'The 3-Statement Projection'!C39 -> 1.8026418 | E112: ='The 3-Statement Projection'!D57/'The 3-Statement Projection'!D39 -> 2.1869107 | F112: ='The 3-Statement Projection'!E57/'The 3-Statement Projection'!E39 -> 2.3173523 | G112: ='The 3-Statement Projection'!F57/'The 3-Statement Projection'!F39 -> 2.5458538 | H112: ='The 3-Statement Projection'!G57/'The 3-Statement Projection'!G39 -> 2.8411764 | I112: ='The 3-Statement Projection'!H57/'The 3-Statement Projection'!H39 -> 3.2325339 | J112: ='The 3-Statement Projection'!I57/'The 3-Statement Projection'!I39 -> 3.7832562 | K112: ='The 3-Statement Projection'!J57/'The 3-Statement Projection'!J39 -> 4.6186858 | L112: ='The 3-Statement Projection'!K57/'The 3-Statement Projection'!K39 -> 6.0425147
B113: Total Debt / EBITDA | C113: ≤ 3.5x | D113: =('The 3-Statement Projection'!C39+'The 3-Statement Projection'!C45+'The 3-Statement Projection'!C46)/'The 3-Statement Projection'!C15 -> 2.7231092 | E113: =('The 3-Statement Projection'!D39+'The 3-Statement Projection'!D45+'The 3-Statement Projection'!D46)/'The 3-Statement Projection'!D15 -> 1.6145026 | F113: =('The 3-Statement Projection'!E39+'The 3-Statement Projection'!E45+'The 3-Statement Projection'!E46)/'The 3-Statement Projection'!E15 -> 1.1634718 | G113: =('The 3-Statement Projection'!F39+'The 3-Statement Projection'!F45+'The 3-Statement Projection'!F46)/'The 3-Statement Projection'!F15 -> 0.96483404 | H113: =('The 3-Statement Projection'!G39+'The 3-Statement Projection'!G45+'The 3-Statement Projection'!G46)/'The 3-Statement Projection'!G15 -> 0.83059289 | I113: =('The 3-Statement Projection'!H39+'The 3-Statement Projection'!H45+'The 3-Statement Projection'!H46)/'The 3-Statement Projection'!H15 -> 0.70864613 | J113: =('The 3-Statement Projection'!I39+'The 3-Statement Projection'!I45+'The 3-Statement Projection'!I46)/'The 3-Statement Projection'!I15 -> 0.58669938 | K113: =('The 3-Statement Projection'!J39+'The 3-Statement Projection'!J45+'The 3-Statement Projection'!J46)/'The 3-Statement Projection'!J15 -> 0.46475263 | L113: =('The 3-Statement Projection'!K39+'The 3-Statement Projection'!K45+'The 3-Statement Projection'!K46)/'The 3-Statement Projection'!K15 -> 0.34280587
B114: Net Debt / EBITDA | C114: ≤ 2.5x | D114: =('The 3-Statement Projection'!C39+'The 3-Statement Projection'!C45+'The 3-Statement Projection'!C46-'The 3-Statement Projection'!C67)/'The 3-Statement Projection'!C15 -> 1.6745161 | E114: =('The 3-Statement Projection'!D39+'The 3-Statement Projection'!D45+'The 3-Statement Projection'!D46-'The 3-Statement Projection'!D67)/'The 3-Statement Projection'!D15 -> 1.5299122 | F114: =('The 3-Statement Projection'!E39+'The 3-Statement Projection'!E45+'The 3-Statement Projection'!E46-'The 3-Statement Projection'!E67)/'The 3-Statement Projection'!E15 -> 1.1079519 | G114: =('The 3-Statement Projection'!F39+'The 3-Statement Projection'!F45+'The 3-Statement Projection'!F46-'The 3-Statement Projection'!F67)/'The 3-Statement Projection'!F15 -> 0.14683591 | H114: =('The 3-Statement Projection'!G39+'The 3-Statement Projection'!G45+'The 3-Statement Projection'!G46-'The 3-Statement Projection'!G67)/'The 3-Statement Projection'!G15 -> -0.38151133 | I114: =('The 3-Statement Projection'!H39+'The 3-Statement Projection'!H45+'The 3-Statement Projection'!H46-'The 3-Statement Projection'!H67)/'The 3-Statement Projection'!H15 -> -0.89514783 | J114: =('The 3-Statement Projection'!I39+'The 3-Statement Projection'!I45+'The 3-Statement Projection'!I46-'The 3-Statement Projection'!I67)/'The 3-Statement Projection'!I15 -> -1.4041915 | K114: =('The 3-Statement Projection'!J39+'The 3-Statement Projection'!J45+'The 3-Statement Projection'!J46-'The 3-Statement Projection'!J67)/'The 3-Statement Projection'!J15 -> -1.8574925 | L114: =('The 3-Statement Projection'!K39+'The 3-Statement Projection'!K45+'The 3-Statement Projection'!K46-'The 3-Statement Projection'!K67)/'The 3-Statement Projection'!K15 -> -2.3148096
B115: Net Debt / Tangible Net Worth | C115: ≤ 2.0x | D115: =('The 3-Statement Projection'!C39+'The 3-Statement Projection'!C45+'The 3-Statement Projection'!C46-'The 3-Statement Projection'!C67)/'The 3-Statement Projection'!C36 -> 0.42081244 | E115: =('The 3-Statement Projection'!D39+'The 3-Statement Projection'!D45+'The 3-Statement Projection'!D46-'The 3-Statement Projection'!D67)/'The 3-Statement Projection'!D36 -> 0.75965833 | F115: =('The 3-Statement Projection'!E39+'The 3-Statement Projection'!E45+'The 3-Statement Projection'!E46-'The 3-Statement Projection'!E67)/'The 3-Statement Projection'!E36 -> 0.44659099 | G115: =('The 3-Statement Projection'!F39+'The 3-Statement Projection'!F45+'The 3-Statement Projection'!F46-'The 3-Statement Projection'!F67)/'The 3-Statement Projection'!F36 -> 0.051979578 | H115: =('The 3-Statement Projection'!G39+'The 3-Statement Projection'!G45+'The 3-Statement Projection'!G46-'The 3-Statement Projection'!G67)/'The 3-Statement Projection'!G36 -> -0.12031098 | I115: =('The 3-Statement Projection'!H39+'The 3-Statement Projection'!H45+'The 3-Statement Projection'!H46-'The 3-Statement Projection'!H67)/'The 3-Statement Projection'!H36 -> -0.25181937 | J115: =('The 3-Statement Projection'!I39+'The 3-Statement Projection'!I45+'The 3-Statement Projection'!I46-'The 3-Statement Projection'!I67)/'The 3-Statement Projection'!I36 -> -0.35619216 | K115: =('The 3-Statement Projection'!J39+'The 3-Statement Projection'!J45+'The 3-Statement Projection'!J46-'The 3-Statement Projection'!J67)/'The 3-Statement Projection'!J36 -> -0.4286336 | L115: =('The 3-Statement Projection'!K39+'The 3-Statement Projection'!K45+'The 3-Statement Projection'!K46-'The 3-Statement Projection'!K67)/'The 3-Statement Projection'!K36 -> -0.48953963
B116: Current Ratio (CA/CL) | C116: ≥ 1.00x | D116: ='The 3-Statement Projection'!C70/'The 3-Statement Projection'!C49 -> 1.2964588 | E116: ='The 3-Statement Projection'!D70/'The 3-Statement Projection'!D49 -> 1.129856 | F116: ='The 3-Statement Projection'!E70/'The 3-Statement Projection'!E49 -> 1.6688764 | G116: ='The 3-Statement Projection'!F70/'The 3-Statement Projection'!F49 -> 2.7621392 | H116: ='The 3-Statement Projection'!G70/'The 3-Statement Projection'!G49 -> 3.2788446 | I116: ='The 3-Statement Projection'!H70/'The 3-Statement Projection'!H49 -> 3.7980058 | J116: ='The 3-Statement Projection'!I70/'The 3-Statement Projection'!I49 -> 4.3110794 | K116: ='The 3-Statement Projection'!J70/'The 3-Statement Projection'!J49 -> 4.7502695 | L116: ='The 3-Statement Projection'!K70/'The 3-Statement Projection'!K49 -> 5.1947827
B117: Return on Equity (%) | C117: — | D117: ='The 3-Statement Projection'!C27/(('The 3-Statement Projection'!C36+'The 3-Statement Projection'!B36)/2) -> 0.13987294 | E117: ='The 3-Statement Projection'!D27/(('The 3-Statement Projection'!D36+'The 3-Statement Projection'!C36)/2) -> 0.28905848 | F117: ='The 3-Statement Projection'!E27/(('The 3-Statement Projection'!E36+'The 3-Statement Projection'!D36)/2) -> 0.24091352 | G117: ='The 3-Statement Projection'!F27/(('The 3-Statement Projection'!F36+'The 3-Statement Projection'!E36)/2) -> 0.21868757 | H117: ='The 3-Statement Projection'!G27/(('The 3-Statement Projection'!G36+'The 3-Statement Projection'!F36)/2) -> 0.19618584 | I117: ='The 3-Statement Projection'!H27/(('The 3-Statement Projection'!H36+'The 3-Statement Projection'!G36)/2) -> 0.17557126 | J117: ='The 3-Statement Projection'!I27/(('The 3-Statement Projection'!I36+'The 3-Statement Projection'!H36)/2) -> 0.15897046 | K117: ='The 3-Statement Projection'!J27/(('The 3-Statement Projection'!J36+'The 3-Statement Projection'!I36)/2) -> 0.14531608 | L117: ='The 3-Statement Projection'!K27/(('The 3-Statement Projection'!K36+'The 3-Statement Projection'!J36)/2) -> 0.13388395
B118: Return on Assets (%) | C118: — | D118: ='The 3-Statement Projection'!C27/(('The 3-Statement Projection'!C72+'The 3-Statement Projection'!B72)/2) -> 0.061070655 | E118: ='The 3-Statement Projection'!D27/(('The 3-Statement Projection'!D72+'The 3-Statement Projection'!C72)/2) -> 0.12551175 | F118: ='The 3-Statement Projection'!E27/(('The 3-Statement Projection'!E72+'The 3-Statement Projection'!D72)/2) -> 0.11781779 | G118: ='The 3-Statement Projection'!F27/(('The 3-Statement Projection'!F72+'The 3-Statement Projection'!E72)/2) -> 0.12341013 | H118: ='The 3-Statement Projection'!G27/(('The 3-Statement Projection'!G72+'The 3-Statement Projection'!F72)/2) -> 0.12092511 | I118: ='The 3-Statement Projection'!H27/(('The 3-Statement Projection'!H72+'The 3-Statement Projection'!G72)/2) -> 0.11600689 | J118: ='The 3-Statement Projection'!I27/(('The 3-Statement Projection'!I72+'The 3-Statement Projection'!H72)/2) -> 0.1114827 | K118: ='The 3-Statement Projection'!J27/(('The 3-Statement Projection'!J72+'The 3-Statement Projection'!I72)/2) -> 0.10732606 | L118: ='The 3-Statement Projection'!K27/(('The 3-Statement Projection'!K72+'The 3-Statement Projection'!J72)/2) -> 0.10348907
B119: Net WC Cycle (Days) | C119: — | D119: ='Assumptions & Drivers'!D55 -> 40 | E119: ='Assumptions & Drivers'!E55 -> 37 | F119: ='Assumptions & Drivers'!F55 -> 34 | G119: ='Assumptions & Drivers'!G55 -> 32 | H119: ='Assumptions & Drivers'!H55 -> 31 | I119: ='Assumptions & Drivers'!I55 -> 31 | J119: ='Assumptions & Drivers'!J55 -> 31 | K119: ='Assumptions & Drivers'!K55 -> 31 | L119: ='Assumptions & Drivers'!L55 -> 31
B121: 7. KNOWN DEVIATIONS FROM MENTOR MODEL
B122: # | C122: Deviation | D122: EXP Model | E122: Mentor | F122: Impact
B123: 1 | C123: Employee costs | D123: 0.93% of sales (₹20–23 Cr) | E123: Flat ₹12.45 Cr/yr | F123: Conservative: +₹7–9 Cr/yr cost
B124: 2 | C124: Forecast horizon | D124: 8 years (FY26E–FY33E) | E124: 6 years (FY26E–FY31E) | F124: More explicit FCFF, less TV reliance
B125: 3 | C125: Coke price growth | D125: 0% base (2% bull) | E125: 0% flat all scenarios | F125: Aligned in base case
B126: 4 | C126: Depreciation method | D126: Asset-class SL + IT WDV | E126: Capex-driven single rate | F126: More granular, similar output
B127: 5 | C127: Tax computation | D127: CIT vs MAT dual test | E127: CIT vs MAT dual test | F127: Aligned
B128: 6 | C128: Revolver facility | D128: ₹30 Cr conditional draw | E128: Not modeled | F128: Adds liquidity realism
B130: 8. SENSITIVITY MATRIX — Implied Value per Share (₹)
B131: WACC (rows) × Terminal Growth (cols). Grid explores WACC 10.5%–16.5% and g 2.0%–5.0%. Base-case matrix cell (WACC 12.51%, g=3%) highlighted at E136 = ₹636/sh. Primary model base case uses g=0% → ₹515/sh (see Mentor Reconciliation). Source: 'WACC & DCF Valuation'!A84:H91
B133: WACC ↓ / g → | C133: ='WACC & DCF Valuation'!B84 -> 0.02 | D133: ='WACC & DCF Valuation'!C84 -> 0.025 | E133: ='WACC & DCF Valuation'!D84 -> 0.03 | F133: ='WACC & DCF Valuation'!E84 -> 0.035 | G133: ='WACC & DCF Valuation'!F84 -> 0.04 | H133: ='WACC & DCF Valuation'!G84 -> 0.045 | I133: ='WACC & DCF Valuation'!H84 -> 0.05
B134: ='WACC & DCF Valuation'!A85 -> 0.10514351 | C134: ='WACC & DCF Valuation'!B85 -> 770.19618 | D134: ='WACC & DCF Valuation'!C85 -> 802.39328 | E134: ='WACC & DCF Valuation'!D85 -> 838.87513 | F134: ='WACC & DCF Valuation'!E85 -> 880.55801 | G134: ='WACC & DCF Valuation'!F85 -> 928.63951 | H134: ='WACC & DCF Valuation'!G85 -> 984.71548 | I134: ='WACC & DCF Valuation'!H85 -> 1050.9605
B135: ='WACC & DCF Valuation'!A86 -> 0.11514351 | C135: ='WACC & DCF Valuation'!B86 -> 674.46621 | D135: ='WACC & DCF Valuation'!C86 -> 698.51751 | E135: ='WACC & DCF Valuation'!D86 -> 725.3936 | F135: ='WACC & DCF Valuation'!E86 -> 755.62319 | G135: ='WACC & DCF Valuation'!F86 -> 789.87569 | H135: ='WACC & DCF Valuation'!G86 -> 829.01139 | I135: ='WACC & DCF Valuation'!H86 -> 874.1547
B136: ='WACC & DCF Valuation'!A87 -> 0.12514351 | C136: ='WACC & DCF Valuation'!B87 -> 596.85592 | D136: ='WACC & DCF Valuation'!C87 -> 615.25969 | E136: ='WACC & DCF Valuation'!D87 -> 635.59777 | F136: ='WACC & DCF Valuation'!E87 -> 658.19205 | G136: ='WACC & DCF Valuation'!F87 -> 683.43999 | H136: ='WACC & DCF Valuation'!G87 -> 711.83827 | I136: ='WACC & DCF Valuation'!H87 -> 744.01576
B137: ='WACC & DCF Valuation'!A88 -> 0.13514351 | C137: ='WACC & DCF Valuation'!B88 -> 532.65136 | D137: ='WACC & DCF Valuation'!C88 -> 547.01331 | E137: ='WACC & DCF Valuation'!D88 -> 562.74121 | F137: ='WACC & DCF Valuation'!E88 -> 580.03964 | G137: ='WACC & DCF Valuation'!F88 -> 599.15622 | H137: ='WACC & DCF Valuation'!G88 -> 620.39347 | I137: ='WACC & DCF Valuation'!H88 -> 644.12502
B138: ='WACC & DCF Valuation'!A89 -> 0.14514351 | C138: ='WACC & DCF Valuation'!B89 -> 478.64477 | D138: ='WACC & DCF Valuation'!C89 -> 490.0378 | E138: ='WACC & DCF Valuation'!D89 -> 502.4203 | F138: ='WACC & DCF Valuation'!E89 -> 515.92701 | G138: ='WACC & DCF Valuation'!F89 -> 530.71832 | H138: ='WACC & DCF Valuation'!G89 -> 546.98664 | I138: ='WACC & DCF Valuation'!H89 -> 564.96484
B139: ='WACC & DCF Valuation'!A90 -> 0.15514351 | C139: ='WACC & DCF Valuation'!B90 -> 432.57742 | D139: ='WACC & DCF Valuation'!C90 -> 441.74169 | E139: ='WACC & DCF Valuation'!D90 -> 451.63827 | F139: ='WACC & DCF Valuation'!E90 -> 462.35857 | G139: ='WACC & DCF Valuation'!F90 -> 474.00992 | H139: ='WACC & DCF Valuation'!G90 -> 486.7191 | I139: ='WACC & DCF Valuation'!H90 -> 500.63702
B140: ='WACC & DCF Valuation'!A91 -> 0.16514351 | C140: ='WACC & DCF Valuation'!B91 -> 392.81266 | D140: ='WACC & DCF Valuation'!C91 -> 400.2727 | E140: ='WACC & DCF Valuation'!D91 -> 408.28474 | F140: ='WACC & DCF Valuation'!E91 -> 416.91242 | G140: ='WACC & DCF Valuation'!F91 -> 426.22952 | H140: ='WACC & DCF Valuation'!G91 -> 436.32211 | I140: ='WACC & DCF Valuation'!H91 -> 447.29123
B142: Base case for this matrix: WACC 12.51%, g=3% → ₹636/sh (cell E136, highlighted). Note the primary model uses g=0% → ₹515/sh; the matrix grid explores the range g=2%–5% (standard practice) to stress-test terminal assumptions. WACC range: 10.5%–16.5% (base ±2%/+4%).
B143: Lender view (WACC 14.1%, g=0%) is handled separately on WACC & DCF!A104:H149 and shown on Dashboard C53.

Sheet Historical FS
B2: ="Historical Financial Statements - "&'Executive Summary'!B2 -> Historical Financial Statements - Jindal Coke Ltd.
B3: Years | C3: ='Income and Expenditure Summary'!C4 -> FY16A | D3: ='Income and Expenditure Summary'!D4 -> FY17A | E3: ='Income and Expenditure Summary'!E4 -> FY18A | F3: ='Income and Expenditure Summary'!F4 -> FY19A | G3: ='Income and Expenditure Summary'!G4 -> FY20A | H3: ='Income and Expenditure Summary'!H4 -> FY21A | I3: ='Income and Expenditure Summary'!I4 -> FY22A | J3: ='Income and Expenditure Summary'!J4 -> FY23A | ... L3: ='Income and Expenditure Summary'!L4 -> FY25A | M3: Formula Reference
A4: # | B4: Income Statement
B5: Net Sales | C5: =IFERROR(SUM('Income and Expenditure Summary'!C10:C11)-'Income and Expenditure Summary'!C28,0) -> 358.26 | D5: =IFERROR(SUM('Income and Expenditure Summary'!D10:D11)-'Income and Expenditure Summary'!D28,0) -> 656.45 | E5: =IFERROR(SUM('Income and Expenditure Summary'!E10:E11)-'Income and Expenditure Summary'!E28,0) -> 888.16 | F5: =IFERROR(SUM('Income and Expenditure Summary'!F10:F11)-'Income and Expenditure Summary'!F28,0) -> 937.12 | G5: =IFERROR(SUM('Income and Expenditure Summary'!G10:G11)-'Income and Expenditure Summary'!G28,0) -> 761.73 | H5: =IFERROR(SUM('Income and Expenditure Summary'!H10:H11)-'Income and Expenditure Summary'!H28,0) -> 763.42 | I5: =IFERROR(SUM('Income and Expenditure Summary'!I10:I11)-'Income and Expenditure Summary'!I28,0) -> 1242.06 | J5: =IFERROR(SUM('Income and Expenditure Summary'!J10:J11)-'Income and Expenditure Summary'!J28,0) -> 1993.14 | ... L5: =IFERROR(SUM('Income and Expenditure Summary'!L10:L11)-'Income and Expenditure Summary'!L28,0) -> 1871.33 | M5: Net Sales = Industrial Sales + Income from Non-Financial Services - Indirect Taxes
B6: Sales Growth | C6: - | D6: =IFERROR(D5/C5 -1,0) -> 0.83232848 | E6: =IFERROR(E5/D5 -1,0) -> 0.35297433 | F6: =IFERROR(F5/E5 -1,0) -> 0.055125203 | G6: =IFERROR(G5/F5 -1,0) -> -0.18715853 | H6: =IFERROR(H5/G5 -1,0) -> 0.0022186339 | I6: =IFERROR(I5/H5 -1,0) -> 0.62696812 | J6: =IFERROR(J5/I5 -1,0) -> 0.60470509 | K6: =IFERROR(K5/J5 -1,0) -> -0.21089336 | L6: =IFERROR(L5/K5 -1,0) -> 0.18980799 | M6: Sales Growth = (Net Sales / Prior Year Net Sales) - 1
B8: COGS | C8: =IFERROR('Income and Expenditure Summary'!C22-'Income and Expenditure Summary'!C27-'Income and Expenditure Summary'!C28-SUM('Income and Expenditure Summary'!C30:C32,'Income and Expenditure Summary'!C34:C41)-'Income and Expenditure Summary'!C19,0) -> 337.43 | D8: =IFERROR('Income and Expenditure Summary'!D22-'Income and Expenditure Summary'!D27-'Income and Expenditure Summary'!D28-SUM('Income and Expenditure Summary'!D30:D32,'Income and Expenditure Summary'!D34:D41)-'Income and Expenditure Summary'!D19,0) -> 515.51 | E8: =IFERROR('Income and Expenditure Summary'!E22-'Income and Expenditure Summary'!E27-'Income and Expenditure Summary'!E28-SUM('Income and Expenditure Summary'!E30:E32,'Income and Expenditure Summary'!E34:E41)-'Income and Expenditure Summary'!E19,0) -> 682.56 | F8: =IFERROR('Income and Expenditure Summary'!F22-'Income and Expenditure Summary'!F27-'Income and Expenditure Summary'!F28-SUM('Income and Expenditure Summary'!F30:F32,'Income and Expenditure Summary'!F34:F41)-'Income and Expenditure Summary'!F19,0) -> 754.55 | G8: =IFERROR('Income and Expenditure Summary'!G22-'Income and Expenditure Summary'!G27-'Income and Expenditure Summary'!G28-SUM('Income and Expenditure Summary'!G30:G32,'Income and Expenditure Summary'!G34:G41)-'Income and Expenditure Summary'!G19,0) -> 665.53 | H8: =IFERROR('Income and Expenditure Summary'!H22-'Income and Expenditure Summary'!H27-'Income and Expenditure Summary'!H28-SUM('Income and Expenditure Summary'!H30:H32,'Income and Expenditure Summary'!H34:H41)-'Income and Expenditure Summary'!H19,0) -> 569.84 | I8: =IFERROR('Income and Expenditure Summary'!I22-'Income and Expenditure Summary'!I27-'Income and Expenditure Summary'!I28-SUM('Income and Expenditure Summary'!I30:I32,'Income and Expenditure Summary'!I34:I41)-'Income and Expenditure Summary'!I19,0) -> 807 | J8: =IFERROR('Income and Expenditure Summary'!J22-'Income and Expenditure Summary'!J27-'Income and Expenditure Summary'!J28-SUM('Income and Expenditure Summary'!J30:J32,'Income and Expenditure Summary'!J34:J41)-'Income and Expenditure Summary'!J19,0) -> 1670.8 | ... L8: =IFERROR('Income and Expenditure Summary'!L22-'Income and Expenditure Summary'!L27-'Income and Expenditure Summary'!L28-SUM('Income and Expenditure Summary'!L30:L32,'Income and Expenditure Summary'!L34:L41)-'Income and Expenditure Summary'!L19,0) -> 1575.49 | M8: COGS = Total Operating Expenses - Employee Benefit - Indirect Taxes - SG&A Items - Change in Stock
B9: COGS % Sales | C9: =IFERROR(C8/C5,0) -> 0.94185787 | D9: =IFERROR(D8/D5,0) -> 0.78529972 | E9: =IFERROR(E8/E5,0) -> 0.76851018 | F9: =IFERROR(F8/F5,0) -> 0.8051797 | G9: =IFERROR(G8/G5,0) -> 0.87370853 | H9: =IFERROR(H8/H5,0) -> 0.74643054 | I9: =IFERROR(I8/I5,0) -> 0.64972707 | J9: =IFERROR(J8/J5,0) -> 0.83827528 | ... L9: =IFERROR(L8/L5,0) -> 0.84190923 | M9: COGS % Sales = COGS / Net Sales
B11: Gross Profit | C11: =IFERROR(C5-C8,0) -> 20.83 | D11: =IFERROR(D5-D8,0) -> 140.94 | E11: =IFERROR(E5-E8,0) -> 205.6 | F11: =IFERROR(F5-F8,0) -> 182.57 | G11: =IFERROR(G5-G8,0) -> 96.2 | H11: =IFERROR(H5-H8,0) -> 193.58 | I11: =IFERROR(I5-I8,0) -> 435.06 | J11: =IFERROR(J5-J8,0) -> 322.34 | ... L11: =IFERROR(L5-L8,0) -> 295.84 | M11: Gross Profit = Net Sales - COGS
B12: Gross Profit Margin | C12: =IFERROR(C11/C5,0) -> 0.058142131 | D12: =IFERROR(D11/D5,0) -> 0.21470028 | E12: =IFERROR(E11/E5,0) -> 0.23148982 | F12: =IFERROR(F11/F5,0) -> 0.1948203 | G12: =IFERROR(G11/G5,0) -> 0.12629147 | H12: =IFERROR(H11/H5,0) -> 0.25356946 | I12: =IFERROR(I11/I5,0) -> 0.35027293 | J12: =IFERROR(J11/J5,0) -> 0.16172472 | ... L12: =IFERROR(L11/L5,0) -> 0.15809077 | M12: Gross Profit Margin = Gross Profit / Net Sales
B14: Employee Benefit Expenses | C14: =IFERROR('Income and Expenditure Summary'!C27,0) -> 7.13 | D14: =IFERROR('Income and Expenditure Summary'!D27,0) -> 9.43 | E14: =IFERROR('Income and Expenditure Summary'!E27,0) -> 8.19 | F14: =IFERROR('Income and Expenditure Summary'!F27,0) -> 9.75 | G14: =IFERROR('Income and Expenditure Summary'!G27,0) -> 10.08 | H14: =IFERROR('Income and Expenditure Summary'!H27,0) -> 10.28 | I14: =IFERROR('Income and Expenditure Summary'!I27,0) -> 12.84 | J14: =IFERROR('Income and Expenditure Summary'!J27,0) -> 12.16 | ... L14: =IFERROR('Income and Expenditure Summary'!L27,0) -> 17.85 | M14: Employee Benefit Expenses = Sourced from I&E Summary (Compensation to Employees)
B15: Employee Benefit Exp % Sales | C15: =IFERROR(C14/C5,0) -> 0.019901747 | D15: =IFERROR(D14/D5,0) -> 0.014365146 | E15: =IFERROR(E14/E5,0) -> 0.0092213115 | F15: =IFERROR(F14/F5,0) -> 0.010404217 | G15: =IFERROR(G14/G5,0) -> 0.013233035 | H15: =IFERROR(H14/H5,0) -> 0.01346572 | I15: =IFERROR(I14/I5,0) -> 0.010337665 | J15: =IFERROR(J14/J5,0) -> 0.0061009262 | ... L15: =IFERROR(L14/L5,0) -> 0.0095386704 | M15: Employee Benefit Exp % Sales = Employee Benefit Expenses / Net Sales
B17: Selling, General & Admin Expenses | C17: =IFERROR(SUM('Income and Expenditure Summary'!C29:C32,'Income and Expenditure Summary'!C34:C41),0) -> 18.86 | D17: =IFERROR(SUM('Income and Expenditure Summary'!D29:D32,'Income and Expenditure Summary'!D34:D41),0) -> 21.88 | E17: =IFERROR(SUM('Income and Expenditure Summary'!E29:E32,'Income and Expenditure Summary'!E34:E41),0) -> 34.41 | F17: =IFERROR(SUM('Income and Expenditure Summary'!F29:F32,'Income and Expenditure Summary'!F34:F41),0) -> 41.49 | G17: =IFERROR(SUM('Income and Expenditure Summary'!G29:G32,'Income and Expenditure Summary'!G34:G41),0) -> 35.32 | H17: =IFERROR(SUM('Income and Expenditure Summary'!H29:H32,'Income and Expenditure Summary'!H34:H41),0) -> 35.71 | I17: =IFERROR(SUM('Income and Expenditure Summary'!I29:I32,'Income and Expenditure Summary'!I34:I41),0) -> 45.81 | J17: =IFERROR(SUM('Income and Expenditure Summary'!J29:J32,'Income and Expenditure Summary'!J34:J41),0) -> 50.25 | ... L17: =IFERROR(SUM('Income and Expenditure Summary'!L29:L32,'Income and Expenditure Summary'!L34:L41),0) -> 77.55 | M17: SG&A Expenses = Rent + Repairs + Insurance + Professional Fees + Directors Fees + Selling & Distribution + Travel + Communications + Miscellaneous + Other Operational
B18: S,G&A % Sales | C18: =IFERROR(C17/C5,0) -> 0.052643332 | D18: =IFERROR(D17/D5,0) -> 0.033330794 | E18: =IFERROR(E17/E5,0) -> 0.038743019 | F18: =IFERROR(F17/F5,0) -> 0.044273946 | G18: =IFERROR(G17/G5,0) -> 0.046368136 | H18: =IFERROR(H17/H5,0) -> 0.046776349 | I18: =IFERROR(I17/I5,0) -> 0.036882276 | J18: =IFERROR(J17/J5,0) -> 0.025211475 | ... L18: =IFERROR(L17/L5,0) -> 0.041441114 | M18: SG&A % Sales = SG&A Expenses / Net Sales
B20: EBITDA | C20: =IFERROR(C11-C14-C17,0) -> -5.16 | D20: =IFERROR(D11-D14-D17,0) -> 109.63 | E20: =IFERROR(E11-E14-E17,0) -> 163 | F20: =IFERROR(F11-F14-F17,0) -> 131.33 | G20: =IFERROR(G11-G14-G17,0) -> 50.8 | H20: =IFERROR(H11-H14-H17,0) -> 147.59 | I20: =IFERROR(I11-I14-I17,0) -> 376.41 | J20: =IFERROR(J11-J14-J17,0) -> 259.93 | ... L20: =IFERROR(L11-L14-L17,0) -> 200.44 | M20: EBITDA = Gross Profit - Employee Benefit Expenses - SG&A Expenses
B21: EBITDA Margin | C21: =IFERROR(C20/C5,0) -> -0.014402948 | D21: =IFERROR(D20/D5,0) -> 0.16700434 | E21: =IFERROR(E20/E5,0) -> 0.18352549 | F21: =IFERROR(F20/F5,0) -> 0.14014214 | G21: =IFERROR(G20/G5,0) -> 0.066690297 | H21: =IFERROR(H20/H5,0) -> 0.1933274 | I21: =IFERROR(I20/I5,0) -> 0.30305299 | J21: =IFERROR(J20/J5,0) -> 0.13041231 | ... L21: =IFERROR(L20/L5,0) -> 0.10711099 | M21: EBITDA Margin = EBITDA / Net Sales
B23: Depreciation | C23: =IFERROR('Income and Expenditure Summary'!C47,0) -> 29.11 | D23: =IFERROR('Income and Expenditure Summary'!D47,0) -> 29.34 | E23: =IFERROR('Income and Expenditure Summary'!E47,0) -> 27.29 | F23: =IFERROR('Income and Expenditure Summary'!F47,0) -> 17.23 | G23: =IFERROR('Income and Expenditure Summary'!G47,0) -> 17.96 | H23: =IFERROR('Income and Expenditure Summary'!H47,0) -> 19.99 | I23: =IFERROR('Income and Expenditure Summary'!I47,0) -> 21.21 | J23: =IFERROR('Income and Expenditure Summary'!J47,0) -> 21.45 | ... L23: =IFERROR('Income and Expenditure Summary'!L47,0) -> 30.98 | M23: Depreciation = Sourced from I&E Summary (Depreciation under Non-Cash Charges)
B24: Depreciation % Sales | C24: =IFERROR(C23/C5,0) -> 0.081253838 | D24: =IFERROR(D23/D5,0) -> 0.04469495 | E24: =IFERROR(E23/E5,0) -> 0.030726446 | F24: =IFERROR(F23/F5,0) -> 0.018386119 | G24: =IFERROR(G23/G5,0) -> 0.023577908 | H24: =IFERROR(H23/H5,0) -> 0.0261848 | I24: =IFERROR(I23/I5,0) -> 0.01707647 | J24: =IFERROR(J23/J5,0) -> 0.010761913 | ... L24: =IFERROR(L23/L5,0) -> 0.01655507 | M24: Depreciation % Sales = Depreciation / Net Sales
B26: EBIT | C26: =IFERROR(C20-C23,0) -> -34.27 | D26: =IFERROR(D20-D23,0) -> 80.29 | E26: =IFERROR(E20-E23,0) -> 135.71 | F26: =IFERROR(F20-F23,0) -> 114.1 | G26: =IFERROR(G20-G23,0) -> 32.84 | H26: =IFERROR(H20-H23,0) -> 127.6 | I26: =IFERROR(I20-I23,0) -> 355.2 | J26: =IFERROR(J20-J23,0) -> 238.48 | ... L26: =IFERROR(L20-L23,0) -> 169.46 | M26: EBIT = EBITDA - Depreciation
B27: EBIT Margin | C27: =IFERROR(C26/C5,0) -> -0.095656786 | D27: =IFERROR(D26/D5,0) -> 0.12230939 | E27: =IFERROR(E26/E5,0) -> 0.15279905 | F27: =IFERROR(F26/F5,0) -> 0.12175602 | G27: =IFERROR(G26/G5,0) -> 0.043112389 | H27: =IFERROR(H26/H5,0) -> 0.1671426 | I27: =IFERROR(I26/I5,0) -> 0.28597652 | J27: =IFERROR(J26/J5,0) -> 0.1196504 | ... L27: =IFERROR(L26/L5,0) -> 0.090555915 | M27: EBIT Margin = EBIT / Net Sales
B29: Finance Costs | C29: =IFERROR(SUM('Income and Expenditure Summary'!C45:C46),0) -> 9.31 | D29: =IFERROR(SUM('Income and Expenditure Summary'!D45:D46),0) -> 53.01 | E29: =IFERROR(SUM('Income and Expenditure Summary'!E45:E46),0) -> 59.95 | F29: =IFERROR(SUM('Income and Expenditure Summary'!F45:F46),0) -> 55.18 | G29: =IFERROR(SUM('Income and Expenditure Summary'!G45:G46),0) -> 51.75 | H29: =IFERROR(SUM('Income and Expenditure Summary'!H45:H46),0) -> 50.96 | I29: =IFERROR(SUM('Income and Expenditure Summary'!I45:I46),0) -> 34.91 | J29: =IFERROR(SUM('Income and Expenditure Summary'!J45:J46),0) -> 33.2 | ... L29: =IFERROR(SUM('Income and Expenditure Summary'!L45:L46),0) -> 33.51 | M29: Finance Costs = Fee Based Financial Services Expenses + Fund Based Financial Services Expenses
B30: Finance Costs % Sales | C30: =IFERROR(C29/C5,0) -> 0.025986714 | D30: =IFERROR(D29/D5,0) -> 0.080752533 | E30: =IFERROR(E29/E5,0) -> 0.067499099 | F30: =IFERROR(F29/F5,0) -> 0.058882534 | G30: =IFERROR(G29/G5,0) -> 0.067937458 | H30: =IFERROR(H29/H5,0) -> 0.066752246 | I30: =IFERROR(I29/I5,0) -> 0.028106533 | J30: =IFERROR(J29/J5,0) -> 0.016657134 | ... L30: =IFERROR(L29/L5,0) -> 0.01790705 | M30: Finance Costs % Sales = Finance Costs / Net Sales
B32: Other income | C32: =IFERROR('Income and Expenditure Summary'!C12+'Income and Expenditure Summary'!C16,0) -> 0 | D32: =IFERROR('Income and Expenditure Summary'!D12+'Income and Expenditure Summary'!D16,0) -> 8.62 | E32: =IFERROR('Income and Expenditure Summary'!E12+'Income and Expenditure Summary'!E16,0) -> 6.08 | F32: =IFERROR('Income and Expenditure Summary'!F12+'Income and Expenditure Summary'!F16,0) -> 5.47 | G32: =IFERROR('Income and Expenditure Summary'!G12+'Income and Expenditure Summary'!G16,0) -> 5.01 | H32: =IFERROR('Income and Expenditure Summary'!H12+'Income and Expenditure Summary'!H16,0) -> 3.37 | I32: =IFERROR('Income and Expenditure Summary'!I12+'Income and Expenditure Summary'!I16,0) -> 4.98 | J32: =IFERROR('Income and Expenditure Summary'!J12+'Income and Expenditure Summary'!J16,0) -> 14.3 | ... L32: =IFERROR('Income and Expenditure Summary'!L12+'Income and Expenditure Summary'!L16,0) -> 18.7 | M32: Other Income = Income from Financial Services + Other Income
B33: Other Income % Sales | C33: =IFERROR(C32/C5,0) -> 0 | D33: =IFERROR(D32/D5,0) -> 0.013131236 | E33: =IFERROR(E32/E5,0) -> 0.0068456134 | F33: =IFERROR(F32/F5,0) -> 0.0058370326 | G33: =IFERROR(G32/G5,0) -> 0.0065771336 | H33: =IFERROR(H32/H5,0) -> 0.004414346 | I33: =IFERROR(I32/I5,0) -> 0.0040094681 | J33: =IFERROR(J32/J5,0) -> 0.0071746089 | ... L33: =IFERROR(L32/L5,0) -> 0.0099928928 | M33: Other Income % Sales = Other Income / Net Sales
B35: Net Extraordinary Items | C35: =IFERROR('Income and Expenditure Summary'!C17-'Income and Expenditure Summary'!C53,0) -> -5.46 | D35: =IFERROR('Income and Expenditure Summary'!D17-'Income and Expenditure Summary'!D53,0) -> 1.13 | E35: =IFERROR('Income and Expenditure Summary'!E17-'Income and Expenditure Summary'!E53,0) -> 1.56 | F35: =IFERROR('Income and Expenditure Summary'!F17-'Income and Expenditure Summary'!F53,0) -> 0.1 | G35: =IFERROR('Income and Expenditure Summary'!G17-'Income and Expenditure Summary'!G53,0) -> 0.2 | H35: =IFERROR('Income and Expenditure Summary'!H17-'Income and Expenditure Summary'!H53,0) -> 2.95 | I35: =IFERROR('Income and Expenditure Summary'!I17-'Income and Expenditure Summary'!I53,0) -> 3.95 | J35: =IFERROR('Income and Expenditure Summary'!J17-'Income and Expenditure Summary'!J53,0) -> 0 | ... L35: =IFERROR('Income and Expenditure Summary'!L17-'Income and Expenditure Summary'!L53,0) -> 0 | M35: Net Extraordinary Items = Prior Period & Extraordinary Income - Prior Period & Extraordinary Expenses
B37: Profit Before Tax | C37: =IFERROR(SUM(C26,C32,C35)-C29,0) -> -49.04 | D37: =IFERROR(SUM(D26,D32,D35)-D29,0) -> 37.03 | E37: =IFERROR(SUM(E26,E32,E35)-E29,0) -> 83.4 | F37: =IFERROR(SUM(F26,F32,F35)-F29,0) -> 64.49 | G37: =IFERROR(SUM(G26,G32,G35)-G29,0) -> -13.7 | H37: =IFERROR(SUM(H26,H32,H35)-H29,0) -> 82.96 | I37: =IFERROR(SUM(I26,I32,I35)-I29,0) -> 329.22 | J37: =IFERROR(SUM(J26,J32,J35)-J29,0) -> 219.58 | ... L37: =IFERROR(SUM(L26,L32,L35)-L29,0) -> 154.65 | M37: Profit Before Tax = EBIT + Other Income + Net Extraordinary Items - Finance Costs
B38: PBT % Sales | C38: =IFERROR(C37/C5,0) -> -0.13688383 | D38: =IFERROR(D37/D5,0) -> 0.056409475 | E38: =IFERROR(E37/E5,0) -> 0.093902 | F38: =IFERROR(F37/F5,0) -> 0.068817227 | G38: =IFERROR(G37/G5,0) -> -0.017985375 | H38: =IFERROR(H37/H5,0) -> 0.10866888 | I38: =IFERROR(I37/I5,0) -> 0.26505966 | J38: =IFERROR(J37/J5,0) -> 0.11016788 | ... L38: =IFERROR(L37/L5,0) -> 0.082641757 | M38: PBT % Sales = Profit Before Tax / Net Sales
B40: Provision for Direct Tax | C40: =IFERROR('Income and Expenditure Summary'!C55,0) -> -16.97 | D40: =IFERROR('Income and Expenditure Summary'!D55,0) -> 12.86 | E40: =IFERROR('Income and Expenditure Summary'!E55,0) -> 26.23 | F40: =IFERROR('Income and Expenditure Summary'!F55,0) -> 24.38 | G40: =IFERROR('Income and Expenditure Summary'!G55,0) -> -1.95 | H40: =IFERROR('Income and Expenditure Summary'!H55,0) -> 25.1 | I40: =IFERROR('Income and Expenditure Summary'!I55,0) -> 90.41 | J40: =IFERROR('Income and Expenditure Summary'!J55,0) -> 54.6 | ... L40: =IFERROR('Income and Expenditure Summary'!L55,0) -> 40.05 | M40: Provision for Direct Tax = Sourced from I&E Summary (Provision for Direct Tax)
B42: Profit After Tax | C42: =IFERROR(C37-C40,0) -> -32.07 | D42: =IFERROR(D37-D40,0) -> 24.17 | E42: =IFERROR(E37-E40,0) -> 57.17 | F42: =IFERROR(F37-F40,0) -> 40.11 | G42: =IFERROR(G37-G40,0) -> -11.75 | H42: =IFERROR(H37-H40,0) -> 57.86 | I42: =IFERROR(I37-I40,0) -> 238.81 | J42: =IFERROR(J37-J40,0) -> 164.98 | ... L42: =IFERROR(L37-L40,0) -> 114.6 | M42: Profit After Tax = Profit Before Tax - Provision for Direct Tax
B43: Net Income Margin | C43: =IFERROR(C42/C5,0) -> -0.089515994 | D43: =IFERROR(D42/D5,0) -> 0.036819255 | E43: =IFERROR(E42/E5,0) -> 0.064369033 | F43: =IFERROR(F42/F5,0) -> 0.042801349 | G43: =IFERROR(G42/G5,0) -> -0.015425413 | H43: =IFERROR(H42/H5,0) -> 0.075790522 | I43: =IFERROR(I42/I5,0) -> 0.19226929 | J43: =IFERROR(J42/J5,0) -> 0.082773915 | ... L43: =IFERROR(L42/L5,0) -> 0.061239867 | M43: Net Income Margin = Profit After Tax / Net Sales
B45: Check: PAT (HFS vs I&E) | C45: =IF(ROUND(C42-'Income and Expenditure Summary'!C57,2)=0,"✓ Match","✗ Diff: "&TEXT(ROUND(C42-'Income and Expenditure Summary'!C57,2),"0.00")) -> ✓ Match | D45: =IF(ROUND(D42-'Income and Expenditure Summary'!D57,2)=0,"✓ Match","✗ Diff: "&TEXT(ROUND(D42-'Income and Expenditure Summary'!D57,2),"0.00")) -> ✓ Match | E45: =IF(ROUND(E42-'Income and Expenditure Summary'!E57,2)=0,"✓ Match","✗ Diff: "&TEXT(ROUND(E42-'Income and Expenditure Summary'!E57,2),"0.00")) -> ✓ Match | F45: =IF(ROUND(F42-'Income and Expenditure Summary'!F57,2)=0,"✓ Match","✗ Diff: "&TEXT(ROUND(F42-'Income and Expenditure Summary'!F57,2),"0.00")) -> ✓ Match | G45: =IF(ROUND(G42-'Income and Expenditure Summary'!G57,2)=0,"✓ Match","✗ Diff: "&TEXT(ROUND(G42-'Income and Expenditure Summary'!G57,2),"0.00")) -> ✓ Match | H45: =IF(ROUND(H42-'Income and Expenditure Summary'!H57,2)=0,"✓ Match","✗ Diff: "&TEXT(ROUND(H42-'Income and Expenditure Summary'!H57,2),"0.00")) -> ✓ Match | I45: =IF(ROUND(I42-'Income and Expenditure Summary'!I57,2)=0,"✓ Match","✗ Diff: "&TEXT(ROUND(I42-'Income and Expenditure Summary'!I57,2),"0.00")) -> ✓ Match | J45: =IF(ROUND(J42-'Income and Expenditure Summary'!J57,2)=0,"✓ Match","✗ Diff: "&TEXT(ROUND(J42-'Income and Expenditure Summary'!J57,2),"0.00")) -> ✓ Match | K45: =IF(ROUND(K42-'Income and Expenditure Summary'!K57,2)=0,"✓ Match","✗ Diff: "&TEXT(ROUND(K42-'Income and Expenditure Summary'!K57,2),"0.00")) -> ✓ Match | L45: =IF(ROUND(L42-'Income and Expenditure Summary'!L57,2)<=0.01,"✓ Match","✗ Diff: "&TEXT(ROUND(L42-'Income and Expenditure Summary'!L57,2),"0.00")) -> ✓ Match
A47: # | B47: Balance Sheet
B49: Equity & Liabilities
B51: Equity
B53: Share Capital | C53: =IFERROR('Balance Sheet Summary'!C10,0) -> 91.7 | D53: =IFERROR('Balance Sheet Summary'!D10,0) -> 141.7 | E53: =IFERROR('Balance Sheet Summary'!E10,0) -> 141.7 | F53: =IFERROR('Balance Sheet Summary'!F10,0) -> 141.7 | G53: =IFERROR('Balance Sheet Summary'!G10,0) -> 141.7 | H53: =IFERROR('Balance Sheet Summary'!H10,0) -> 141.69 | I53: =IFERROR('Balance Sheet Summary'!I10,0) -> 141.69 | J53: =IFERROR('Balance Sheet Summary'!J10,0) -> 141.69 | ... L53: =IFERROR('Balance Sheet Summary'!L10,0) -> 134.85
B54: Reserves & Surplus | C54: =IFERROR('Balance Sheet Summary'!C16,0) -> -6.11 | D54: =IFERROR('Balance Sheet Summary'!D16,0) -> -9.12 | E54: =IFERROR('Balance Sheet Summary'!E16,0) -> 110.03 | F54: =IFERROR('Balance Sheet Summary'!F16,0) -> 150.16 | G54: =IFERROR('Balance Sheet Summary'!G16,0) -> 138.35 | H54: =IFERROR('Balance Sheet Summary'!H16,0) -> 196.19 | I54: =IFERROR('Balance Sheet Summary'!I16,0) -> 434.96 | J54: =IFERROR('Balance Sheet Summary'!J16,0) -> 599.87 | ... L54: =IFERROR('Balance Sheet Summary'!L16,0) -> 662.75
B56: Total Equity | C56: =IFERROR(C53+C54,0) -> 85.59 | D56: =IFERROR(D53+D54,0) -> 132.58 | E56: =IFERROR(E53+E54,0) -> 251.73 | F56: =IFERROR(F53+F54,0) -> 291.86 | G56: =IFERROR(G53+G54,0) -> 280.05 | H56: =IFERROR(H53+H54,0) -> 337.88 | I56: =IFERROR(I53+I54,0) -> 576.65 | J56: =IFERROR(J53+J54,0) -> 741.56 | ... L56: =IFERROR(L53+L54,0) -> 797.6 | M56: Share Capital + Reserves and Surplus
B58: Non-Current Liabilities
B60: LT Borrowings (excl. current portion) | C60: =IFERROR('Balance Sheet Summary'!C26,0) -> 0 | D60: =IFERROR('Balance Sheet Summary'!D26,0) -> 488.17 | E60: =IFERROR('Balance Sheet Summary'!E26,0) -> 495.52 | F60: =IFERROR('Balance Sheet Summary'!F26,0) -> 408.05 | G60: =IFERROR('Balance Sheet Summary'!G26,0) -> 391.51 | H60: =IFERROR('Balance Sheet Summary'!H26,0) -> 387.8 | I60: =IFERROR('Balance Sheet Summary'!I26,0) -> 502.23 | J60: =IFERROR('Balance Sheet Summary'!J26,0) -> 324.03 | ... L60: =IFERROR('Balance Sheet Summary'!L26,0) -> 279.58
B61: Deferred Tax Liability | C61: =IFERROR('Balance Sheet Summary'!C35,0) -> 0 | D61: =IFERROR('Balance Sheet Summary'!D35,0) -> 0 | E61: =IFERROR('Balance Sheet Summary'!E35,0) -> 33.78 | F61: =IFERROR('Balance Sheet Summary'!F35,0) -> 44.17 | G61: =IFERROR('Balance Sheet Summary'!G35,0) -> 42.19 | H61: =IFERROR('Balance Sheet Summary'!H35,0) -> 53.07 | I61: =IFERROR('Balance Sheet Summary'!I35,0) -> 64.12 | J61: =IFERROR('Balance Sheet Summary'!J35,0) -> 66.09 | ... L61: =IFERROR('Balance Sheet Summary'!L35,0) -> 72.9
B62: Long-term Provisions | C62: =IFERROR('Balance Sheet Summary'!C37,0) -> 0.35 | D62: =IFERROR('Balance Sheet Summary'!D37,0) -> 0.69 | E62: =IFERROR('Balance Sheet Summary'!E37,0) -> 0.97 | F62: =IFERROR('Balance Sheet Summary'!F37,0) -> 1.05 | G62: =IFERROR('Balance Sheet Summary'!G37,0) -> 1.35 | H62: =IFERROR('Balance Sheet Summary'!H37,0) -> 1.44 | I62: =IFERROR('Balance Sheet Summary'!I37,0) -> 1.72 | J62: =IFERROR('Balance Sheet Summary'!J37,0) -> 1.82 | ... L62: =IFERROR('Balance Sheet Summary'!L37,0) -> 2.55
B63: Total Non-Current Liabilities | C63: =IFERROR(C60+C61+C62,0) -> 0.35 | D63: =IFERROR(D60+D61+D62,0) -> 488.86 | E63: =IFERROR(E60+E61+E62,0) -> 530.27 | F63: =IFERROR(F60+F61+F62,0) -> 453.27 | G63: =IFERROR(G60+G61+G62,0) -> 435.05 | H63: =IFERROR(H60+H61+H62,0) -> 442.31 | I63: =IFERROR(I60+I61+I62,0) -> 568.07 | J63: =IFERROR(J60+J61+J62,0) -> 391.94 | ... L63: =IFERROR(L60+L61+L62,0) -> 355.03 | M63: LT Borrowings + Deferred Tax Liability + LT Provisions
B65: Current Liabilities
B67: Short-term Borrowings | C67: =IFERROR('Balance Sheet Summary'!C40,0) -> 4.01 | D67: =IFERROR('Balance Sheet Summary'!D40,0) -> 81.78 | E67: =IFERROR('Balance Sheet Summary'!E40,0) -> 0 | F67: =IFERROR('Balance Sheet Summary'!F40,0) -> 0 | G67: =IFERROR('Balance Sheet Summary'!G40,0) -> 0 | H67: =IFERROR('Balance Sheet Summary'!H40,0) -> 0 | I67: =IFERROR('Balance Sheet Summary'!I40,0) -> 4.28 | J67: =IFERROR('Balance Sheet Summary'!J40,0) -> 33.65 | ... L67: =IFERROR('Balance Sheet Summary'!L40,0) -> 109
B68: Trade Payables & Acceptances | C68: =IFERROR('Balance Sheet Summary'!C41,0) -> 132.43 | D68: =IFERROR('Balance Sheet Summary'!D41,0) -> 236.51 | E68: =IFERROR('Balance Sheet Summary'!E41,0) -> 49.75 | F68: =IFERROR('Balance Sheet Summary'!F41,0) -> 65.16 | G68: =IFERROR('Balance Sheet Summary'!G41,0) -> 75.96 | H68: =IFERROR('Balance Sheet Summary'!H41,0) -> 10.81 | I68: =IFERROR('Balance Sheet Summary'!I41,0) -> 357.53 | J68: =IFERROR('Balance Sheet Summary'!J41,0) -> 298.68 | ... L68: =IFERROR('Balance Sheet Summary'!L41,0) -> 369.13
B69: Other Current Liabilities | C69: =IFERROR('Balance Sheet Summary'!C39-'Balance Sheet Summary'!C40-'Balance Sheet Summary'!C41,0) -> 389.64 | D69: =IFERROR('Balance Sheet Summary'!D39-'Balance Sheet Summary'!D40-'Balance Sheet Summary'!D41,0) -> 13.08 | E69: =IFERROR('Balance Sheet Summary'!E39-'Balance Sheet Summary'!E40-'Balance Sheet Summary'!E41,0) -> 19.38 | F69: =IFERROR('Balance Sheet Summary'!F39-'Balance Sheet Summary'!F40-'Balance Sheet Summary'!F41,0) -> 42.98 | G69: =IFERROR('Balance Sheet Summary'!G39-'Balance Sheet Summary'!G40-'Balance Sheet Summary'!G41,0) -> 32.58 | H69: =IFERROR('Balance Sheet Summary'!H39-'Balance Sheet Summary'!H40-'Balance Sheet Summary'!H41,0) -> 36.35 | I69: =IFERROR('Balance Sheet Summary'!I39-'Balance Sheet Summary'!I40-'Balance Sheet Summary'!I41,0) -> 109.02 | J69: =IFERROR('Balance Sheet Summary'!J39-'Balance Sheet Summary'!J40-'Balance Sheet Summary'!J41,0) -> 25.22 | ... L69: =IFERROR('Balance Sheet Summary'!L39-'Balance Sheet Summary'!L40-'Balance Sheet Summary'!L41,0) -> 246.71 | M69: From Balance Sheet Summary: Total CL (row 39) minus ST Borrowings minus Trade Payables
B70: Total Current Liabilities | C70: =IFERROR(C67+C68+C69,0) -> 526.08 | D70: =IFERROR(D67+D68+D69,0) -> 331.37 | E70: =IFERROR(E67+E68+E69,0) -> 69.13 | F70: =IFERROR(F67+F68+F69,0) -> 108.14 | G70: =IFERROR(G67+G68+G69,0) -> 108.54 | H70: =IFERROR(H67+H68+H69,0) -> 47.16 | I70: =IFERROR(I67+I68+I69,0) -> 470.83 | J70: =IFERROR(J67+J68+J69,0) -> 357.55 | ... L70: =IFERROR(L67+L68+L69,0) -> 724.84 | M70: ST Borrowings + Trade Payables + Other Current Liabilities
B72: Total Liabilities | C72: =IFERROR(C63+C70,0) -> 526.43 | D72: =IFERROR(D63+D70,0) -> 820.23 | E72: =IFERROR(E63+E70,0) -> 599.4 | F72: =IFERROR(F63+F70,0) -> 561.41 | G72: =IFERROR(G63+G70,0) -> 543.59 | H72: =IFERROR(H63+H70,0) -> 489.47 | I72: =IFERROR(I63+I70,0) -> 1038.9 | J72: =IFERROR(J63+J70,0) -> 749.49 | ... L72: =IFERROR(L63+L70,0) -> 1079.87 | M72: Total Non-Current Liabilities + Total Current Liabilities
B74: Total Equity + Liabilities | C74: =IFERROR(C56+C63+C70,0) -> 612.02 | D74: =IFERROR(D56+D63+D70,0) -> 952.81 | E74: =IFERROR(E56+E63+E70,0) -> 851.13 | F74: =IFERROR(F56+F63+F70,0) -> 853.27 | G74: =IFERROR(G56+G63+G70,0) -> 823.64 | H74: =IFERROR(H56+H63+H70,0) -> 827.35 | I74: =IFERROR(I56+I63+I70,0) -> 1615.55 | J74: =IFERROR(J56+J63+J70,0) -> 1491.05 | ... L74: =IFERROR(L56+L63+L70,0) -> 1877.47 | M74: Total Equity + Total Non-Current Liabilities + Total Current Liabilities
B76: Assets
B78: Non-Current Assets
B80: Net Fixed Assets | C80: =IFERROR('Balance Sheet Summary'!C45,0) -> 459.69 | D80: =IFERROR('Balance Sheet Summary'!D45,0) -> 433.4 | E80: =IFERROR('Balance Sheet Summary'!E45,0) -> 504.27 | F80: =IFERROR('Balance Sheet Summary'!F45,0) -> 487.08 | G80: =IFERROR('Balance Sheet Summary'!G45,0) -> 500.49 | H80: =IFERROR('Balance Sheet Summary'!H45,0) -> 494.03 | I80: =IFERROR('Balance Sheet Summary'!I45,0) -> 493.2 | J80: =IFERROR('Balance Sheet Summary'!J45,0) -> 473.46 | ... L80: =IFERROR('Balance Sheet Summary'!L45,0) -> 787.43
B81: Capital Work-in-Progress | C81: =IFERROR('Balance Sheet Summary'!C50,0) -> 6.71 | D81: =IFERROR('Balance Sheet Summary'!D50,0) -> 3.03 | E81: =IFERROR('Balance Sheet Summary'!E50,0) -> 0 | F81: =IFERROR('Balance Sheet Summary'!F50,0) -> 16.65 | G81: =IFERROR('Balance Sheet Summary'!G50,0) -> 0.69 | H81: =IFERROR('Balance Sheet Summary'!H50,0) -> 0.17 | I81: =IFERROR('Balance Sheet Summary'!I50,0) -> 1.62 | J81: =IFERROR('Balance Sheet Summary'!J50,0) -> 159 | ... L81: =IFERROR('Balance Sheet Summary'!L50,0) -> 178.59
B82: Long-term Investments | C82: =IFERROR('Balance Sheet Summary'!C53,0) -> 0 | D82: =IFERROR('Balance Sheet Summary'!D53,0) -> 0.05 | E82: =IFERROR('Balance Sheet Summary'!E53,0) -> 0.06 | F82: =IFERROR('Balance Sheet Summary'!F53,0) -> 0.03 | G82: =IFERROR('Balance Sheet Summary'!G53,0) -> 0.02 | H82: =IFERROR('Balance Sheet Summary'!H53,0) -> 0.05 | I82: =IFERROR('Balance Sheet Summary'!I53,0) -> 0.14 | J82: =IFERROR('Balance Sheet Summary'!J53,0) -> 0.25 | ... L82: =IFERROR('Balance Sheet Summary'!L53,0) -> 0.45
B83: Long-term Loans & Advances | C83: =IFERROR('Balance Sheet Summary'!C57,0) -> 0 | D83: =IFERROR('Balance Sheet Summary'!D57,0) -> 7.75 | E83: =IFERROR('Balance Sheet Summary'!E57,0) -> 0 | F83: =IFERROR('Balance Sheet Summary'!F57,0) -> 0 | G83: =IFERROR('Balance Sheet Summary'!G57,0) -> 0 | H83: =IFERROR('Balance Sheet Summary'!H57,0) -> 0 | I83: =IFERROR('Balance Sheet Summary'!I57,0) -> 119.06 | J83: =IFERROR('Balance Sheet Summary'!J57,0) -> 449.18 | ... L83: =IFERROR('Balance Sheet Summary'!L57,0) -> 28.15
B84: Other Long-term Assets (incl. DTA) | C84: =IFERROR('Balance Sheet Summary'!C58+'Balance Sheet Summary'!C59,0) -> 16.98 | D84: =IFERROR('Balance Sheet Summary'!D58+'Balance Sheet Summary'!D59,0) -> 121.73 | E84: =IFERROR('Balance Sheet Summary'!E58+'Balance Sheet Summary'!E59,0) -> 116.3 | F84: =IFERROR('Balance Sheet Summary'!F58+'Balance Sheet Summary'!F59,0) -> 112.44 | G84: =IFERROR('Balance Sheet Summary'!G58+'Balance Sheet Summary'!G59,0) -> 109.34 | H84: =IFERROR('Balance Sheet Summary'!H58+'Balance Sheet Summary'!H59,0) -> 105.25 | I84: =IFERROR('Balance Sheet Summary'!I58+'Balance Sheet Summary'!I59,0) -> 6.23 | J84: =IFERROR('Balance Sheet Summary'!J58+'Balance Sheet Summary'!J59,0) -> 2.36 | ... L84: =IFERROR('Balance Sheet Summary'!L58+'Balance Sheet Summary'!L59,0) -> 146.98 | M84: From Balance Sheet Summary: DTA (row 58) + Other LT Assets (row 59)
B85: Total Non-Current Assets | C85: =IFERROR(C80+C81+C82+C83+C84,0) -> 483.38 | D85: =IFERROR(D80+D81+D82+D83+D84,0) -> 565.96 | E85: =IFERROR(E80+E81+E82+E83+E84,0) -> 620.63 | F85: =IFERROR(F80+F81+F82+F83+F84,0) -> 616.2 | G85: =IFERROR(G80+G81+G82+G83+G84,0) -> 610.54 | H85: =IFERROR(H80+H81+H82+H83+H84,0) -> 599.5 | I85: =IFERROR(I80+I81+I82+I83+I84,0) -> 620.25 | J85: =IFERROR(J80+J81+J82+J83+J84,0) -> 1084.25 | ... L85: =IFERROR(L80+L81+L82+L83+L84,0) -> 1141.6 | M85: Net Fixed Assets + CWIP + LT Investments + LT Loans + Other LT Assets
B87: Current Assets
B89: Inventories | C89: =IFERROR('Balance Sheet Summary'!C62,0) -> 104.7 | D89: =IFERROR('Balance Sheet Summary'!D62,0) -> 156.52 | E89: =IFERROR('Balance Sheet Summary'!E62,0) -> 54.78 | F89: =IFERROR('Balance Sheet Summary'!F62,0) -> 140.43 | G89: =IFERROR('Balance Sheet Summary'!G62,0) -> 136.77 | H89: =IFERROR('Balance Sheet Summary'!H62,0) -> 99.85 | I89: =IFERROR('Balance Sheet Summary'!I62,0) -> 603.33 | J89: =IFERROR('Balance Sheet Summary'!J62,0) -> 284.14 | ... L89: =IFERROR('Balance Sheet Summary'!L62,0) -> 321.4
B90: Trade Receivables | C90: =IFERROR('Balance Sheet Summary'!C63,0) -> 18.19 | D90: =IFERROR('Balance Sheet Summary'!D63,0) -> 26.96 | E90: =IFERROR('Balance Sheet Summary'!E63,0) -> 34.3 | F90: =IFERROR('Balance Sheet Summary'!F63,0) -> 12.93 | G90: =IFERROR('Balance Sheet Summary'!G63,0) -> 8.6 | H90: =IFERROR('Balance Sheet Summary'!H63,0) -> 47.83 | I90: =IFERROR('Balance Sheet Summary'!I63,0) -> 108.87 | J90: =IFERROR('Balance Sheet Summary'!J63,0) -> 37.56 | ... L90: =IFERROR('Balance Sheet Summary'!L63,0) -> 114.13
B91: Cash & Bank Balance | C91: =IFERROR('Balance Sheet Summary'!C64,0) -> 0.04 | D91: =IFERROR('Balance Sheet Summary'!D64,0) -> 11.91 | E91: =IFERROR('Balance Sheet Summary'!E64,0) -> 46.55 | F91: =IFERROR('Balance Sheet Summary'!F64,0) -> 25.19 | G91: =IFERROR('Balance Sheet Summary'!G64,0) -> 18.92 | H91: =IFERROR('Balance Sheet Summary'!H64,0) -> 48.52 | I91: =IFERROR('Balance Sheet Summary'!I64,0) -> 248.19 | J91: =IFERROR('Balance Sheet Summary'!J64,0) -> 11.14 | ... L91: =IFERROR('Balance Sheet Summary'!L64,0) -> 210.18
B92: Other Current Assets | C92: =IFERROR(ROUND('Balance Sheet Summary'!C61-C89-C90-C91-('Balance Sheet Summary'!C65+'Balance Sheet Summary'!C66),2),0) -> 0 | D92: =IFERROR(ROUND('Balance Sheet Summary'!D61-D89-D90-D91-('Balance Sheet Summary'!D65+'Balance Sheet Summary'!D66),2),0) -> 160 | E92: =IFERROR(ROUND('Balance Sheet Summary'!E61-E89-E90-E91-('Balance Sheet Summary'!E65+'Balance Sheet Summary'!E66),2),0) -> 0.01 | F92: =IFERROR(ROUND('Balance Sheet Summary'!F61-F89-F90-F91-('Balance Sheet Summary'!F65+'Balance Sheet Summary'!F66),2),0) -> 0.06 | G92: =IFERROR(ROUND('Balance Sheet Summary'!G61-G89-G90-G91-('Balance Sheet Summary'!G65+'Balance Sheet Summary'!G66),2),0) -> 0.74 | H92: =IFERROR(ROUND('Balance Sheet Summary'!H61-H89-H90-H91-('Balance Sheet Summary'!H65+'Balance Sheet Summary'!H66),2),0) -> 1.88 | I92: =IFERROR(ROUND('Balance Sheet Summary'!I61-I89-I90-I91-('Balance Sheet Summary'!I65+'Balance Sheet Summary'!I66),2),0) -> 0.09 | J92: =IFERROR(ROUND('Balance Sheet Summary'!J61-J89-J90-J91-('Balance Sheet Summary'!J65+'Balance Sheet Summary'!J66),2),0) -> 6.11 | K92: =IFERROR(ROUND('Balance Sheet Summary'!K61-K89-K90-K91-('Balance Sheet Summary'!K65+'Balance Sheet Summary'!K66),2),0) -> 28.47 | L92: =IFERROR(IF(ABS('Balance Sheet Summary'!L61-L89-L90-L91-('Balance Sheet Summary'!L65+'Balance Sheet Summary'!L66))<0.05,0,ROUND('Balance Sheet Summary'!L61-L89-L90-L91-('Balance Sheet Summary'!L65+'Balance Sheet Summary'!L66),2)),0) -> 0 | M92: From Balance Sheet Summary: Total CA (row 61) minus Inventories, Receivables, Cash, ST Loans and Investments
B93: ST Loans, Advances & Investments | C93: =IFERROR('Balance Sheet Summary'!C65+'Balance Sheet Summary'!C66,0) -> 5.71 | D93: =IFERROR('Balance Sheet Summary'!D65+'Balance Sheet Summary'!D66,0) -> 31.46 | E93: =IFERROR('Balance Sheet Summary'!E65+'Balance Sheet Summary'!E66,0) -> 94.86 | F93: =IFERROR('Balance Sheet Summary'!F65+'Balance Sheet Summary'!F66,0) -> 58.46 | G93: =IFERROR('Balance Sheet Summary'!G65+'Balance Sheet Summary'!G66,0) -> 48.07 | H93: =IFERROR('Balance Sheet Summary'!H65+'Balance Sheet Summary'!H66,0) -> 29.77 | I93: =IFERROR('Balance Sheet Summary'!I65+'Balance Sheet Summary'!I66,0) -> 34.82 | J93: =IFERROR('Balance Sheet Summary'!J65+'Balance Sheet Summary'!J66,0) -> 67.85 | ... L93: =IFERROR('Balance Sheet Summary'!L65+'Balance Sheet Summary'!L66,0) -> 90.16 | M93: From Balance Sheet Summary: ST Investments (row 65) + ST Loans and Advances (row 66)
B94: Total Current Assets | C94: =IFERROR(C89+C90+C91+C92+C93,0) -> 128.64 | D94: =IFERROR(D89+D90+D91+D92+D93,0) -> 386.85 | E94: =IFERROR(E89+E90+E91+E92+E93,0) -> 230.5 | F94: =IFERROR(F89+F90+F91+F92+F93,0) -> 237.07 | G94: =IFERROR(G89+G90+G91+G92+G93,0) -> 213.1 | H94: =IFERROR(H89+H90+H91+H92+H93,0) -> 227.85 | I94: =IFERROR(I89+I90+I91+I92+I93,0) -> 995.3 | J94: =IFERROR(J89+J90+J91+J92+J93,0) -> 406.8 | ... L94: =IFERROR(L89+L90+L91+L92+L93,0) -> 735.87 | M94: Inventories + Trade Receivables + Cash & Bank + Other CA + ST Loans & Investments
B96: Total Assets | C96: =IFERROR(C85+C94,0) -> 612.02 | D96: =IFERROR(D85+D94,0) -> 952.81 | E96: =IFERROR(E85+E94,0) -> 851.13 | F96: =IFERROR(F85+F94,0) -> 853.27 | G96: =IFERROR(G85+G94,0) -> 823.64 | H96: =IFERROR(H85+H94,0) -> 827.35 | I96: =IFERROR(I85+I94,0) -> 1615.55 | J96: =IFERROR(J85+J94,0) -> 1491.05 | ... L96: =IFERROR(L85+L94,0) -> 1877.47 | M96: Total Non-Current Assets + Total Current Assets
B98: Balance Check (Assets - E+L) | C98: =IFERROR(IF(ROUND(C96-C74,2)=0,"Match",ROUND(C96-C74,2)),"Error") -> Match | D98: =IFERROR(IF(ROUND(D96-D74,2)=0,"Match",ROUND(D96-D74,2)),"Error") -> Match | E98: =IFERROR(IF(ROUND(E96-E74,2)=0,"Match",ROUND(E96-E74,2)),"Error") -> Match | F98: =IFERROR(IF(ROUND(F96-F74,2)=0,"Match",ROUND(F96-F74,2)),"Error") -> Match | G98: =IFERROR(IF(ROUND(G96-G74,2)=0,"Match",ROUND(G96-G74,2)),"Error") -> Match | H98: =IFERROR(IF(ROUND(H96-H74,2)=0,"Match",ROUND(H96-H74,2)),"Error") -> Match | I98: =IFERROR(IF(ROUND(I96-I74,2)=0,"Match",ROUND(I96-I74,2)),"Error") -> Match | J98: =IFERROR(IF(ROUND(J96-J74,2)=0,"Match",ROUND(J96-J74,2)),"Error") -> Match | ... L98: =IFERROR(IF(ROUND(L96-L74,2)=0,"Match",ROUND(L96-L74,2)),"Error") -> Match | M98: Balance Check = Total Assets - (Total Equity + Total Liabilities) → must = 0.00
B100: BSS Cross-Check | C100: =IFERROR(IF(AND(ROUND(C96-'Balance Sheet Summary'!C43,2)=0,ROUND(C74-'Balance Sheet Summary'!C8,2)=0),"Match","E+L vs BSS: "&TEXT(ROUND(C74-'Balance Sheet Summary'!C8,2),"0.00")),"Error") -> Match | D100: =IFERROR(IF(AND(ROUND(D96-'Balance Sheet Summary'!D43,2)=0,ROUND(D74-'Balance Sheet Summary'!D8,2)=0),"Match","E+L vs BSS: "&TEXT(ROUND(D74-'Balance Sheet Summary'!D8,2),"0.00")),"Error") -> Match | E100: =IFERROR(IF(AND(ROUND(E96-'Balance Sheet Summary'!E43,2)=0,ROUND(E74-'Balance Sheet Summary'!E8,2)=0),"Match","E+L vs BSS: "&TEXT(ROUND(E74-'Balance Sheet Summary'!E8,2),"0.00")),"Error") -> Match | F100: =IFERROR(IF(AND(ROUND(F96-'Balance Sheet Summary'!F43,2)=0,ROUND(F74-'Balance Sheet Summary'!F8,2)=0),"Match","E+L vs BSS: "&TEXT(ROUND(F74-'Balance Sheet Summary'!F8,2),"0.00")),"Error") -> Match | G100: =IFERROR(IF(AND(ROUND(G96-'Balance Sheet Summary'!G43,2)=0,ROUND(G74-'Balance Sheet Summary'!G8,2)=0),"Match","E+L vs BSS: "&TEXT(ROUND(G74-'Balance Sheet Summary'!G8,2),"0.00")),"Error") -> Match | H100: =IFERROR(IF(AND(ROUND(H96-'Balance Sheet Summary'!H43,2)=0,ROUND(H74-'Balance Sheet Summary'!H8,2)=0),"Match","E+L vs BSS: "&TEXT(ROUND(H74-'Balance Sheet Summary'!H8,2),"0.00")),"Error") -> Match | I100: =IFERROR(IF(AND(ROUND(I96-'Balance Sheet Summary'!I43,2)=0,ROUND(I74-'Balance Sheet Summary'!I8,2)=0),"Match","E+L vs BSS: "&TEXT(ROUND(I74-'Balance Sheet Summary'!I8,2),"0.00")),"Error") -> Match | J100: =IFERROR(IF(AND(ROUND(J96-'Balance Sheet Summary'!J43,2)=0,ROUND(J74-'Balance Sheet Summary'!J8,2)=0),"Match","E+L vs BSS: "&TEXT(ROUND(J74-'Balance Sheet Summary'!J8,2),"0.00")),"Error") -> Match | ... L100: =IFERROR(IF(AND(ROUND(L96-'Balance Sheet Summary'!L43,2)=0,ROUND(L74-'Balance Sheet Summary'!L8,2)=0),"Match","E+L vs BSS: "&TEXT(ROUND(L74-'Balance Sheet Summary'!L8,2),"0.00")),"Error") -> E+L vs BSS: 0.01 | M100: Verifies Total E+L (row 72) vs Balance Sheet Summary Total Liabilities (row 8) — independent of HFS balance check
A102: # | B102: Cash Flow Statement
B104: Cash Flow from Operating Activities (CFO)
B106: Profit After Tax (PAT) | D106: =D42 -> 24.17 | E106: =E42 -> 57.17 | F106: =F42 -> 40.11 | G106: =G42 -> -11.75 | H106: =H42 -> 57.86 | I106: =I42 -> 238.81 | J106: =J42 -> 164.98 | K106: =K42 -> 99.52 | L106: =L42 -> 114.6
B107: Add: Depreciation | D107: =D23 -> 29.34 | E107: =E23 -> 27.29 | F107: =F23 -> 17.23 | G107: =G23 -> 17.96 | H107: =H23 -> 19.99 | I107: =I23 -> 21.21 | J107: =J23 -> 21.45 | K107: =K23 -> 21.11 | L107: =L23 -> 30.98
B108: Change in Deferred Tax Liability | D108: =D61-C61 -> 0 | E108: =E61-D61 -> 33.78 | F108: =F61-E61 -> 10.39 | G108: =G61-F61 -> -1.98 | H108: =H61-G61 -> 10.88 | I108: =I61-H61 -> 11.05 | J108: =J61-I61 -> 1.97 | K108: =K61-J61 -> 0.07 | L108: =L61-K61 -> 6.74 | M108: = Deferred Tax Liability (Current Year) - Deferred Tax Liability (Prior Year)
B109: Change in Long-term Provisions | D109: =D62-C62 -> 0.34 | E109: =E62-D62 -> 0.28 | F109: =F62-E62 -> 0.08 | G109: =G62-F62 -> 0.3 | H109: =H62-G62 -> 0.09 | I109: =I62-H62 -> 0.28 | J109: =J62-I62 -> 0.1 | K109: =K62-J62 -> 0.45 | L109: =L62-K62 -> 0.28 | M109: = Long-term Provisions (Current Year) - Long-term Provisions (Prior Year)
B111: Changes in Working Capital:
B112: Change in Inventories | D112: =C89-D89 -> -51.82 | E112: =D89-E89 -> 101.74 | F112: =E89-F89 -> -85.65 | G112: =F89-G89 -> 3.66 | H112: =G89-H89 -> 36.92 | I112: =H89-I89 -> -503.48 | J112: =I89-J89 -> 319.19 | K112: =J89-K89 -> -55.88 | L112: =K89-L89 -> 18.62 | M112: = Inventories (Prior Year) - Inventories (Current Year)
B113: Change in Trade Receivables | D113: =C90-D90 -> -8.77 | E113: =D90-E90 -> -7.34 | F113: =E90-F90 -> 21.37 | G113: =F90-G90 -> 4.33 | H113: =G90-H90 -> -39.23 | I113: =H90-I90 -> -61.04 | J113: =I90-J90 -> 71.31 | K113: =J90-K90 -> -39.32 | L113: =K90-L90 -> -37.25 | M113: = Trade Receivables (Prior Year) - Trade Receivables (Current Year)
B114: Change in Other Current Assets | D114: =C92-D92 -> -160 | E114: =D92-E92 -> 159.99 | F114: =E92-F92 -> -0.05 | G114: =F92-G92 -> -0.68 | H114: =G92-H92 -> -1.14 | I114: =H92-I92 -> 1.79 | J114: =I92-J92 -> -6.02 | K114: =J92-K92 -> -22.36 | L114: =K92-L92 -> 28.47 | M114: = Other Current Assets (Prior Year) - Other Current Assets (Current Year)
B115: Change in Trade Payables & Acceptances | D115: =D68-C68 -> 104.08 | E115: =E68-D68 -> -186.76 | F115: =F68-E68 -> 15.41 | G115: =G68-F68 -> 10.8 | H115: =H68-G68 -> -65.15 | I115: =I68-H68 -> 346.72 | J115: =J68-I68 -> -58.85 | K115: =K68-J68 -> 321.4 | L115: =L68-K68 -> -250.95 | M115: = Trade Payables (Current Year) - Trade Payables (Prior Year)
B116: Change in Other Current Liabilities | D116: =D69-C69 -> -376.56 | E116: =E69-D69 -> 6.3 | F116: =F69-E69 -> 23.6 | G116: =G69-F69 -> -10.4 | H116: =H69-G69 -> 3.77 | I116: =I69-H69 -> 72.67 | J116: =J69-I69 -> -83.8 | K116: =K69-J69 -> 14.74 | L116: =L69-K69 -> 206.75 | M116: = Other Current Liabilities (Current Year) - Other Current Liabilities (Prior Year)
B118: Total CFO | D118: =SUM(D106:D109,D112:D116) -> -439.22 | E118: =SUM(E106:E109,E112:E116) -> 192.45 | F118: =SUM(F106:F109,F112:F116) -> 42.49 | G118: =SUM(G106:G109,G112:G116) -> 12.24 | H118: =SUM(H106:H109,H112:H116) -> 23.99 | I118: =SUM(I106:I109,I112:I116) -> 128.01 | J118: =SUM(J106:J109,J112:J116) -> 430.33 | K118: =SUM(K106:K109,K112:K116) -> 339.73 | L118: =SUM(L106:L109,L112:L116) -> 118.24 | M118: = Sum of PAT + Depreciation + Δ DTL + Δ LT Provisions + Working Capital Changes
B120: Cash Flow from Investing Activities (CFI)
B122: Capital Expenditures (Capex) | D122: =-((D80+D81)-(C80+C81)+D23) -> 0.63 | E122: =-((E80+E81)-(D80+D81)+E23) -> -95.13 | F122: =-((F80+F81)-(E80+E81)+F23) -> -16.69 | G122: =-((G80+G81)-(F80+F81)+G23) -> -15.41 | H122: =-((H80+H81)-(G80+G81)+H23) -> -13.01 | I122: =-((I80+I81)-(H80+H81)+I23) -> -21.83 | J122: =-((J80+J81)-(I80+I81)+J23) -> -159.09 | K122: =-((K80+K81)-(J80+J81)+K23) -> -282.7 | L122: =-((L80+L81)-(K80+K81)+L23) -> -102.95 | M122: = -(NFA_CY + CWIP_CY - NFA_PY - CWIP_PY + Depreciation_CY)
B123: Change in Long-term Investments | D123: =C82-D82 -> -0.05 | E123: =D82-E82 -> -0.01 | F123: =E82-F82 -> 0.03 | G123: =F82-G82 -> 0.01 | H123: =G82-H82 -> -0.03 | I123: =H82-I82 -> -0.09 | J123: =I82-J82 -> -0.11 | K123: =J82-K82 -> -0.28 | L123: =K82-L82 -> 0.08 | M123: = Long-term Investments (Prior Year) - Long-term Investments (Current Year)
B124: Change in Long-term Loans & Advances | D124: =C83-D83 -> -7.75 | E124: =D83-E83 -> 7.75 | F124: =E83-F83 -> 0 | G124: =F83-G83 -> 0 | H124: =G83-H83 -> 0 | I124: =H83-I83 -> -119.06 | J124: =I83-J83 -> -330.12 | K124: =J83-K83 -> 180.75 | L124: =K83-L83 -> 240.28 | M124: = Long-term Loans & Advances (Prior Year) - Long-term Loans & Advances (Current Year)
B125: Change in Other Long-term Assets | D125: =C84-D84 -> -104.75 | E125: =D84-E84 -> 5.43 | F125: =E84-F84 -> 3.86 | G125: =F84-G84 -> 3.1 | H125: =G84-H84 -> 4.09 | I125: =H84-I84 -> 99.02 | J125: =I84-J84 -> 3.87 | K125: =J84-K84 -> 1.11 | L125: =K84-L84 -> -145.73 | M125: = Other Long-term Assets (Prior Year) - Other Long-term Assets (Current Year)
B126: Change in ST Loans, Advances & Investments | D126: =C93-D93 -> -25.75 | E126: =D93-E93 -> -63.4 | F126: =E93-F93 -> 36.4 | G126: =F93-G93 -> 10.39 | H126: =G93-H93 -> 18.3 | I126: =H93-I93 -> -5.05 | J126: =I93-J93 -> -33.03 | K126: =J93-K93 -> -123.28 | L126: =K93-L93 -> 100.97 | O126: = ST Loans, Advances & Investments (Prior Year) - ST Loans (Current Year)
B127: Total CFI | D127: =SUM(D122:D126) -> -137.67 | E127: =SUM(E122:E126) -> -145.36 | F127: =SUM(F122:F126) -> 23.6 | G127: =SUM(G122:G126) -> -1.91 | H127: =SUM(H122:H126) -> 9.35 | I127: =SUM(I122:I126) -> -47.01 | J127: =SUM(J122:J126) -> -518.48 | K127: =SUM(K122:K126) -> -224.4 | L127: =SUM(L122:L126) -> 92.65 | M127: = Sum of Capex + Δ LT Investments + Δ LT Loans + Δ Other LT Assets + Δ ST Loans
B129: Cash Flow from Financing Activities (CFF)
B131: Change in Share Capital | D131: =D53-C53 -> 50 | E131: =E53-D53 -> 0 | F131: =F53-E53 -> 0 | G131: =G53-F53 -> 0 | H131: =H53-G53 -> -0.01 | I131: =I53-H53 -> 0 | J131: =J53-I53 -> 0 | K131: =K53-J53 -> 0 | L131: =L53-K53 -> -6.84 | M131: = Share Capital (Current Year) - Share Capital (Prior Year)
B132: Change in LT Borrowings | D132: =D60-C60 -> 488.17 | E132: =E60-D60 -> 7.35 | F132: =F60-E60 -> -87.47 | G132: =G60-F60 -> -16.54 | H132: =H60-G60 -> -3.71 | I132: =I60-H60 -> 114.43 | J132: =J60-I60 -> -178.2 | K132: =K60-J60 -> -18.78 | L132: =L60-K60 -> -25.67 | M132: = LT Borrowings (Current Year) - LT Borrowings (Prior Year)
B133: Change in Short-term Borrowings | D133: =D67-C67 -> 77.77 | E133: =E67-D67 -> -81.78 | F133: =F67-E67 -> 0 | G133: =G67-F67 -> 0 | H133: =H67-G67 -> 0 | I133: =I67-H67 -> 4.28 | J133: =J67-I67 -> 29.37 | K133: =K67-J67 -> -32.84 | L133: =L67-K67 -> 108.19 | M133: = Short-term Borrowings (Current Year) - Short-term Borrowings (Prior Year)
B134: Dividends Paid | D134: =-(D42-(D54-C54)) -> -27.18 | E134: =-(E42-(E54-D54)) -> 61.98 | F134: =-(F42-(F54-E54)) -> 0.02 | G134: =-(G42-(G54-F54)) -> -0.06 | H134: =-(H42-(H54-G54)) -> -0.02 | I134: =-(I42-(I54-H54)) -> -0.04 | J134: =-(J42-(J54-I54)) -> -0.07 | K134: =-(K42-(K54-J54)) -> -0.05 | L134: =-(L42-(L54-K54)) -> -151.19 | M134: = -(PAT - (Reserves & Surplus CY - Reserves & Surplus PY))
B136: Total CFF | D136: =SUM(D131:D134) -> 588.76 | E136: =SUM(E131:E134) -> -12.45 | F136: =SUM(F131:F134) -> -87.45 | G136: =SUM(G131:G134) -> -16.6 | H136: =SUM(H131:H134) -> -3.74 | I136: =SUM(I131:I134) -> 118.67 | J136: =SUM(J131:J134) -> -148.9 | K136: =SUM(K131:K134) -> -51.67 | L136: =SUM(L131:L134) -> -75.51 | M136: = Sum of Δ Share Capital + Δ LT Borrowings + Δ ST Borrowings + Dividends Paid
B138: Net Change in Cash & Cash Equivalents | D138: =D118+D127+D136 -> 11.87 | E138: =E118+E127+E136 -> 34.64 | F138: =F118+F127+F136 -> -21.36 | G138: =G118+G127+G136 -> -6.27 | H138: =H118+H127+H136 -> 29.6 | I138: =I118+I127+I136 -> 199.67 | J138: =J118+J127+J136 -> -237.05 | K138: =K118+K127+K136 -> 63.66 | L138: =L118+L127+L136 -> 135.38 | M138: = Total CFO + Total CFI + Total CFF
B140: Opening Cash Balance | D140: =C91 -> 0.04 | E140: =D91 -> 11.91 | F140: =E91 -> 46.55 | G140: =F91 -> 25.19 | H140: =G91 -> 18.92 | I140: =H91 -> 48.52 | J140: =I91 -> 248.19 | K140: =J91 -> 11.14 | L140: =K91 -> 74.8 | M140: = Prior Year Cash & Bank Balance (row 91)
B141: Closing Cash Balance (Calculated) | D141: =D140+D138 -> 11.91 | E141: =E140+E138 -> 46.55 | F141: =F140+F138 -> 25.19 | G141: =G140+G138 -> 18.92 | H141: =H140+H138 -> 48.52 | I141: =I140+I138 -> 248.19 | J141: =J140+J138 -> 11.14 | K141: =K140+K138 -> 74.8 | L141: =L140+L138 -> 210.18 | M141: = Opening Cash Balance + Net Change in Cash
B143: Check (Calc. vs BS) | D143: =IFERROR(IF(ROUND(D141-D91,2)=0,"Match",ROUND(D141-D91,2)),"Error") -> Match | E143: =IFERROR(IF(ROUND(E141-E91,2)=0,"Match",ROUND(E141-E91,2)),"Error") -> Match | F143: =IFERROR(IF(ROUND(F141-F91,2)=0,"Match",ROUND(F141-F91,2)),"Error") -> Match | G143: =IFERROR(IF(ROUND(G141-G91,2)=0,"Match",ROUND(G141-G91,2)),"Error") -> Match | H143: =IFERROR(IF(ROUND(H141-H91,2)=0,"Match",ROUND(H141-H91,2)),"Error") -> Match | I143: =IFERROR(IF(ROUND(I141-I91,2)=0,"Match",ROUND(I141-I91,2)),"Error") -> Match | J143: =IFERROR(IF(ROUND(J141-J91,2)=0,"Match",ROUND(J141-J91,2)),"Error") -> Match | K143: =IFERROR(IF(ROUND(K141-K91,2)=0,"Match",ROUND(K141-K91,2)),"Error") -> Match | L143: =IFERROR(IF(ROUND(L141-L91,2)=0,"Match",ROUND(L141-L91,2)),"Error") -> Match | M143: = Closing Cash (Calc.) - Cash & Bank Balance (BS). Display "Match" if 0

Sheet Ratio Analysis
B2: ="Ratio Analysis - "&'Executive Summary'!B2 -> Ratio Analysis - Jindal Coke Ltd.
B3: ='Historical FS'!B3 -> Years | C3: ='Historical FS'!C3 -> FY16A | D3: ='Historical FS'!D3 -> FY17A | E3: ='Historical FS'!E3 -> FY18A | F3: ='Historical FS'!F3 -> FY19A | G3: ='Historical FS'!G3 -> FY20A | H3: ='Historical FS'!H3 -> FY21A | I3: ='Historical FS'!I3 -> FY22A | ... L3: ='Historical FS'!L3 -> FY25A | M3: Trend (FY16→FY25) | N3: FY26E | O3: FY27E | P3: FY28E | Q3: FY29E | R3: FY30E | S3: FY31E | T3: FY32E | U3: FY33E | V3: Formula Reference | W3: Interpretation
B5: 1. Growth Ratios
B6: Sales Growth | C6: =IFERROR('Historical FS'!C6,0) -> - | D6: =IFERROR('Historical FS'!D6,0) -> 0.83232848 | E6: =IFERROR('Historical FS'!E6,0) -> 0.35297433 | F6: =IFERROR('Historical FS'!F6,0) -> 0.055125203 | G6: =IFERROR('Historical FS'!G6,0) -> -0.18715853 | H6: =IFERROR('Historical FS'!H6,0) -> 0.0022186339 | I6: =IFERROR('Historical FS'!I6,0) -> 0.62696812 | J6: =IFERROR('Historical FS'!J6,0) -> 0.60470509 | ... L6: =IFERROR('Historical FS'!L6,0) -> 0.18980799 | N6: =IFERROR(('The 3-Statement Projection'!D6/'The 3-Statement Projection'!C6)-1,0) -> 0.11210268 | O6: =IFERROR(('The 3-Statement Projection'!E6/'The 3-Statement Projection'!D6)-1,0) -> 0.055018677 | P6: =IFERROR(('The 3-Statement Projection'!F6/'The 3-Statement Projection'!E6)-1,0) -> 0 | Q6: =IFERROR(('The 3-Statement Projection'!G6/'The 3-Statement Projection'!F6)-1,0) -> 0 | R6: =IFERROR(('The 3-Statement Projection'!H6/'The 3-Statement Projection'!G6)-1,0) -> 0 | S6: =IFERROR(('The 3-Statement Projection'!I6/'The 3-Statement Projection'!H6)-1,0) -> 0 | T6: =IFERROR(('The 3-Statement Projection'!J6/'The 3-Statement Projection'!I6)-1,0) -> 0 | U6: =IFERROR(('The 3-Statement Projection'!K6/'The 3-Statement Projection'!J6)-1,0) -> 0 | V6: Sales Growth = (Net Sales CY / Net Sales PY) − 1 | W6: Sales growth is highly volatile, showing sharp spikes (FY17, FY22–23) and contractions (FY20, FY24), indicating cyclical demand or external shocks. The recovery in FY25 suggests stabilization, but inconsistency implies dependence on market conditions rather than steady organic growth.
B7: EBITDA Growth | C7: - | D7: =IF(OR('Historical FS'!C20<=0,'Historical FS'!D20<=0),"N/M",'Historical FS'!D20/'Historical FS'!C20 -1) -> N/M | E7: =IF(OR('Historical FS'!D20<=0,'Historical FS'!E20<=0),"N/M",'Historical FS'!E20/'Historical FS'!D20 -1) -> 0.4868193 | F7: =IF(OR('Historical FS'!E20<=0,'Historical FS'!F20<=0),"N/M",'Historical FS'!F20/'Historical FS'!E20 -1) -> -0.19429448 | G7: =IF(OR('Historical FS'!F20<=0,'Historical FS'!G20<=0),"N/M",'Historical FS'!G20/'Historical FS'!F20 -1) -> -0.61318815 | H7: =IF(OR('Historical FS'!G20<=0,'Historical FS'!H20<=0),"N/M",'Historical FS'!H20/'Historical FS'!G20 -1) -> 1.905315 | I7: =IF(OR('Historical FS'!H20<=0,'Historical FS'!I20<=0),"N/M",'Historical FS'!I20/'Historical FS'!H20 -1) -> 1.550376 | J7: =IFERROR('Historical FS'!J20/'Historical FS'!I20 -1,0) -> -0.3094498 | K7: =IFERROR('Historical FS'!K20/'Historical FS'!J20 -1,0) -> -0.37367753 | L7: =IFERROR('Historical FS'!L20/'Historical FS'!K20 -1,0) -> 0.23120393 | N7: =IFERROR('The 3-Statement Projection'!D15/'The 3-Statement Projection'!C15-1,0) -> 0.8945592 | O7: =IFERROR('The 3-Statement Projection'!E15/'The 3-Statement Projection'!D15-1,0) -> -0.051388043 | P7: =IFERROR('The 3-Statement Projection'!F15/'The 3-Statement Projection'!E15-1,0) -> 0.012190015 | Q7: =IFERROR('The 3-Statement Projection'!G15/'The 3-Statement Projection'!F15-1,0) -> 0.012043208 | R7: =IFERROR('The 3-Statement Projection'!H15/'The 3-Statement Projection'!G15-1,0) -> 0 | S7: =IFERROR('The 3-Statement Projection'!I15/'The 3-Statement Projection'!H15-1,0) -> 0 | T7: =IFERROR('The 3-Statement Projection'!J15/'The 3-Statement Projection'!I15-1,0) -> 0 | U7: =IFERROR('The 3-Statement Projection'!K15/'The 3-Statement Projection'!J15-1,0) -> 0 | V7: EBITDA Growth = (EBITDA CY / EBITDA PY) − 1 | W7: EBITDA growth is even more erratic than sales, with extreme swings (e.g., +190% in FY21, -61% in FY20), reflecting fluctuating operating efficiency. This indicates inconsistent cost control or operating leverage, where margins expand sharply in upcycles but compress significantly in downturns.
B8: EBIT Growth | C8: - | D8: =IF(OR('Historical FS'!C26<=0,'Historical FS'!D26<=0),"N/M",'Historical FS'!D26/'Historical FS'!C26 -1) -> N/M | E8: =IF(OR('Historical FS'!D26<=0,'Historical FS'!E26<=0),"N/M",'Historical FS'!E26/'Historical FS'!D26 -1) -> 0.69024785 | F8: =IF(OR('Historical FS'!E26<=0,'Historical FS'!F26<=0),"N/M",'Historical FS'!F26/'Historical FS'!E26 -1) -> -0.15923661 | G8: =IF(OR('Historical FS'!F26<=0,'Historical FS'!G26<=0),"N/M",'Historical FS'!G26/'Historical FS'!F26 -1) -> -0.7121823 | H8: =IF(OR('Historical FS'!G26<=0,'Historical FS'!H26<=0),"N/M",'Historical FS'!H26/'Historical FS'!G26 -1) -> 2.8855055 | I8: =IF(OR('Historical FS'!H26<=0,'Historical FS'!I26<=0),"N/M",'Historical FS'!I26/'Historical FS'!H26 -1) -> 1.7836991 | J8: =IFERROR('Historical FS'!J26/'Historical FS'!I26 -1,0) -> -0.3286036 | K8: =IFERROR('Historical FS'!K26/'Historical FS'!J26 -1,0) -> -0.40586213 | L8: =IFERROR('Historical FS'!L26/'Historical FS'!K26 -1,0) -> 0.19599125 | N8: =IFERROR('The 3-Statement Projection'!D19/'The 3-Statement Projection'!C19-1,0) -> 0.97114356 | O8: =IFERROR('The 3-Statement Projection'!E19/'The 3-Statement Projection'!D19-1,0) -> -0.062087675 | P8: =IFERROR('The 3-Statement Projection'!F19/'The 3-Statement Projection'!E19-1,0) -> 0.010009334 | Q8: =IFERROR('The 3-Statement Projection'!G19/'The 3-Statement Projection'!F19-1,0) -> 0.0098109552 | R8: =IFERROR('The 3-Statement Projection'!H19/'The 3-Statement Projection'!G19-1,0) -> -0.004127747 | S8: =IFERROR('The 3-Statement Projection'!I19/'The 3-Statement Projection'!H19-1,0) -> -0.0042484773 | T8: =IFERROR('The 3-Statement Projection'!J19/'The 3-Statement Projection'!I19-1,0) -> -0.0043732689 | U8: =IFERROR('The 3-Statement Projection'!K19/'The 3-Statement Projection'!J19-1,0) -> -0.0045022904 | V8: EBIT Growth = (EBIT CY / EBIT PY) − 1 | W8: EBIT growth mirrors EBITDA volatility but with sharper movements, highlighting the additional impact of depreciation and fixed costs. Large swings (e.g., +288% in FY21, -71% in FY20) suggest high operating leverage, making profitability highly sensitive to revenue changes.
B9: Net Profit Growth | C9: - | D9: =IF(OR('Historical FS'!C42<=0,'Historical FS'!D42<=0),"N/M",'Historical FS'!D42/'Historical FS'!C42 -1) -> N/M | E9: =IF(OR('Historical FS'!D42<=0,'Historical FS'!E42<=0),"N/M",'Historical FS'!E42/'Historical FS'!D42 -1) -> 1.3653289 | F9: =IF(OR('Historical FS'!E42<=0,'Historical FS'!F42<=0),"N/M",'Historical FS'!F42/'Historical FS'!E42 -1) -> -0.29840826 | G9: =IF(OR('Historical FS'!F42<=0,'Historical FS'!G42<=0),"N/M",'Historical FS'!G42/'Historical FS'!F42 -1) -> N/M | H9: =IF(OR('Historical FS'!G42<=0,'Historical FS'!H42<=0),"N/M",'Historical FS'!H42/'Historical FS'!G42 -1) -> N/M | I9: =IF(OR('Historical FS'!H42<=0,'Historical FS'!I42<=0),"N/M",'Historical FS'!I42/'Historical FS'!H42 -1) -> 3.1273764 | J9: =IFERROR('Historical FS'!J42/'Historical FS'!I42 -1,0) -> -0.30915791 | K9: =IFERROR('Historical FS'!K42/'Historical FS'!J42 -1,0) -> -0.39677537 | L9: =IFERROR('Historical FS'!L42/'Historical FS'!K42 -1,0) -> 0.15152733 | N9: =IFERROR('The 3-Statement Projection'!D27/'The 3-Statement Projection'!C27-1,0) -> 0.97042475 | O9: =IFERROR('The 3-Statement Projection'!E27/'The 3-Statement Projection'!D27-1,0) -> -0.11529376 | P9: =IFERROR('The 3-Statement Projection'!F27/'The 3-Statement Projection'!E27-1,0) -> 0.05290939 | Q9: =IFERROR('The 3-Statement Projection'!G27/'The 3-Statement Projection'!F27-1,0) -> 0.026028736 | R9: =IFERROR('The 3-Statement Projection'!H27/'The 3-Statement Projection'!G27-1,0) -> 0.0095162408 | S9: =IFERROR('The 3-Statement Projection'!I27/'The 3-Statement Projection'!H27-1,0) -> 0.009266916 | T9: =IFERROR('The 3-Statement Projection'!J27/'The 3-Statement Projection'!I27-1,0) -> 0.0090668112 | U9: =IFERROR('The 3-Statement Projection'!K27/'The 3-Statement Projection'!J27-1,0) -> 0.0088685092 | V9: Net Profit Growth = (PAT CY / PAT PY) − 1 | W9: Net profit grew +15% in FY25 to ₹114.6 Cr, trailing EBITDA/EBIT growth due to higher interest expense (re-levering for Battery-2). Still meaningfully below FY22 supernormal peak (₹239 Cr). Earliest years (FY17-FY21) show N/M due to negative-base distortions.
B11: 2. Profitability Ratios
B12: Gross Margin | C12: =IFERROR('Historical FS'!C12,0) -> 0.058142131 | D12: =IFERROR('Historical FS'!D12,0) -> 0.21470028 | E12: =IFERROR('Historical FS'!E12,0) -> 0.23148982 | F12: =IFERROR('Historical FS'!F12,0) -> 0.1948203 | G12: =IFERROR('Historical FS'!G12,0) -> 0.12629147 | H12: =IFERROR('Historical FS'!H12,0) -> 0.25356946 | I12: =IFERROR('Historical FS'!I12,0) -> 0.35027293 | J12: =IFERROR('Historical FS'!J12,0) -> 0.16172472 | ... L12: =IFERROR('Historical FS'!L12,0) -> 0.15809077 | N12: =IFERROR('The 3-Statement Projection'!D10/'The 3-Statement Projection'!D6,0) -> 0.22917245 | O12: =IFERROR('The 3-Statement Projection'!E10/'The 3-Statement Projection'!E6,0) -> 0.21076871 | P12: =IFERROR('The 3-Statement Projection'!F10/'The 3-Statement Projection'!F6,0) -> 0.21276871 | Q12: =IFERROR('The 3-Statement Projection'!G10/'The 3-Statement Projection'!G6,0) -> 0.21476871 | R12: =IFERROR('The 3-Statement Projection'!H10/'The 3-Statement Projection'!H6,0) -> 0.21476871 | S12: =IFERROR('The 3-Statement Projection'!I10/'The 3-Statement Projection'!I6,0) -> 0.21476871 | T12: =IFERROR('The 3-Statement Projection'!J10/'The 3-Statement Projection'!J6,0) -> 0.21476871 | U12: =IFERROR('The 3-Statement Projection'!K10/'The 3-Statement Projection'!K6,0) -> 0.21476871 | V12: Gross Margin = Gross Profit / Net Sales | W12: Gross margin recovered to 15.8% in FY25 (from 15.0% FY24), a modest improvement. Still far below the FY22 peak of 35% driven by favourable coke spreads. The business remains a commodity margin play — gross margin is highly sensitive to coke price cycles and imported coal costs.
B13: EBITDA Margin | C13: =IFERROR('Historical FS'!C21,0) -> -0.014402948 | D13: =IFERROR('Historical FS'!D21,0) -> 0.16700434 | E13: =IFERROR('Historical FS'!E21,0) -> 0.18352549 | F13: =IFERROR('Historical FS'!F21,0) -> 0.14014214 | G13: =IFERROR('Historical FS'!G21,0) -> 0.066690297 | H13: =IFERROR('Historical FS'!H21,0) -> 0.1933274 | I13: =IFERROR('Historical FS'!I21,0) -> 0.30305299 | J13: =IFERROR('Historical FS'!J21,0) -> 0.13041231 | ... L13: =IFERROR('Historical FS'!L21,0) -> 0.10711099 | N13: =IFERROR('The 3-Statement Projection'!D16,0) -> 0.18247245 | O13: =IFERROR('The 3-Statement Projection'!E16,0) -> 0.16406871 | P13: =IFERROR('The 3-Statement Projection'!F16,0) -> 0.16606871 | Q13: =IFERROR('The 3-Statement Projection'!G16,0) -> 0.16806871 | R13: =IFERROR('The 3-Statement Projection'!H16,0) -> 0.16806871 | S13: =IFERROR('The 3-Statement Projection'!I16,0) -> 0.16806871 | T13: =IFERROR('The 3-Statement Projection'!J16,0) -> 0.16806871 | U13: =IFERROR('The 3-Statement Projection'!K16,0) -> 0.16806871 | V13: EBITDA Margin = EBITDA / Net Sales | W13: EBITDA margin ticked up to 10.7% in FY25 (from 10.4% FY24), still meaningfully below the FY22 peak of 30.3%. Operating leverage is intact but coke spreads remain mid-cycle. Management forecasts 16.8% by FY29E on volume ramp and mix improvement.
B14: EBIT Margin | C14: =IFERROR('Historical FS'!C27,0) -> -0.095656786 | D14: =IFERROR('Historical FS'!D27,0) -> 0.12230939 | E14: =IFERROR('Historical FS'!E27,0) -> 0.15279905 | F14: =IFERROR('Historical FS'!F27,0) -> 0.12175602 | G14: =IFERROR('Historical FS'!G27,0) -> 0.043112389 | H14: =IFERROR('Historical FS'!H27,0) -> 0.1671426 | I14: =IFERROR('Historical FS'!I27,0) -> 0.28597652 | J14: =IFERROR('Historical FS'!J27,0) -> 0.1196504 | ... L14: =IFERROR('Historical FS'!L27,0) -> 0.090555915 | N14: =IFERROR('The 3-Statement Projection'!D19/'The 3-Statement Projection'!D6,0) -> 0.1605056 | O14: =IFERROR('The 3-Statement Projection'!E19/'The 3-Statement Projection'!E6,0) -> 0.14268959 | P14: =IFERROR('The 3-Statement Projection'!F19/'The 3-Statement Projection'!F6,0) -> 0.14411782 | Q14: =IFERROR('The 3-Statement Projection'!G19/'The 3-Statement Projection'!G6,0) -> 0.14553175 | R14: =IFERROR('The 3-Statement Projection'!H19/'The 3-Statement Projection'!H6,0) -> 0.14493103 | S14: =IFERROR('The 3-Statement Projection'!I19/'The 3-Statement Projection'!I6,0) -> 0.14431529 | T14: =IFERROR('The 3-Statement Projection'!J19/'The 3-Statement Projection'!J6,0) -> 0.14368416 | U14: =IFERROR('The 3-Statement Projection'!K19/'The 3-Statement Projection'!K6,0) -> 0.14303726 | V14: EBIT Margin = EBIT / Net Sales | W14: EBIT margin at 9.1% in FY25 (up modestly from 9.0% FY24) remains below the 9-year median and far from the FY22 peak of 28.6%. Below-mid-cycle profitability; depreciation intensity is rising with Battery-2 capitalised, adding a structural drag that volume growth must offset.
B15: EBT Margin | C15: =IFERROR('Historical FS'!C38,0) -> -0.13688383 | D15: =IFERROR('Historical FS'!D38,0) -> 0.056409475 | E15: =IFERROR('Historical FS'!E38,0) -> 0.093902 | F15: =IFERROR('Historical FS'!F38,0) -> 0.068817227 | G15: =IFERROR('Historical FS'!G38,0) -> -0.017985375 | H15: =IFERROR('Historical FS'!H38,0) -> 0.10866888 | I15: =IFERROR('Historical FS'!I38,0) -> 0.26505966 | J15: =IFERROR('Historical FS'!J38,0) -> 0.11016788 | ... L15: =IFERROR('Historical FS'!L38,0) -> 0.082641757 | N15: =IFERROR('The 3-Statement Projection'!D23/'The 3-Statement Projection'!D6,0) -> 0.14499795 | O15: =IFERROR('The 3-Statement Projection'!E23/'The 3-Statement Projection'!E6,0) -> 0.12159082 | P15: =IFERROR('The 3-Statement Projection'!F23/'The 3-Statement Projection'!F6,0) -> 0.12802412 | Q15: =IFERROR('The 3-Statement Projection'!G23/'The 3-Statement Projection'!G6,0) -> 0.13135642 | R15: =IFERROR('The 3-Statement Projection'!H23/'The 3-Statement Projection'!H6,0) -> 0.13260644 | S15: =IFERROR('The 3-Statement Projection'!I23/'The 3-Statement Projection'!I6,0) -> 0.1338353 | T15: =IFERROR('The 3-Statement Projection'!J23/'The 3-Statement Projection'!J6,0) -> 0.13504876 | U15: =IFERROR('The 3-Statement Projection'!K23/'The 3-Statement Projection'!K6,0) -> 0.13624644 | V15: EBT Margin = Profit Before Tax / Net Sales | W15: EBT margin 8.3% in FY25 (vs 8.6% FY24) reflects higher interest from the FY25 net TL drawdown (+₹113 Cr to fund Battery-2). Finance costs are structurally elevated vs FY23-24 deleveraging years — this is the cost of the capacity expansion.
B16: Net Profit Margin | C16: =IFERROR('Historical FS'!C43,0) -> -0.089515994 | D16: =IFERROR('Historical FS'!D43,0) -> 0.036819255 | E16: =IFERROR('Historical FS'!E43,0) -> 0.064369033 | F16: =IFERROR('Historical FS'!F43,0) -> 0.042801349 | G16: =IFERROR('Historical FS'!G43,0) -> -0.015425413 | H16: =IFERROR('Historical FS'!H43,0) -> 0.075790522 | I16: =IFERROR('Historical FS'!I43,0) -> 0.19226929 | J16: =IFERROR('Historical FS'!J43,0) -> 0.082773915 | ... L16: =IFERROR('Historical FS'!L43,0) -> 0.061239867 | N16: =IFERROR('The 3-Statement Projection'!D28,0) -> 0.10850486 | O16: =IFERROR('The 3-Statement Projection'!E28,0) -> 0.090988844 | P16: =IFERROR('The 3-Statement Projection'!F28,0) -> 0.095803008 | Q16: =IFERROR('The 3-Statement Projection'!G28,0) -> 0.098296639 | R16: =IFERROR('The 3-Statement Projection'!H28,0) -> 0.099232054 | S16: =IFERROR('The 3-Statement Projection'!I28,0) -> 0.10015163 | T16: =IFERROR('The 3-Statement Projection'!J28,0) -> 0.10105968 | U16: =IFERROR('The 3-Statement Projection'!K28,0) -> 0.10195593 | V16: Net Profit Margin = Profit After Tax / Net Sales | W16: Net margin 6.1% in FY25 (vs 6.3% FY24) is modestly lower despite higher revenue, reflecting interest drag. Still solidly positive — a long way from FY16 (-9.0%) and FY20 (-1.8%) loss years. Effective tax rate consistent at ~25-26% in profitable years.
B18: SG&A Expenses % Sales | C18: =IFERROR('Historical FS'!C18,0) -> 0.052643332 | D18: =IFERROR('Historical FS'!D18,0) -> 0.033330794 | E18: =IFERROR('Historical FS'!E18,0) -> 0.038743019 | F18: =IFERROR('Historical FS'!F18,0) -> 0.044273946 | G18: =IFERROR('Historical FS'!G18,0) -> 0.046368136 | H18: =IFERROR('Historical FS'!H18,0) -> 0.046776349 | I18: =IFERROR('Historical FS'!I18,0) -> 0.036882276 | J18: =IFERROR('Historical FS'!J18,0) -> 0.025211475 | ... L18: =IFERROR('Historical FS'!L18,0) -> 0.041441114 | N18: =IFERROR('The 3-Statement Projection'!D13/'The 3-Statement Projection'!D6,0) -> 0.0374 | O18: =IFERROR('The 3-Statement Projection'!E13/'The 3-Statement Projection'!E6,0) -> 0.0374 | P18: =IFERROR('The 3-Statement Projection'!F13/'The 3-Statement Projection'!F6,0) -> 0.0374 | Q18: =IFERROR('The 3-Statement Projection'!G13/'The 3-Statement Projection'!G6,0) -> 0.0374 | R18: =IFERROR('The 3-Statement Projection'!H13/'The 3-Statement Projection'!H6,0) -> 0.0374 | S18: =IFERROR('The 3-Statement Projection'!I13/'The 3-Statement Projection'!I6,0) -> 0.0374 | T18: =IFERROR('The 3-Statement Projection'!J13/'The 3-Statement Projection'!J6,0) -> 0.0374 | U18: =IFERROR('The 3-Statement Projection'!K13/'The 3-Statement Projection'!K6,0) -> 0.0374 | V18: SG&A % Sales = SG&A Expenses / Net Sales | W18: SG&A stood at 4.1% in FY25 (up from 3.7% FY24). Cost absorption was modestly pressured as overhead costs rose alongside expanded operations. Well-managed historically — range has been 2.5-4.7% of sales.
B19: Depreciation % Sales | C19: =IFERROR('Historical FS'!C24,0) -> 0.081253838 | D19: =IFERROR('Historical FS'!D24,0) -> 0.04469495 | E19: =IFERROR('Historical FS'!E24,0) -> 0.030726446 | F19: =IFERROR('Historical FS'!F24,0) -> 0.018386119 | G19: =IFERROR('Historical FS'!G24,0) -> 0.023577908 | H19: =IFERROR('Historical FS'!H24,0) -> 0.0261848 | I19: =IFERROR('Historical FS'!I24,0) -> 0.01707647 | J19: =IFERROR('Historical FS'!J24,0) -> 0.010761913 | ... L19: =IFERROR('Historical FS'!L24,0) -> 0.01655507 | N19: =IFERROR('The 3-Statement Projection'!D18/'The 3-Statement Projection'!D6,0) -> 0.021966851 | O19: =IFERROR('The 3-Statement Projection'!E18/'The 3-Statement Projection'!E6,0) -> 0.021379118 | P19: =IFERROR('The 3-Statement Projection'!F18/'The 3-Statement Projection'!F6,0) -> 0.02195089 | Q19: =IFERROR('The 3-Statement Projection'!G18/'The 3-Statement Projection'!G6,0) -> 0.022536957 | R19: =IFERROR('The 3-Statement Projection'!H18/'The 3-Statement Projection'!H6,0) -> 0.023137675 | S19: =IFERROR('The 3-Statement Projection'!I18/'The 3-Statement Projection'!I6,0) -> 0.023753411 | T19: =IFERROR('The 3-Statement Projection'!J18/'The 3-Statement Projection'!J6,0) -> 0.024384541 | U19: =IFERROR('The 3-Statement Projection'!K18/'The 3-Statement Projection'!K6,0) -> 0.025031448 | V19: Depreciation % Sales = Depreciation / Net Sales | W19: Depreciation intensity rose to 1.66% of sales in FY25 (from 1.3% FY24) as Battery-2 commissioning added ₹433 Cr of gross block. This is the structural step-change — expect dep % to stay elevated through the projection period.
B20: Operating Income % Sales | C20: =IFERROR('Historical FS'!C27,0) -> -0.095656786 | D20: =IFERROR('Historical FS'!D27,0) -> 0.12230939 | E20: =IFERROR('Historical FS'!E27,0) -> 0.15279905 | F20: =IFERROR('Historical FS'!F27,0) -> 0.12175602 | G20: =IFERROR('Historical FS'!G27,0) -> 0.043112389 | H20: =IFERROR('Historical FS'!H27,0) -> 0.1671426 | I20: =IFERROR('Historical FS'!I27,0) -> 0.28597652 | J20: =IFERROR('Historical FS'!J27,0) -> 0.1196504 | ... L20: =IFERROR('Historical FS'!L27,0) -> 0.090555915 | N20: =IFERROR('The 3-Statement Projection'!D19/'The 3-Statement Projection'!D6,0) -> 0.1605056 | O20: =IFERROR('The 3-Statement Projection'!E19/'The 3-Statement Projection'!E6,0) -> 0.14268959 | P20: =IFERROR('The 3-Statement Projection'!F19/'The 3-Statement Projection'!F6,0) -> 0.14411782 | Q20: =IFERROR('The 3-Statement Projection'!G19/'The 3-Statement Projection'!G6,0) -> 0.14553175 | R20: =IFERROR('The 3-Statement Projection'!H19/'The 3-Statement Projection'!H6,0) -> 0.14493103 | S20: =IFERROR('The 3-Statement Projection'!I19/'The 3-Statement Projection'!I6,0) -> 0.14431529 | T20: =IFERROR('The 3-Statement Projection'!J19/'The 3-Statement Projection'!J6,0) -> 0.14368416 | U20: =IFERROR('The 3-Statement Projection'!K19/'The 3-Statement Projection'!K6,0) -> 0.14303726 | V20: Operating Income % Sales = EBIT / Net Sales | W20: Identical to EBIT Margin. Operating income tracks EBIT directly in this model. See EBIT Margin (Row 14) interpretation — FY25 at 9.1%, below mid-cycle.
B22: 3. Liquidity & Leverage Ratios
B23: Current Ratio | C23: =IFERROR('Historical FS'!C94/'Historical FS'!C70,0) -> 0.24452555 | D23: =IFERROR('Historical FS'!D94/'Historical FS'!D70,0) -> 1.1674261 | E23: =IFERROR('Historical FS'!E94/'Historical FS'!E70,0) -> 3.3342977 | F23: =IFERROR('Historical FS'!F94/'Historical FS'!F70,0) -> 2.1922508 | G23: =IFERROR('Historical FS'!G94/'Historical FS'!G70,0) -> 1.9633315 | H23: =IFERROR('Historical FS'!H94/'Historical FS'!H70,0) -> 4.8314249 | I23: =IFERROR('Historical FS'!I94/'Historical FS'!I70,0) -> 2.1139265 | J23: =IFERROR('Historical FS'!J94/'Historical FS'!J70,0) -> 1.137743 | ... L23: =IFERROR('Historical FS'!L94/'Historical FS'!L70,0) -> 1.0152172 | N23: =IFERROR('The 3-Statement Projection'!D70/'The 3-Statement Projection'!D49,0) -> 1.129856 | O23: =IFERROR('The 3-Statement Projection'!E70/'The 3-Statement Projection'!E49,0) -> 1.6688764 | P23: =IFERROR('The 3-Statement Projection'!F70/'The 3-Statement Projection'!F49,0) -> 2.7621392 | Q23: =IFERROR('The 3-Statement Projection'!G70/'The 3-Statement Projection'!G49,0) -> 3.2788446 | R23: =IFERROR('The 3-Statement Projection'!H70/'The 3-Statement Projection'!H49,0) -> 3.7980058 | S23: =IFERROR('The 3-Statement Projection'!I70/'The 3-Statement Projection'!I49,0) -> 4.3110794 | T23: =IFERROR('The 3-Statement Projection'!J70/'The 3-Statement Projection'!J49,0) -> 4.7502695 | U23: =IFERROR('The 3-Statement Projection'!K70/'The 3-Statement Projection'!K49,0) -> 5.1947827 | V23: Current Ratio = Total Current Assets / Total Current Liabilities | W23: Current ratio eased to 1.02x in FY25 (from 1.08x FY24), reflecting the ₹109 Cr short-term borrowings reappearing on the liability side. Still above 1.0x comfort threshold, but tighter than the FY21 peak of 4.8x when cash was abundant.
B24: Quick Ratio | C24: =IFERROR(('Historical FS'!C94-'Historical FS'!C89)/'Historical FS'!C70,0) -> 0.045506387 | D24: =IFERROR(('Historical FS'!D94-'Historical FS'!D89)/'Historical FS'!D70,0) -> 0.69508405 | E24: =IFERROR(('Historical FS'!E94-'Historical FS'!E89)/'Historical FS'!E70,0) -> 2.5418776 | F24: =IFERROR(('Historical FS'!F94-'Historical FS'!F89)/'Historical FS'!F70,0) -> 0.89365637 | G24: =IFERROR(('Historical FS'!G94-'Historical FS'!G89)/'Historical FS'!G70,0) -> 0.70324304 | H24: =IFERROR(('Historical FS'!H94-'Historical FS'!H89)/'Historical FS'!H70,0) -> 2.7141645 | I24: =IFERROR(('Historical FS'!I94-'Historical FS'!I89)/'Historical FS'!I70,0) -> 0.83250855 | J24: =IFERROR(('Historical FS'!J94-'Historical FS'!J89)/'Historical FS'!J70,0) -> 0.34305692 | ... L24: =IFERROR(('Historical FS'!L94-'Historical FS'!L89)/'Historical FS'!L70,0) -> 0.57180895 | N24: =IFERROR(('The 3-Statement Projection'!D70-'The 3-Statement Projection'!D65)/'The 3-Statement Projection'!D49,0) -> 0.70713655 | O24: =IFERROR(('The 3-Statement Projection'!E70-'The 3-Statement Projection'!E65)/'The 3-Statement Projection'!E49,0) -> 1.0234682 | P24: =IFERROR(('The 3-Statement Projection'!F70-'The 3-Statement Projection'!F65)/'The 3-Statement Projection'!F49,0) -> 2.0829472 | Q24: =IFERROR(('The 3-Statement Projection'!G70-'The 3-Statement Projection'!G65)/'The 3-Statement Projection'!G49,0) -> 2.6002071 | R24: =IFERROR(('The 3-Statement Projection'!H70-'The 3-Statement Projection'!H65)/'The 3-Statement Projection'!H49,0) -> 3.1193683 | S24: =IFERROR(('The 3-Statement Projection'!I70-'The 3-Statement Projection'!I65)/'The 3-Statement Projection'!I49,0) -> 3.6324419 | T24: =IFERROR(('The 3-Statement Projection'!J70-'The 3-Statement Projection'!J65)/'The 3-Statement Projection'!J49,0) -> 4.071632 | U24: =IFERROR(('The 3-Statement Projection'!K70-'The 3-Statement Projection'!K65)/'The 3-Statement Projection'!K49,0) -> 4.5161452 | V24: Quick Ratio = (Total Current Assets − Inventories) / Total Current Liabilities | W24: Quick ratio edged up to 0.57x in FY25 (from 0.56x FY24), still below the 1.0x comfort level. Inventory remains a large share of current assets (17% of total assets in FY25 vs 18% FY24).
B25: Debt to Equity Ratio | C25: =IFERROR(('Historical FS'!C60+'Historical FS'!C67)/'Historical FS'!C56,0) -> 0.046851268 | D25: =IFERROR(('Historical FS'!D60+'Historical FS'!D67)/'Historical FS'!D56,0) -> 4.2989139 | E25: =IFERROR(('Historical FS'!E60+'Historical FS'!E67)/'Historical FS'!E56,0) -> 1.9684583 | F25: =IFERROR(('Historical FS'!F60+'Historical FS'!F67)/'Historical FS'!F56,0) -> 1.3981018 | G25: =IFERROR(('Historical FS'!G60+'Historical FS'!G67)/'Historical FS'!G56,0) -> 1.3980004 | H25: =IFERROR(('Historical FS'!H60+'Historical FS'!H67)/'Historical FS'!H56,0) -> 1.1477448 | I25: =IFERROR(('Historical FS'!I60+'Historical FS'!I67)/'Historical FS'!I56,0) -> 0.87836643 | J25: =IFERROR(('Historical FS'!J60+'Historical FS'!J67)/'Historical FS'!J56,0) -> 0.48233454 | ... L25: =IFERROR(('Historical FS'!L60+'Historical FS'!L67)/'Historical FS'!L56,0) -> 0.48718656 | N25: =IFERROR(('The 3-Statement Projection'!D39+'The 3-Statement Projection'!D45+'The 3-Statement Projection'!D46)/'The 3-Statement Projection'!D36,0) -> 0.80166062 | O25: =IFERROR(('The 3-Statement Projection'!E39+'The 3-Statement Projection'!E45+'The 3-Statement Projection'!E46)/'The 3-Statement Projection'!E36,0) -> 0.46896985 | P25: =IFERROR(('The 3-Statement Projection'!F39+'The 3-Statement Projection'!F45+'The 3-Statement Projection'!F46)/'The 3-Statement Projection'!F36,0) -> 0.34154907 | Q25: =IFERROR(('The 3-Statement Projection'!G39+'The 3-Statement Projection'!G45+'The 3-Statement Projection'!G46)/'The 3-Statement Projection'!G36,0) -> 0.26193046 | R25: =IFERROR(('The 3-Statement Projection'!H39+'The 3-Statement Projection'!H45+'The 3-Statement Projection'!H46)/'The 3-Statement Projection'!H36,0) -> 0.19935347 | S25: =IFERROR(('The 3-Statement Projection'!I39+'The 3-Statement Projection'!I45+'The 3-Statement Projection'!I46)/'The 3-Statement Projection'!I36,0) -> 0.14882423 | T25: =IFERROR(('The 3-Statement Projection'!J39+'The 3-Statement Projection'!J45+'The 3-Statement Projection'!J46)/'The 3-Statement Projection'!J36,0) -> 0.10724597 | U25: =IFERROR(('The 3-Statement Projection'!K39+'The 3-Statement Projection'!K45+'The 3-Statement Projection'!K46)/'The 3-Statement Projection'!K36,0) -> 0.072497134 | V25: Debt to Equity = (LT Borrowings + ST Borrowings) / Total Equity | W25: D/E re-levered to 0.49x in FY25A (from 0.36x FY24) as FY25 saw a ₹113 Cr net Bank TL drawdown + ₹114 Cr net Buyers Credit drawdown to fund Battery-2 commissioning. Forward trajectory: rapid deleveraging as BC runs off completely by FY28 and Bank TL amortizes. D/E drops to ~0.23x by FY29E. Net Debt turns negative in FY28.
B26: Interest Coverage Ratio | C26: =IFERROR('Historical FS'!C26/'Historical FS'!C29,0) -> -3.6809882 | D26: =IFERROR('Historical FS'!D26/'Historical FS'!D29,0) -> 1.5146199 | E26: =IFERROR('Historical FS'!E26/'Historical FS'!E29,0) -> 2.2637198 | F26: =IFERROR('Historical FS'!F26/'Historical FS'!F29,0) -> 2.0677782 | G26: =IFERROR('Historical FS'!G26/'Historical FS'!G29,0) -> 0.63458937 | H26: =IFERROR('Historical FS'!H26/'Historical FS'!H29,0) -> 2.5039246 | I26: =IFERROR('Historical FS'!I26/'Historical FS'!I29,0) -> 10.174735 | J26: =IFERROR('Historical FS'!J26/'Historical FS'!J29,0) -> 7.1831325 | ... L26: =IFERROR('Historical FS'!L26/'Historical FS'!L29,0) -> 5.0569979 | N26: =IFERROR('The 3-Statement Projection'!D19/'The 3-Statement Projection'!D21,0) -> 5.6278393 | O26: =IFERROR('The 3-Statement Projection'!E19/'The 3-Statement Projection'!E21,0) -> 6.7629354 | P26: =IFERROR('The 3-Statement Projection'!F19/'The 3-Statement Projection'!F21,0) -> 8.9549228 | Q26: =IFERROR('The 3-Statement Projection'!G19/'The 3-Statement Projection'!G21,0) -> 10.266555 | R26: =IFERROR('The 3-Statement Projection'!H19/'The 3-Statement Projection'!H21,0) -> 11.759504 | S26: =IFERROR('The 3-Statement Projection'!I19/'The 3-Statement Projection'!I21,0) -> 13.770546 | T26: =IFERROR('The 3-Statement Projection'!J19/'The 3-Statement Projection'!J21,0) -> 16.638953 | U26: =IFERROR('The 3-Statement Projection'!K19/'The 3-Statement Projection'!K21,0) -> 21.063326 | V26: Interest Coverage = EBIT / Finance Costs | W26: Interest coverage improved to 5.06x in FY25A (from 3.55x FY24) as EBIT growth outpaced interest expense increase. Forward trajectory strengthens sharply to 10.7x by FY29E as Buyers Credit amortizes and EBITDA expands. Well above the 3.0x covenant threshold in all periods.
B28: 4. Return / Performance Ratios
B30: Return on Capital Employed | C30: =IFERROR('Historical FS'!C26/('Historical FS'!C56+'Historical FS'!C63),0) -> -0.39876658 | D30: =IFERROR('Historical FS'!D26/('Historical FS'!D56+'Historical FS'!D63),0) -> 0.12919992 | E30: =IFERROR('Historical FS'!E26/('Historical FS'!E56+'Historical FS'!E63),0) -> 0.1735422 | F30: =IFERROR('Historical FS'!F26/('Historical FS'!F56+'Historical FS'!F63),0) -> 0.15312764 | G30: =IFERROR('Historical FS'!G26/('Historical FS'!G56+'Historical FS'!G63),0) -> 0.045923647 | H30: =IFERROR('Historical FS'!H26/('Historical FS'!H56+'Historical FS'!H63),0) -> 0.1635499 | I30: =IFERROR('Historical FS'!I26/('Historical FS'!I56+'Historical FS'!I63),0) -> 0.31029422 | J30: =IFERROR('Historical FS'!J26/('Historical FS'!J56+'Historical FS'!J63),0) -> 0.21039259 | ... L30: =IFERROR('Historical FS'!L26/('Historical FS'!L56+'Historical FS'!L63),0) -> 0.14702029 | N30: =IFERROR('The 3-Statement Projection'!D19/('The 3-Statement Projection'!D36+'The 3-Statement Projection'!D42),0) -> 0.26225183 | O30: =IFERROR('The 3-Statement Projection'!E19/('The 3-Statement Projection'!E36+'The 3-Statement Projection'!E42),0) -> 0.22886099 | P30: =IFERROR('The 3-Statement Projection'!F19/('The 3-Statement Projection'!F36+'The 3-Statement Projection'!F42),0) -> 0.21680431 | Q30: =IFERROR('The 3-Statement Projection'!G19/('The 3-Statement Projection'!G36+'The 3-Statement Projection'!G42),0) -> 0.20579064 | R30: =IFERROR('The 3-Statement Projection'!H19/('The 3-Statement Projection'!H36+'The 3-Statement Projection'!H42),0) -> 0.19323932 | S30: =IFERROR('The 3-Statement Projection'!I19/('The 3-Statement Projection'!I36+'The 3-Statement Projection'!I42),0) -> 0.18196167 | T30: =IFERROR('The 3-Statement Projection'!J19/('The 3-Statement Projection'!J36+'The 3-Statement Projection'!J42),0) -> 0.17176526 | U30: =IFERROR('The 3-Statement Projection'!K19/('The 3-Statement Projection'!K36+'The 3-Statement Projection'!K42),0) -> 0.16249584 | V30: ROCE = EBIT / (Total Equity + Total Non-Current Liabilities) | W30: ROCE improved to 14.7% in FY25 (from 11.7% FY24), well above cost of capital (~12.75% WACC). EBIT grew faster than the invested capital base as Battery-2 began generating returns. Still below FY22 peak of 31% but the trajectory is encouraging.
B31: Retained Earnings % | C31: - | D31: =IFERROR(('Historical FS'!D54-'Historical FS'!C54)/'Historical FS'!D42,0) -> -0.12453455 | E31: =IFERROR(('Historical FS'!E54-'Historical FS'!D54)/'Historical FS'!E42,0) -> 2.084135 | F31: =IFERROR(('Historical FS'!F54-'Historical FS'!E54)/'Historical FS'!F42,0) -> 1.0004986 | G31: =IFERROR(('Historical FS'!G54-'Historical FS'!F54)/'Historical FS'!G42,0) -> 1.0051064 | H31: =IFERROR(('Historical FS'!H54-'Historical FS'!G54)/'Historical FS'!H42,0) -> 0.99965434 | I31: =IFERROR(('Historical FS'!I54-'Historical FS'!H54)/'Historical FS'!I42,0) -> 0.9998325 | J31: =IFERROR(('Historical FS'!J54-'Historical FS'!I54)/'Historical FS'!J42,0) -> 0.99957571 | K31: =IFERROR(('Historical FS'!K54-'Historical FS'!J54)/'Historical FS'!K42,0) -> 0.99949759 | L31: =IFERROR(('Historical FS'!L54-'Historical FS'!K54)/'Historical FS'!L42,0) -> -0.31928447 | N31: =IFERROR(('The 3-Statement Projection'!D35-'The 3-Statement Projection'!C35)/'The 3-Statement Projection'!D27,0) -> -0.1453099 | O31: =IFERROR(('The 3-Statement Projection'!E35-'The 3-Statement Projection'!D35)/'The 3-Statement Projection'!E27,0) -> 0.64528876 | P31: =IFERROR(('The 3-Statement Projection'!F35-'The 3-Statement Projection'!E35)/'The 3-Statement Projection'!F27,0) -> 0.64803803 | Q31: =IFERROR(('The 3-Statement Projection'!G35-'The 3-Statement Projection'!F35)/'The 3-Statement Projection'!G27,0) -> 0.64935622 | R31: =IFERROR(('The 3-Statement Projection'!H35-'The 3-Statement Projection'!G35)/'The 3-Statement Projection'!H27,0) -> 0.64983362 | S31: =IFERROR(('The 3-Statement Projection'!I35-'The 3-Statement Projection'!H35)/'The 3-Statement Projection'!I27,0) -> 0.65029424 | T31: =IFERROR(('The 3-Statement Projection'!J35-'The 3-Statement Projection'!I35)/'The 3-Statement Projection'!J27,0) -> 0.65074086 | U31: =IFERROR(('The 3-Statement Projection'!K35-'The 3-Statement Projection'!J35)/'The 3-Statement Projection'!K27,0) -> 0.65117388 | V31: Retained Earnings % = (Reserves CY − Reserves PY) / Profit After Tax | W31: Retention turned NEGATIVE at -31.9% in FY25 — the first meaningful dividend payout in the company's history. Reserves declined as dividends exceeded retained earnings. Signals management confidence post-expansion; previously ~100% retention through the deleveraging years.
B32: Return on Equity (ROE) | C32: =IFERROR('Historical FS'!C42/'Historical FS'!C56,0) -> -0.37469331 | D32: =IFERROR('Historical FS'!D42/'Historical FS'!D56,0) -> 0.18230502 | E32: =IFERROR('Historical FS'!E42/'Historical FS'!E56,0) -> 0.22710841 | F32: =IFERROR('Historical FS'!F42/'Historical FS'!F56,0) -> 0.1374289 | G32: =IFERROR('Historical FS'!G42/'Historical FS'!G56,0) -> -0.041956793 | H32: =IFERROR('Historical FS'!H42/'Historical FS'!H56,0) -> 0.17124423 | I32: =IFERROR('Historical FS'!I42/'Historical FS'!I56,0) -> 0.41413336 | J32: =IFERROR('Historical FS'!J42/'Historical FS'!J56,0) -> 0.22247694 | ... L32: =IFERROR('Historical FS'!L42/'Historical FS'!L56,0) -> 0.14368104 | N32: =IFERROR('The 3-Statement Projection'!D27/'The 3-Statement Projection'!D36,0) -> 0.29525938 | O32: =IFERROR('The 3-Statement Projection'!E27/'The 3-Statement Projection'!E36,0) -> 0.22353804 | P32: =IFERROR('The 3-Statement Projection'!F27/'The 3-Statement Projection'!F36,0) -> 0.20421697 | Q32: =IFERROR('The 3-Statement Projection'!G27/'The 3-Statement Projection'!G36,0) -> 0.18443767 | R32: =IFERROR('The 3-Statement Projection'!H27/'The 3-Statement Projection'!H36,0) -> 0.16609613 | S32: =IFERROR('The 3-Statement Projection'!I27/'The 3-Statement Projection'!I36,0) -> 0.15115732 | T32: =IFERROR('The 3-Statement Projection'!J27/'The 3-Statement Projection'!J36,0) -> 0.13875551 | U32: =IFERROR('The 3-Statement Projection'!K27/'The 3-Statement Projection'!K36,0) -> 0.1282916 | V32: ROE = Profit After Tax / Total Equity | W32: ROE at 14.4% in FY25 (up from 11.8% FY24) benefits from a slightly smaller equity base (dividends paid) and growing PAT. Cyclically recovering. Far from FY22 peak of 41% but trending in the right direction as the expanded capacity ramps.
B33: Self Sustained Growth Rate | C33: - | D33: =IFERROR(D32*D31,0) -> -0.022703273 | E33: =IFERROR(E32*E31,0) -> 0.47332459 | F33: =IFERROR(F32*F31,0) -> 0.13749743 | G33: =IFERROR(G32*G31,0) -> -0.042171041 | H33: =IFERROR(H32*H31,0) -> 0.17118504 | I33: =IFERROR(I32*I31,0) -> 0.41406399 | J33: =IFERROR(J32*J31,0) -> 0.22238254 | K33: =IFERROR(K32*K31,0) -> 0.11827164 | L33: =IFERROR(L32*L31,0) -> -0.045875125 | N33: =IFERROR(N32*N31,0) -> -0.042904111 | O33: =IFERROR(O32*O31,0) -> 0.14424658 | P33: =IFERROR(P32*P31,0) -> 0.13234036 | Q33: =IFERROR(Q32*Q31,0) -> 0.11976575 | R33: =IFERROR(R32*R31,0) -> 0.10793485 | S33: =IFERROR(S32*S31,0) -> 0.098296735 | T33: =IFERROR(T32*T31,0) -> 0.090293878 | U33: =IFERROR(U32*U31,0) -> 0.083540142 | V33: Self Sustained Growth = ROE × Retained Earnings % | W33: SSGR turned negative at -4.6% in FY25 — with dividends being paid, self-funded growth mathematically goes negative. The company can now grow ₹X via new debt rather than retained earnings. Regime change from the FY18-24 100%-retention era.
B35: 5. Efficiency & Turnover Ratios
B36: Debtor Turnover Ratio | C36: =IFERROR('Historical FS'!C5/'Historical FS'!C90,0) -> 19.695437 | D36: =IFERROR('Historical FS'!D5/'Historical FS'!D90,0) -> 24.349036 | E36: =IFERROR('Historical FS'!E5/'Historical FS'!E90,0) -> 25.893878 | F36: =IFERROR('Historical FS'!F5/'Historical FS'!F90,0) -> 72.476411 | G36: =IFERROR('Historical FS'!G5/'Historical FS'!G90,0) -> 88.573256 | H36: =IFERROR('Historical FS'!H5/'Historical FS'!H90,0) -> 15.961112 | I36: =IFERROR('Historical FS'!I5/'Historical FS'!I90,0) -> 11.408653 | J36: =IFERROR('Historical FS'!J5/'Historical FS'!J90,0) -> 53.065495 | ... L36: =IFERROR('Historical FS'!L5/'Historical FS'!L90,0) -> 16.396478 | N36: =IFERROR('The 3-Statement Projection'!D6/'The 3-Statement Projection'!D65,0) -> 11.012025 | O36: =IFERROR('The 3-Statement Projection'!E6/'The 3-Statement Projection'!E65,0) -> 11.279886 | P36: =IFERROR('The 3-Statement Projection'!F6/'The 3-Statement Projection'!F65,0) -> 11.591257 | Q36: =IFERROR('The 3-Statement Projection'!G6/'The 3-Statement Projection'!G65,0) -> 11.62078 | R36: =IFERROR('The 3-Statement Projection'!H6/'The 3-Statement Projection'!H65,0) -> 11.62078 | S36: =IFERROR('The 3-Statement Projection'!I6/'The 3-Statement Projection'!I65,0) -> 11.62078 | T36: =IFERROR('The 3-Statement Projection'!J6/'The 3-Statement Projection'!J65,0) -> 11.62078 | U36: =IFERROR('The 3-Statement Projection'!K6/'The 3-Statement Projection'!K65,0) -> 11.62078 | V36: Debtor Turnover = Net Sales / Trade Receivables | W36: Debtor turnover 16.4x in FY25 (= 22 days, vs 18 days FY24) — collection slightly slower as revenue scaled. Still well-managed; within tight range of 15-20x typical for this business.
B37: Creditor Turnover Ratio | C37: =IFERROR('Historical FS'!C8/'Historical FS'!C68,0) -> 2.5479876 | D37: =IFERROR('Historical FS'!D8/'Historical FS'!D68,0) -> 2.1796541 | E37: =IFERROR('Historical FS'!E8/'Historical FS'!E68,0) -> 13.719799 | F37: =IFERROR('Historical FS'!F8/'Historical FS'!F68,0) -> 11.579957 | G37: =IFERROR('Historical FS'!G8/'Historical FS'!G68,0) -> 8.761585 | H37: =IFERROR('Historical FS'!H8/'Historical FS'!H68,0) -> 52.714154 | I37: =IFERROR('Historical FS'!I8/'Historical FS'!I68,0) -> 2.2571532 | J37: =IFERROR('Historical FS'!J8/'Historical FS'!J68,0) -> 5.5939467 | ... L37: =IFERROR('Historical FS'!L8/'Historical FS'!L68,0) -> 4.2681169 | N37: =IFERROR('The 3-Statement Projection'!D9/'The 3-Statement Projection'!D47,0) -> 9.125 | O37: =IFERROR('The 3-Statement Projection'!E9/'The 3-Statement Projection'!E47,0) -> 9.125 | P37: =IFERROR('The 3-Statement Projection'!F9/'The 3-Statement Projection'!F47,0) -> 9.125 | Q37: =IFERROR('The 3-Statement Projection'!G9/'The 3-Statement Projection'!G47,0) -> 9.125 | R37: =IFERROR('The 3-Statement Projection'!H9/'The 3-Statement Projection'!H47,0) -> 9.125 | S37: =IFERROR('The 3-Statement Projection'!I9/'The 3-Statement Projection'!I47,0) -> 9.125 | T37: =IFERROR('The 3-Statement Projection'!J9/'The 3-Statement Projection'!J47,0) -> 9.125 | U37: =IFERROR('The 3-Statement Projection'!K9/'The 3-Statement Projection'!K47,0) -> 9.125 | V37: Creditor Turnover = COGS / Trade Payables & Acceptances | W37: Creditor turnover 4.3x in FY25 (= 86 days, vs 169 days FY24) — MAJOR shift. Trade payables roughly halved in length as supplier terms tightened. This is a structural working-capital headwind that compressed CFO.
B38: Inventory Turnover | C38: =IFERROR('Historical FS'!C8/'Historical FS'!C89,0) -> 3.2228271 | D38: =IFERROR('Historical FS'!D8/'Historical FS'!D89,0) -> 3.2935727 | E38: =IFERROR('Historical FS'!E8/'Historical FS'!E89,0) -> 12.460022 | F38: =IFERROR('Historical FS'!F8/'Historical FS'!F89,0) -> 5.3731396 | G38: =IFERROR('Historical FS'!G8/'Historical FS'!G89,0) -> 4.8660525 | H38: =IFERROR('Historical FS'!H8/'Historical FS'!H89,0) -> 5.7069604 | I38: =IFERROR('Historical FS'!I8/'Historical FS'!I89,0) -> 1.3375765 | J38: =IFERROR('Historical FS'!J8/'Historical FS'!J89,0) -> 5.8801999 | ... L38: =IFERROR('Historical FS'!L8/'Historical FS'!L89,0) -> 4.9019602 | N38: =IFERROR('The 3-Statement Projection'!D9/'The 3-Statement Projection'!D65,0) -> 8.4883721 | O38: =IFERROR('The 3-Statement Projection'!E9/'The 3-Statement Projection'!E65,0) -> 8.902439 | P38: =IFERROR('The 3-Statement Projection'!F9/'The 3-Statement Projection'!F65,0) -> 9.125 | Q38: =IFERROR('The 3-Statement Projection'!G9/'The 3-Statement Projection'!G65,0) -> 9.125 | R38: =IFERROR('The 3-Statement Projection'!H9/'The 3-Statement Projection'!H65,0) -> 9.125 | S38: =IFERROR('The 3-Statement Projection'!I9/'The 3-Statement Projection'!I65,0) -> 9.125 | T38: =IFERROR('The 3-Statement Projection'!J9/'The 3-Statement Projection'!J65,0) -> 9.125 | U38: =IFERROR('The 3-Statement Projection'!K9/'The 3-Statement Projection'!K65,0) -> 9.125 | V38: Inventory Turnover = COGS / Inventories | W38: Inventory turnover 4.9x in FY25 (= 74 days, vs 93 days FY24) — modest improvement. Inventory days have normalised from the FY22 peak of 273 days when the company stockpiled heavily. Current level is efficient for a coke producer.
B39: Fixed Asset Turnover | C39: =IFERROR('Historical FS'!C5/'Historical FS'!C80,0) -> 0.7793513 | D39: =IFERROR('Historical FS'!D5/'Historical FS'!D80,0) -> 1.5146516 | E39: =IFERROR('Historical FS'!E5/'Historical FS'!E80,0) -> 1.7612787 | F39: =IFERROR('Historical FS'!F5/'Historical FS'!F80,0) -> 1.923955 | G39: =IFERROR('Historical FS'!G5/'Historical FS'!G80,0) -> 1.5219685 | H39: =IFERROR('Historical FS'!H5/'Historical FS'!H80,0) -> 1.5452908 | I39: =IFERROR('Historical FS'!I5/'Historical FS'!I80,0) -> 2.5183698 | J39: =IFERROR('Historical FS'!J5/'Historical FS'!J80,0) -> 4.2097326 | ... L39: =IFERROR('Historical FS'!L5/'Historical FS'!L80,0) -> 2.3765033 | N39: =IFERROR('The 3-Statement Projection'!D6/'The 3-Statement Projection'!D57,0) -> 2.2064026 | O39: =IFERROR('The 3-Statement Projection'!E6/'The 3-Statement Projection'!E57,0) -> 2.387164 | P39: =IFERROR('The 3-Statement Projection'!F6/'The 3-Statement Projection'!F57,0) -> 2.4514674 | Q39: =IFERROR('The 3-Statement Projection'!G6/'The 3-Statement Projection'!G57,0) -> 2.5213129 | R39: =IFERROR('The 3-Statement Projection'!H6/'The 3-Statement Projection'!H57,0) -> 2.5974107 | S39: =IFERROR('The 3-Statement Projection'!I6/'The 3-Statement Projection'!I57,0) -> 2.6805985 | T39: =IFERROR('The 3-Statement Projection'!J6/'The 3-Statement Projection'!J57,0) -> 2.7718701 | U39: =IFERROR('The 3-Statement Projection'!K6/'The 3-Statement Projection'!K57,0) -> 2.8724149 | V39: Fixed Asset Turnover = Net Sales / Net Fixed Assets | W39: FAT fell to 2.4x in FY25 (from 3.4x FY24) as Battery-2 capitalisation added ₹433 Cr to Net Fixed Assets (up from ~₹461 Cr to ~₹786 Cr). The ratio will re-expand as the new capacity drives revenue.
B40: Capital Turnover Ratio | C40: =IFERROR('Historical FS'!C5/'Historical FS'!C56,0) -> 4.1857694 | D40: =IFERROR('Historical FS'!D5/'Historical FS'!D56,0) -> 4.9513501 | E40: =IFERROR('Historical FS'!E5/'Historical FS'!E56,0) -> 3.5282247 | F40: =IFERROR('Historical FS'!F5/'Historical FS'!F56,0) -> 3.2108545 | G40: =IFERROR('Historical FS'!G5/'Historical FS'!G56,0) -> 2.7199786 | H40: =IFERROR('Historical FS'!H5/'Historical FS'!H56,0) -> 2.2594412 | I40: =IFERROR('Historical FS'!I5/'Historical FS'!I56,0) -> 2.1539235 | J40: =IFERROR('Historical FS'!J5/'Historical FS'!J56,0) -> 2.6877663 | ... L40: =IFERROR('Historical FS'!L5/'Historical FS'!L56,0) -> 2.3462011 | N40: =IFERROR('The 3-Statement Projection'!D6/'The 3-Statement Projection'!D36,0) -> 2.7211627 | O40: =IFERROR('The 3-Statement Projection'!E6/'The 3-Statement Projection'!E36,0) -> 2.4567632 | P40: =IFERROR('The 3-Statement Projection'!F6/'The 3-Statement Projection'!F36,0) -> 2.1316342 | Q40: =IFERROR('The 3-Statement Projection'!G6/'The 3-Statement Projection'!G36,0) -> 1.8763375 | R40: =IFERROR('The 3-Statement Projection'!H6/'The 3-Statement Projection'!H36,0) -> 1.6738153 | S40: =IFERROR('The 3-Statement Projection'!I6/'The 3-Statement Projection'!I36,0) -> 1.5092847 | T40: =IFERROR('The 3-Statement Projection'!J6/'The 3-Statement Projection'!J36,0) -> 1.3730055 | U40: =IFERROR('The 3-Statement Projection'!K6/'The 3-Statement Projection'!K36,0) -> 1.2583044 | V40: Capital Turnover = Net Sales / Total Equity | W40: Capital turnover 2.3x in FY25 (vs 1.9x FY24) — improved as revenue grew on a shrinking equity base (dividends paid). Mechanical improvement rather than operational — watch for sustained uplift as Battery-2 ramps.
B43: 6. Operating Cycle Ratios
B44: Debtor Days | C44: =IFERROR(365/C36,0) -> 18.532211 | D44: =IFERROR(365/D36,0) -> 14.990327 | E44: =IFERROR(365/E36,0) -> 14.095996 | F44: =IFERROR(365/F36,0) -> 5.0361213 | G44: =IFERROR(365/G36,0) -> 4.1208827 | H44: =IFERROR(365/H36,0) -> 22.86808 | I44: =IFERROR(365/I36,0) -> 31.993261 | J44: =IFERROR(365/J36,0) -> 6.8782925 | ... L44: =IFERROR(365/L36,0) -> 22.260879 | N44: =IFERROR(365/N36,0) -> 33.145585 | O44: =IFERROR(365/O36,0) -> 32.358483 | P44: =IFERROR(365/P36,0) -> 31.489252 | Q44: =IFERROR(365/Q36,0) -> 31.409252 | R44: =IFERROR(365/R36,0) -> 31.409252 | S44: =IFERROR(365/S36,0) -> 31.409252 | T44: =IFERROR(365/T36,0) -> 31.409252 | U44: =IFERROR(365/U36,0) -> 31.409252 | V44: Debtor Days = 365 / Debtor Turnover Ratio | W44: Debtor days lengthened to 22 in FY25 (from 18 days FY24). Still very tight — well-managed working capital. Historical range 4-32 days; current level is middle-of-pack and not a concern.
B45: Payable Days | C45: =IFERROR(365/C37,0) -> 143.2503 | D45: =IFERROR(365/D37,0) -> 167.45776 | E45: =IFERROR(365/E37,0) -> 26.603888 | F45: =IFERROR(365/F37,0) -> 31.519979 | G45: =IFERROR(365/G37,0) -> 41.659129 | H45: =IFERROR(365/H37,0) -> 6.9241366 | I45: =IFERROR(365/I37,0) -> 161.70812 | J45: =IFERROR(365/J37,0) -> 65.249102 | ... L45: =IFERROR(365/L37,0) -> 85.517807 | N45: =IFERROR(365/N37,0) -> 40 | O45: =IFERROR(365/O37,0) -> 40 | P45: =IFERROR(365/P37,0) -> 40 | Q45: =IFERROR(365/Q37,0) -> 40 | R45: =IFERROR(365/R37,0) -> 40 | S45: =IFERROR(365/S37,0) -> 40 | T45: =IFERROR(365/T37,0) -> 40 | U45: =IFERROR(365/U37,0) -> 40 | V45: Payable Days = 365 / Creditor Turnover Ratio | W45: Payable days halved to 86 in FY25 (from 169 days FY24). Suppliers tightened credit terms — this is a structural working capital headwind. The FY24 number was anomalously long; FY25 is closer to industry norms.
B46: Inventory Days | C46: =IFERROR(365/C38,0) -> 113.2546 | D46: =IFERROR(365/D38,0) -> 110.8219 | E46: =IFERROR(365/E38,0) -> 29.293688 | F46: =IFERROR(365/F38,0) -> 67.930488 | G46: =IFERROR(365/G38,0) -> 75.009466 | H46: =IFERROR(365/H38,0) -> 63.956988 | I46: =IFERROR(365/I38,0) -> 272.8816 | J46: =IFERROR(365/J38,0) -> 62.07272 | ... L46: =IFERROR(365/L38,0) -> 74.460009 | N46: =IFERROR(365/N38,0) -> 43 | O46: =IFERROR(365/O38,0) -> 41 | P46: =IFERROR(365/P38,0) -> 40 | Q46: =IFERROR(365/Q38,0) -> 40 | R46: =IFERROR(365/R38,0) -> 40 | S46: =IFERROR(365/S38,0) -> 40 | T46: =IFERROR(365/T38,0) -> 40 | U46: =IFERROR(365/U38,0) -> 40 | V46: Inventory Days = 365 / Inventory Turnover Ratio | W46: Inventory days eased to 74 in FY25 (from 93 days FY24), improving efficiency. Down sharply from the FY22 extreme of 273 days. Appropriate level for a coke manufacturer running at elevated utilisation.
B47: Cash Conversion Cycle | C47: =IFERROR(C44+C46-C45,0) -> -11.463492 | D47: =IFERROR(D44+D46-D45,0) -> -41.645529 | E47: =IFERROR(E44+E46-E45,0) -> 16.785796 | F47: =IFERROR(F44+F46-F45,0) -> 41.446631 | G47: =IFERROR(G44+G46-G45,0) -> 37.47122 | H47: =IFERROR(H44+H46-H45,0) -> 79.900932 | I47: =IFERROR(I44+I46-I45,0) -> 143.16674 | J47: =IFERROR(J44+J46-J45,0) -> 3.70191 | ... L47: =IFERROR(L44+L46-L45,0) -> 11.203081 | N47: =IFERROR(N44+N46-N45,0) -> 36.145585 | O47: =IFERROR(O44+O46-O45,0) -> 33.358483 | P47: =IFERROR(P44+P46-P45,0) -> 31.489252 | Q47: =IFERROR(Q44+Q46-Q45,0) -> 31.409252 | R47: =IFERROR(R44+R46-R45,0) -> 31.409252 | S47: =IFERROR(S44+S46-S45,0) -> 31.409252 | T47: =IFERROR(T44+T46-T45,0) -> 31.409252 | U47: =IFERROR(U44+U46-U45,0) -> 31.409252 | V47: CCC = Debtor Days + Inventory Days − Payable Days | W47: CCC swung to +11 days in FY25 (from -59 days FY24). The favourable negative-CCC dynamic (paid-before-paying) has reversed as payable days shortened. Working capital now absorbs cash rather than releasing it — this is the key cash flow story of FY25.
B49: 7. Cash Flow Ratios
B50: CFO / Sales | C50: - | D50: =IFERROR('Historical FS'!D118/'Historical FS'!D5,0) -> -0.66908371 | E50: =IFERROR('Historical FS'!E118/'Historical FS'!E5,0) -> 0.21668393 | F50: =IFERROR('Historical FS'!F118/'Historical FS'!F5,0) -> 0.045341045 | G50: =IFERROR('Historical FS'!G118/'Historical FS'!G5,0) -> 0.016068686 | H50: =IFERROR('Historical FS'!H118/'Historical FS'!H5,0) -> 0.03142438 | I50: =IFERROR('Historical FS'!I118/'Historical FS'!I5,0) -> 0.10306265 | J50: =IFERROR('Historical FS'!J118/'Historical FS'!J5,0) -> 0.21590556 | K50: =IFERROR('Historical FS'!K118/'Historical FS'!K5,0) -> 0.21600331 | L50: =IFERROR('Historical FS'!L118/'Historical FS'!L5,0) -> 0.063185007 | N50: =IFERROR('The 3-Statement Projection'!D85/'The 3-Statement Projection'!D6,0) -> 0.063930301 | O50: =IFERROR('The 3-Statement Projection'!E85/'The 3-Statement Projection'!E6,0) -> 0.11441192 | P50: =IFERROR('The 3-Statement Projection'!F85/'The 3-Statement Projection'!F6,0) -> 0.12237266 | Q50: =IFERROR('The 3-Statement Projection'!G85/'The 3-Statement Projection'!G6,0) -> 0.1228225 | R50: =IFERROR('The 3-Statement Projection'!H85/'The 3-Statement Projection'!H6,0) -> 0.1212053 | S50: =IFERROR('The 3-Statement Projection'!I85/'The 3-Statement Projection'!I6,0) -> 0.12237267 | T50: =IFERROR('The 3-Statement Projection'!J85/'The 3-Statement Projection'!J6,0) -> 0.12358252 | U50: =IFERROR('The 3-Statement Projection'!K85/'The 3-Statement Projection'!K6,0) -> 0.12482888 | V50: CFO / Sales = Total CFO / Net Sales | W50: CFO/Sales compressed to 6.3% in FY25 (from 21.6% FY24). Sharp drop reflects the working-capital bleed from payable-day compression. Accounting profits remained strong but cash generation lagged materially — watch this metric in FY26 as WC normalises.
B51: CFO / Total Assets | C51: - | D51: =IFERROR('Historical FS'!D118/'Historical FS'!D96,0) -> -0.46097333 | E51: =IFERROR('Historical FS'!E118/'Historical FS'!E96,0) -> 0.22611117 | F51: =IFERROR('Historical FS'!F118/'Historical FS'!F96,0) -> 0.049796665 | G51: =IFERROR('Historical FS'!G118/'Historical FS'!G96,0) -> 0.014860862 | H51: =IFERROR('Historical FS'!H118/'Historical FS'!H96,0) -> 0.028996193 | I51: =IFERROR('Historical FS'!I118/'Historical FS'!I96,0) -> 0.079236173 | J51: =IFERROR('Historical FS'!J118/'Historical FS'!J96,0) -> 0.2886087 | K51: =IFERROR('Historical FS'!K118/'Historical FS'!K96,0) -> 0.18113523 | L51: =IFERROR('Historical FS'!L118/'Historical FS'!L96,0) -> 0.06297837 | N51: =IFERROR('The 3-Statement Projection'!D85/'The 3-Statement Projection'!D72,0) -> 0.077317763 | O51: =IFERROR('The 3-Statement Projection'!E85/'The 3-Statement Projection'!E72,0) -> 0.15037633 | P51: =IFERROR('The 3-Statement Projection'!F85/'The 3-Statement Projection'!F72,0) -> 0.1545581 | Q51: =IFERROR('The 3-Statement Projection'!G85/'The 3-Statement Projection'!G72,0) -> 0.1472717 | R51: =IFERROR('The 3-Statement Projection'!H85/'The 3-Statement Projection'!H72,0) -> 0.13823436 | S51: =IFERROR('The 3-Statement Projection'!I85/'The 3-Statement Projection'!I72,0) -> 0.13302673 | T51: =IFERROR('The 3-Statement Projection'!J85/'The 3-Statement Projection'!J72,0) -> 0.12828853 | U51: =IFERROR('The 3-Statement Projection'!K85/'The 3-Statement Projection'!K72,0) -> 0.1239545 | V51: CFO / Total Assets = Total CFO / Total Assets | W51: CFO/Assets dropped to 6.3% in FY25 (from 18.1% FY24). Asset base grew (Battery-2) while CFO shrank (WC drag) — double compression. Expect recovery as the expanded capacity drives revenue and WC stabilises.
B52: CFO / Total Debt | C52: - | D52: =IFERROR('Historical FS'!D118/('Historical FS'!D60+'Historical FS'!D67),0) -> -0.770629 | E52: =IFERROR('Historical FS'!E118/('Historical FS'!E60+'Historical FS'!E67),0) -> 0.38837988 | F52: =IFERROR('Historical FS'!F118/('Historical FS'!F60+'Historical FS'!F67),0) -> 0.1041294 | G52: =IFERROR('Historical FS'!G118/('Historical FS'!G60+'Historical FS'!G67),0) -> 0.031263569 | H52: =IFERROR('Historical FS'!H118/('Historical FS'!H60+'Historical FS'!H67),0) -> 0.061861784 | I52: =IFERROR('Historical FS'!I118/('Historical FS'!I60+'Historical FS'!I67),0) -> 0.25272946 | J52: =IFERROR('Historical FS'!J118/('Historical FS'!J60+'Historical FS'!J67),0) -> 1.2031145 | K52: =IFERROR('Historical FS'!K118/('Historical FS'!K60+'Historical FS'!K67),0) -> 1.1100111 | L52: =IFERROR('Historical FS'!L118/('Historical FS'!L60+'Historical FS'!L67),0) -> 0.30428741 | N52: =IFERROR('The 3-Statement Projection'!D85/('The 3-Statement Projection'!D39+'The 3-Statement Projection'!D45+'The 3-Statement Projection'!D46),0) -> 0.21700548 | O52: =IFERROR('The 3-Statement Projection'!E85/('The 3-Statement Projection'!E39+'The 3-Statement Projection'!E45+'The 3-Statement Projection'!E46),0) -> 0.59936261 | P52: =IFERROR('The 3-Statement Projection'!F85/('The 3-Statement Projection'!F39+'The 3-Statement Projection'!F45+'The 3-Statement Projection'!F46),0) -> 0.76373724 | Q52: =IFERROR('The 3-Statement Projection'!G85/('The 3-Statement Projection'!G39+'The 3-Statement Projection'!G45+'The 3-Statement Projection'!G46),0) -> 0.8798383 | R52: =IFERROR('The 3-Statement Projection'!H85/('The 3-Statement Projection'!H39+'The 3-Statement Projection'!H45+'The 3-Statement Projection'!H46),0) -> 1.0176661 | S52: =IFERROR('The 3-Statement Projection'!I85/('The 3-Statement Projection'!I39+'The 3-Statement Projection'!I45+'The 3-Statement Projection'!I46),0) -> 1.2410291 | T52: =IFERROR('The 3-Statement Projection'!J85/('The 3-Statement Projection'!J39+'The 3-Statement Projection'!J45+'The 3-Statement Projection'!J46),0) -> 1.5821524 | U52: =IFERROR('The 3-Statement Projection'!K85/('The 3-Statement Projection'!K39+'The 3-Statement Projection'!K45+'The 3-Statement Projection'!K46),0) -> 2.1666061 | V52: CFO / Total Debt = Total CFO / (LT Borrowings + ST Borrowings) | W52: CFO/Debt fell sharply to 30.4% in FY25 (from 111% FY24). The deleveraging narrative has PAUSED — FY25 saw simultaneous debt increase (Battery-2 funding) and CFO compression (WC). Still acceptable coverage; will recover as operating cash flow rebuilds.

Sheet Common Size Statements
B2: ="Common Size Statements - "&'Executive Summary'!B2 -> Common Size Statements - Jindal Coke Ltd.
B3: ='Historical FS'!B3 -> Years | C3: ='Historical FS'!C3 -> FY16A | D3: ='Historical FS'!D3 -> FY17A | E3: ='Historical FS'!E3 -> FY18A | F3: ='Historical FS'!F3 -> FY19A | G3: ='Historical FS'!G3 -> FY20A | H3: ='Historical FS'!H3 -> FY21A | I3: ='Historical FS'!I3 -> FY22A | ... L3: ='Historical FS'!L3 -> FY25A | M3: ='The 3-Statement Projection'!D3 -> FY26E | N3: ='The 3-Statement Projection'!E3 -> FY27E | O3: ='The 3-Statement Projection'!F3 -> FY28E | P3: ='The 3-Statement Projection'!G3 -> FY29E | Q3: ='The 3-Statement Projection'!H3 -> FY30E | R3: ='The 3-Statement Projection'!I3 -> FY31E | S3: ='The 3-Statement Projection'!J3 -> FY32E | T3: ='The 3-Statement Projection'!K3 -> FY33E
A4: # | B4: ='Historical FS'!B4 -> Income Statement
B5: ='Historical FS'!B5 -> Net Sales | C5: =IFERROR('Historical FS'!C5/'Historical FS'!C5,0) -> 1 | D5: =IFERROR('Historical FS'!D5/'Historical FS'!D5,0) -> 1 | E5: =IFERROR('Historical FS'!E5/'Historical FS'!E5,0) -> 1 | F5: =IFERROR('Historical FS'!F5/'Historical FS'!F5,0) -> 1 | G5: =IFERROR('Historical FS'!G5/'Historical FS'!G5,0) -> 1 | H5: =IFERROR('Historical FS'!H5/'Historical FS'!H5,0) -> 1 | I5: =IFERROR('Historical FS'!I5/'Historical FS'!I5,0) -> 1 | J5: =IFERROR('Historical FS'!J5/'Historical FS'!J5,0) -> 1 | ... L5: =IFERROR('Historical FS'!L5/'Historical FS'!L5,0) -> 1 | M5: =IFERROR('The 3-Statement Projection'!D6/'The 3-Statement Projection'!D$6,0) -> 1 | N5: =IFERROR('The 3-Statement Projection'!E6/'The 3-Statement Projection'!E$6,0) -> 1 | O5: =IFERROR('The 3-Statement Projection'!F6/'The 3-Statement Projection'!F$6,0) -> 1 | P5: =IFERROR('The 3-Statement Projection'!G6/'The 3-Statement Projection'!G$6,0) -> 1 | Q5: =IFERROR('The 3-Statement Projection'!H6/'The 3-Statement Projection'!H$6,0) -> 1 | R5: =IFERROR('The 3-Statement Projection'!I6/'The 3-Statement Projection'!I$6,0) -> 1 | S5: =IFERROR('The 3-Statement Projection'!J6/'The 3-Statement Projection'!J$6,0) -> 1 | T5: =IFERROR('The 3-Statement Projection'!K6/'The 3-Statement Projection'!K$6,0) -> 1
B6: ='Historical FS'!B8 -> COGS | C6: =IFERROR('Historical FS'!C8/'Historical FS'!C5,0) -> 0.94185787 | D6: =IFERROR('Historical FS'!D8/'Historical FS'!D5,0) -> 0.78529972 | E6: =IFERROR('Historical FS'!E8/'Historical FS'!E5,0) -> 0.76851018 | F6: =IFERROR('Historical FS'!F8/'Historical FS'!F5,0) -> 0.8051797 | G6: =IFERROR('Historical FS'!G8/'Historical FS'!G5,0) -> 0.87370853 | H6: =IFERROR('Historical FS'!H8/'Historical FS'!H5,0) -> 0.74643054 | I6: =IFERROR('Historical FS'!I8/'Historical FS'!I5,0) -> 0.64972707 | J6: =IFERROR('Historical FS'!J8/'Historical FS'!J5,0) -> 0.83827528 | ... L6: =IFERROR('Historical FS'!L8/'Historical FS'!L5,0) -> 0.84190923 | M6: =IFERROR('The 3-Statement Projection'!D9/'The 3-Statement Projection'!D$6,0) -> 0.77082755 | N6: =IFERROR('The 3-Statement Projection'!E9/'The 3-Statement Projection'!E$6,0) -> 0.78923129 | O6: =IFERROR('The 3-Statement Projection'!F9/'The 3-Statement Projection'!F$6,0) -> 0.78723129 | P6: =IFERROR('The 3-Statement Projection'!G9/'The 3-Statement Projection'!G$6,0) -> 0.78523129 | Q6: =IFERROR('The 3-Statement Projection'!H9/'The 3-Statement Projection'!H$6,0) -> 0.78523129 | R6: =IFERROR('The 3-Statement Projection'!I9/'The 3-Statement Projection'!I$6,0) -> 0.78523129 | S6: =IFERROR('The 3-Statement Projection'!J9/'The 3-Statement Projection'!J$6,0) -> 0.78523129 | T6: =IFERROR('The 3-Statement Projection'!K9/'The 3-Statement Projection'!K$6,0) -> 0.78523129
B7: ='Historical FS'!B11 -> Gross Profit | C7: =IFERROR('Historical FS'!C11/'Historical FS'!C5,0) -> 0.058142131 | D7: =IFERROR('Historical FS'!D11/'Historical FS'!D5,0) -> 0.21470028 | E7: =IFERROR('Historical FS'!E11/'Historical FS'!E5,0) -> 0.23148982 | F7: =IFERROR('Historical FS'!F11/'Historical FS'!F5,0) -> 0.1948203 | G7: =IFERROR('Historical FS'!G11/'Historical FS'!G5,0) -> 0.12629147 | H7: =IFERROR('Historical FS'!H11/'Historical FS'!H5,0) -> 0.25356946 | I7: =IFERROR('Historical FS'!I11/'Historical FS'!I5,0) -> 0.35027293 | J7: =IFERROR('Historical FS'!J11/'Historical FS'!J5,0) -> 0.16172472 | ... L7: =IFERROR('Historical FS'!L11/'Historical FS'!L5,0) -> 0.15809077 | M7: =IFERROR('The 3-Statement Projection'!D10/'The 3-Statement Projection'!D$6,0) -> 0.22917245 | N7: =IFERROR('The 3-Statement Projection'!E10/'The 3-Statement Projection'!E$6,0) -> 0.21076871 | O7: =IFERROR('The 3-Statement Projection'!F10/'The 3-Statement Projection'!F$6,0) -> 0.21276871 | P7: =IFERROR('The 3-Statement Projection'!G10/'The 3-Statement Projection'!G$6,0) -> 0.21476871 | Q7: =IFERROR('The 3-Statement Projection'!H10/'The 3-Statement Projection'!H$6,0) -> 0.21476871 | R7: =IFERROR('The 3-Statement Projection'!I10/'The 3-Statement Projection'!I$6,0) -> 0.21476871 | S7: =IFERROR('The 3-Statement Projection'!J10/'The 3-Statement Projection'!J$6,0) -> 0.21476871 | T7: =IFERROR('The 3-Statement Projection'!K10/'The 3-Statement Projection'!K$6,0) -> 0.21476871
B8: ='Historical FS'!B14 -> Employee Benefit Expenses | C8: =IFERROR('Historical FS'!C14/'Historical FS'!C5,0) -> 0.019901747 | D8: =IFERROR('Historical FS'!D14/'Historical FS'!D5,0) -> 0.014365146 | E8: =IFERROR('Historical FS'!E14/'Historical FS'!E5,0) -> 0.0092213115 | F8: =IFERROR('Historical FS'!F14/'Historical FS'!F5,0) -> 0.010404217 | G8: =IFERROR('Historical FS'!G14/'Historical FS'!G5,0) -> 0.013233035 | H8: =IFERROR('Historical FS'!H14/'Historical FS'!H5,0) -> 0.01346572 | I8: =IFERROR('Historical FS'!I14/'Historical FS'!I5,0) -> 0.010337665 | J8: =IFERROR('Historical FS'!J14/'Historical FS'!J5,0) -> 0.0061009262 | ... L8: =IFERROR('Historical FS'!L14/'Historical FS'!L5,0) -> 0.0095386704 | M8: =IFERROR('The 3-Statement Projection'!D12/'The 3-Statement Projection'!D$6,0) -> 0.0093 | N8: =IFERROR('The 3-Statement Projection'!E12/'The 3-Statement Projection'!E$6,0) -> 0.0093 | O8: =IFERROR('The 3-Statement Projection'!F12/'The 3-Statement Projection'!F$6,0) -> 0.0093 | P8: =IFERROR('The 3-Statement Projection'!G12/'The 3-Statement Projection'!G$6,0) -> 0.0093 | Q8: =IFERROR('The 3-Statement Projection'!H12/'The 3-Statement Projection'!H$6,0) -> 0.0093 | R8: =IFERROR('The 3-Statement Projection'!I12/'The 3-Statement Projection'!I$6,0) -> 0.0093 | S8: =IFERROR('The 3-Statement Projection'!J12/'The 3-Statement Projection'!J$6,0) -> 0.0093 | T8: =IFERROR('The 3-Statement Projection'!K12/'The 3-Statement Projection'!K$6,0) -> 0.0093
B9: ='Historical FS'!B17 -> Selling, General & Admin Expenses | C9: =IFERROR('Historical FS'!C17/'Historical FS'!C5,0) -> 0.052643332 | D9: =IFERROR('Historical FS'!D17/'Historical FS'!D5,0) -> 0.033330794 | E9: =IFERROR('Historical FS'!E17/'Historical FS'!E5,0) -> 0.038743019 | F9: =IFERROR('Historical FS'!F17/'Historical FS'!F5,0) -> 0.044273946 | G9: =IFERROR('Historical FS'!G17/'Historical FS'!G5,0) -> 0.046368136 | H9: =IFERROR('Historical FS'!H17/'Historical FS'!H5,0) -> 0.046776349 | I9: =IFERROR('Historical FS'!I17/'Historical FS'!I5,0) -> 0.036882276 | J9: =IFERROR('Historical FS'!J17/'Historical FS'!J5,0) -> 0.025211475 | ... L9: =IFERROR('Historical FS'!L17/'Historical FS'!L5,0) -> 0.041441114 | M9: =IFERROR('The 3-Statement Projection'!D13/'The 3-Statement Projection'!D$6,0) -> 0.0374 | N9: =IFERROR('The 3-Statement Projection'!E13/'The 3-Statement Projection'!E$6,0) -> 0.0374 | O9: =IFERROR('The 3-Statement Projection'!F13/'The 3-Statement Projection'!F$6,0) -> 0.0374 | P9: =IFERROR('The 3-Statement Projection'!G13/'The 3-Statement Projection'!G$6,0) -> 0.0374 | Q9: =IFERROR('The 3-Statement Projection'!H13/'The 3-Statement Projection'!H$6,0) -> 0.0374 | R9: =IFERROR('The 3-Statement Projection'!I13/'The 3-Statement Projection'!I$6,0) -> 0.0374 | S9: =IFERROR('The 3-Statement Projection'!J13/'The 3-Statement Projection'!J$6,0) -> 0.0374 | T9: =IFERROR('The 3-Statement Projection'!K13/'The 3-Statement Projection'!K$6,0) -> 0.0374
B10: ='Historical FS'!B20 -> EBITDA | C10: =IFERROR('Historical FS'!C20/'Historical FS'!C5,0) -> -0.014402948 | D10: =IFERROR('Historical FS'!D20/'Historical FS'!D5,0) -> 0.16700434 | E10: =IFERROR('Historical FS'!E20/'Historical FS'!E5,0) -> 0.18352549 | F10: =IFERROR('Historical FS'!F20/'Historical FS'!F5,0) -> 0.14014214 | G10: =IFERROR('Historical FS'!G20/'Historical FS'!G5,0) -> 0.066690297 | H10: =IFERROR('Historical FS'!H20/'Historical FS'!H5,0) -> 0.1933274 | I10: =IFERROR('Historical FS'!I20/'Historical FS'!I5,0) -> 0.30305299 | J10: =IFERROR('Historical FS'!J20/'Historical FS'!J5,0) -> 0.13041231 | ... L10: =IFERROR('Historical FS'!L20/'Historical FS'!L5,0) -> 0.10711099 | M10: =IFERROR('The 3-Statement Projection'!D15/'The 3-Statement Projection'!D$6,0) -> 0.18247245 | N10: =IFERROR('The 3-Statement Projection'!E15/'The 3-Statement Projection'!E$6,0) -> 0.16406871 | O10: =IFERROR('The 3-Statement Projection'!F15/'The 3-Statement Projection'!F$6,0) -> 0.16606871 | P10: =IFERROR('The 3-Statement Projection'!G15/'The 3-Statement Projection'!G$6,0) -> 0.16806871 | Q10: =IFERROR('The 3-Statement Projection'!H15/'The 3-Statement Projection'!H$6,0) -> 0.16806871 | R10: =IFERROR('The 3-Statement Projection'!I15/'The 3-Statement Projection'!I$6,0) -> 0.16806871 | S10: =IFERROR('The 3-Statement Projection'!J15/'The 3-Statement Projection'!J$6,0) -> 0.16806871 | T10: =IFERROR('The 3-Statement Projection'!K15/'The 3-Statement Projection'!K$6,0) -> 0.16806871
B11: ='Historical FS'!B23 -> Depreciation | C11: =IFERROR('Historical FS'!C23/'Historical FS'!C5,0) -> 0.081253838 | D11: =IFERROR('Historical FS'!D23/'Historical FS'!D5,0) -> 0.04469495 | E11: =IFERROR('Historical FS'!E23/'Historical FS'!E5,0) -> 0.030726446 | F11: =IFERROR('Historical FS'!F23/'Historical FS'!F5,0) -> 0.018386119 | G11: =IFERROR('Historical FS'!G23/'Historical FS'!G5,0) -> 0.023577908 | H11: =IFERROR('Historical FS'!H23/'Historical FS'!H5,0) -> 0.0261848 | I11: =IFERROR('Historical FS'!I23/'Historical FS'!I5,0) -> 0.01707647 | J11: =IFERROR('Historical FS'!J23/'Historical FS'!J5,0) -> 0.010761913 | ... L11: =IFERROR('Historical FS'!L23/'Historical FS'!L5,0) -> 0.01655507 | M11: =IFERROR('The 3-Statement Projection'!D18/'The 3-Statement Projection'!D$6,0) -> 0.021966851 | N11: =IFERROR('The 3-Statement Projection'!E18/'The 3-Statement Projection'!E$6,0) -> 0.021379118 | O11: =IFERROR('The 3-Statement Projection'!F18/'The 3-Statement Projection'!F$6,0) -> 0.02195089 | P11: =IFERROR('The 3-Statement Projection'!G18/'The 3-Statement Projection'!G$6,0) -> 0.022536957 | Q11: =IFERROR('The 3-Statement Projection'!H18/'The 3-Statement Projection'!H$6,0) -> 0.023137675 | R11: =IFERROR('The 3-Statement Projection'!I18/'The 3-Statement Projection'!I$6,0) -> 0.023753411 | S11: =IFERROR('The 3-Statement Projection'!J18/'The 3-Statement Projection'!J$6,0) -> 0.024384541 | T11: =IFERROR('The 3-Statement Projection'!K18/'The 3-Statement Projection'!K$6,0) -> 0.025031448
B12: ='Historical FS'!B26 -> EBIT | C12: =IFERROR('Historical FS'!C26/'Historical FS'!C5,0) -> -0.095656786 | D12: =IFERROR('Historical FS'!D26/'Historical FS'!D5,0) -> 0.12230939 | E12: =IFERROR('Historical FS'!E26/'Historical FS'!E5,0) -> 0.15279905 | F12: =IFERROR('Historical FS'!F26/'Historical FS'!F5,0) -> 0.12175602 | G12: =IFERROR('Historical FS'!G26/'Historical FS'!G5,0) -> 0.043112389 | H12: =IFERROR('Historical FS'!H26/'Historical FS'!H5,0) -> 0.1671426 | I12: =IFERROR('Historical FS'!I26/'Historical FS'!I5,0) -> 0.28597652 | J12: =IFERROR('Historical FS'!J26/'Historical FS'!J5,0) -> 0.1196504 | ... L12: =IFERROR('Historical FS'!L26/'Historical FS'!L5,0) -> 0.090555915 | M12: =IFERROR('The 3-Statement Projection'!D19/'The 3-Statement Projection'!D$6,0) -> 0.1605056 | N12: =IFERROR('The 3-Statement Projection'!E19/'The 3-Statement Projection'!E$6,0) -> 0.14268959 | O12: =IFERROR('The 3-Statement Projection'!F19/'The 3-Statement Projection'!F$6,0) -> 0.14411782 | P12: =IFERROR('The 3-Statement Projection'!G19/'The 3-Statement Projection'!G$6,0) -> 0.14553175 | Q12: =IFERROR('The 3-Statement Projection'!H19/'The 3-Statement Projection'!H$6,0) -> 0.14493103 | R12: =IFERROR('The 3-Statement Projection'!I19/'The 3-Statement Projection'!I$6,0) -> 0.14431529 | S12: =IFERROR('The 3-Statement Projection'!J19/'The 3-Statement Projection'!J$6,0) -> 0.14368416 | T12: =IFERROR('The 3-Statement Projection'!K19/'The 3-Statement Projection'!K$6,0) -> 0.14303726
B13: ='Historical FS'!B29 -> Finance Costs | C13: =IFERROR('Historical FS'!C29/'Historical FS'!C5,0) -> 0.025986714 | D13: =IFERROR('Historical FS'!D29/'Historical FS'!D5,0) -> 0.080752533 | E13: =IFERROR('Historical FS'!E29/'Historical FS'!E5,0) -> 0.067499099 | F13: =IFERROR('Historical FS'!F29/'Historical FS'!F5,0) -> 0.058882534 | G13: =IFERROR('Historical FS'!G29/'Historical FS'!G5,0) -> 0.067937458 | H13: =IFERROR('Historical FS'!H29/'Historical FS'!H5,0) -> 0.066752246 | I13: =IFERROR('Historical FS'!I29/'Historical FS'!I5,0) -> 0.028106533 | J13: =IFERROR('Historical FS'!J29/'Historical FS'!J5,0) -> 0.016657134 | ... L13: =IFERROR('Historical FS'!L29/'Historical FS'!L5,0) -> 0.01790705 | M13: =IFERROR('The 3-Statement Projection'!D21/'The 3-Statement Projection'!D$6,0) -> 0.028519933 | N13: =IFERROR('The 3-Statement Projection'!E21/'The 3-Statement Projection'!E$6,0) -> 0.021098766 | O13: =IFERROR('The 3-Statement Projection'!F21/'The 3-Statement Projection'!F$6,0) -> 0.016093697 | P13: =IFERROR('The 3-Statement Projection'!G21/'The 3-Statement Projection'!G$6,0) -> 0.014175325 | Q13: =IFERROR('The 3-Statement Projection'!H21/'The 3-Statement Projection'!H$6,0) -> 0.012324587 | R13: =IFERROR('The 3-Statement Projection'!I21/'The 3-Statement Projection'!I$6,0) -> 0.010479998 | S13: =IFERROR('The 3-Statement Projection'!J21/'The 3-Statement Projection'!J$6,0) -> 0.0086354091 | T13: =IFERROR('The 3-Statement Projection'!K21/'The 3-Statement Projection'!K$6,0) -> 0.0067908201
B14: Other Income | C14: =IFERROR('Historical FS'!C32/'Historical FS'!C5,0) -> 0 | D14: =IFERROR('Historical FS'!D32/'Historical FS'!D5,0) -> 0.013131236 | E14: =IFERROR('Historical FS'!E32/'Historical FS'!E5,0) -> 0.0068456134 | F14: =IFERROR('Historical FS'!F32/'Historical FS'!F5,0) -> 0.0058370326 | G14: =IFERROR('Historical FS'!G32/'Historical FS'!G5,0) -> 0.0065771336 | H14: =IFERROR('Historical FS'!H32/'Historical FS'!H5,0) -> 0.004414346 | I14: =IFERROR('Historical FS'!I32/'Historical FS'!I5,0) -> 0.0040094681 | J14: =IFERROR('Historical FS'!J32/'Historical FS'!J5,0) -> 0.0071746089 | ... L14: =IFERROR('Historical FS'!L32/'Historical FS'!L5,0) -> 0.0099928928 | M14: =IFERROR('The 3-Statement Projection'!D20/'The 3-Statement Projection'!D$6,0) -> 0.01301228 | N14: =IFERROR('The 3-Statement Projection'!E20/'The 3-Statement Projection'!E$6,0) -> 0 | O14: =IFERROR('The 3-Statement Projection'!F20/'The 3-Statement Projection'!F$6,0) -> 0 | P14: =IFERROR('The 3-Statement Projection'!G20/'The 3-Statement Projection'!G$6,0) -> 0 | Q14: =IFERROR('The 3-Statement Projection'!H20/'The 3-Statement Projection'!H$6,0) -> 0 | R14: =IFERROR('The 3-Statement Projection'!I20/'The 3-Statement Projection'!I$6,0) -> 0 | S14: =IFERROR('The 3-Statement Projection'!J20/'The 3-Statement Projection'!J$6,0) -> 0 | T14: =IFERROR('The 3-Statement Projection'!K20/'The 3-Statement Projection'!K$6,0) -> 0
B15: ='Historical FS'!B35 -> Net Extraordinary Items | C15: =IFERROR('Historical FS'!C35/'Historical FS'!C5,0) -> -0.015240328 | D15: =IFERROR('Historical FS'!D35/'Historical FS'!D5,0) -> 0.0017213802 | E15: =IFERROR('Historical FS'!E35/'Historical FS'!E5,0) -> 0.0017564403 | F15: =IFERROR('Historical FS'!F35/'Historical FS'!F5,0) -> 0.00010670992 | G15: =IFERROR('Historical FS'!G35/'Historical FS'!G5,0) -> 0.00026256022 | H15: =IFERROR('Historical FS'!H35/'Historical FS'!H5,0) -> 0.0038641901 | I15: =IFERROR('Historical FS'!I35/'Historical FS'!I5,0) -> 0.0031802006 | J15: =IFERROR('Historical FS'!J35/'Historical FS'!J5,0) -> 0 | ... L15: =IFERROR('Historical FS'!L35/'Historical FS'!L5,0) -> 0 | M15: 0 | N15: 0 | O15: 0 | P15: 0 | Q15: 0 | R15: 0 | S15: 0 | T15: 0
B16: ='Historical FS'!B37 -> Profit Before Tax | C16: =IFERROR('Historical FS'!C37/'Historical FS'!C5,0) -> -0.13688383 | D16: =IFERROR('Historical FS'!D37/'Historical FS'!D5,0) -> 0.056409475 | E16: =IFERROR('Historical FS'!E37/'Historical FS'!E5,0) -> 0.093902 | F16: =IFERROR('Historical FS'!F37/'Historical FS'!F5,0) -> 0.068817227 | G16: =IFERROR('Historical FS'!G37/'Historical FS'!G5,0) -> -0.017985375 | H16: =IFERROR('Historical FS'!H37/'Historical FS'!H5,0) -> 0.10866888 | I16: =IFERROR('Historical FS'!I37/'Historical FS'!I5,0) -> 0.26505966 | J16: =IFERROR('Historical FS'!J37/'Historical FS'!J5,0) -> 0.11016788 | ... L16: =IFERROR('Historical FS'!L37/'Historical FS'!L5,0) -> 0.082641757 | M16: =IFERROR('The 3-Statement Projection'!D23/'The 3-Statement Projection'!D$6,0) -> 0.14499795 | N16: =IFERROR('The 3-Statement Projection'!E23/'The 3-Statement Projection'!E$6,0) -> 0.12159082 | O16: =IFERROR('The 3-Statement Projection'!F23/'The 3-Statement Projection'!F$6,0) -> 0.12802412 | P16: =IFERROR('The 3-Statement Projection'!G23/'The 3-Statement Projection'!G$6,0) -> 0.13135642 | Q16: =IFERROR('The 3-Statement Projection'!H23/'The 3-Statement Projection'!H$6,0) -> 0.13260644 | R16: =IFERROR('The 3-Statement Projection'!I23/'The 3-Statement Projection'!I$6,0) -> 0.1338353 | S16: =IFERROR('The 3-Statement Projection'!J23/'The 3-Statement Projection'!J$6,0) -> 0.13504876 | T16: =IFERROR('The 3-Statement Projection'!K23/'The 3-Statement Projection'!K$6,0) -> 0.13624644
B17: ='Historical FS'!B40 -> Provision for Direct Tax | C17: =IFERROR('Historical FS'!C40/'Historical FS'!C5,0) -> -0.047367833 | D17: =IFERROR('Historical FS'!D40/'Historical FS'!D5,0) -> 0.01959022 | E17: =IFERROR('Historical FS'!E40/'Historical FS'!E5,0) -> 0.029532967 | F17: =IFERROR('Historical FS'!F40/'Historical FS'!F5,0) -> 0.026015878 | G17: =IFERROR('Historical FS'!G40/'Historical FS'!G5,0) -> -0.0025599622 | H17: =IFERROR('Historical FS'!H40/'Historical FS'!H5,0) -> 0.032878363 | I17: =IFERROR('Historical FS'!I40/'Historical FS'!I5,0) -> 0.072790364 | J17: =IFERROR('Historical FS'!J40/'Historical FS'!J5,0) -> 0.027393961 | ... L17: =IFERROR('Historical FS'!L40/'Historical FS'!L5,0) -> 0.021401891 | M17: =IFERROR('The 3-Statement Projection'!D25/'The 3-Statement Projection'!D$6,0) -> 0.036493083 | N17: =IFERROR('The 3-Statement Projection'!E25/'The 3-Statement Projection'!E$6,0) -> 0.030601978 | O17: =IFERROR('The 3-Statement Projection'!F25/'The 3-Statement Projection'!F$6,0) -> 0.03222111 | P17: =IFERROR('The 3-Statement Projection'!G25/'The 3-Statement Projection'!G$6,0) -> 0.033059785 | Q17: =IFERROR('The 3-Statement Projection'!H25/'The 3-Statement Projection'!H$6,0) -> 0.03337439 | R17: =IFERROR('The 3-Statement Projection'!I25/'The 3-Statement Projection'!I$6,0) -> 0.033683667 | S17: =IFERROR('The 3-Statement Projection'!J25/'The 3-Statement Projection'!J$6,0) -> 0.033989071 | T17: =IFERROR('The 3-Statement Projection'!K25/'The 3-Statement Projection'!K$6,0) -> 0.034290503
B18: ='Historical FS'!B42 -> Profit After Tax | C18: =IFERROR('Historical FS'!C42/'Historical FS'!C5,0) -> -0.089515994 | D18: =IFERROR('Historical FS'!D42/'Historical FS'!D5,0) -> 0.036819255 | E18: =IFERROR('Historical FS'!E42/'Historical FS'!E5,0) -> 0.064369033 | F18: =IFERROR('Historical FS'!F42/'Historical FS'!F5,0) -> 0.042801349 | G18: =IFERROR('Historical FS'!G42/'Historical FS'!G5,0) -> -0.015425413 | H18: =IFERROR('Historical FS'!H42/'Historical FS'!H5,0) -> 0.075790522 | I18: =IFERROR('Historical FS'!I42/'Historical FS'!I5,0) -> 0.19226929 | J18: =IFERROR('Historical FS'!J42/'Historical FS'!J5,0) -> 0.082773915 | ... L18: =IFERROR('Historical FS'!L42/'Historical FS'!L5,0) -> 0.061239867 | M18: =IFERROR('The 3-Statement Projection'!D27/'The 3-Statement Projection'!D$6,0) -> 0.10850486 | N18: =IFERROR('The 3-Statement Projection'!E27/'The 3-Statement Projection'!E$6,0) -> 0.090988844 | O18: =IFERROR('The 3-Statement Projection'!F27/'The 3-Statement Projection'!F$6,0) -> 0.095803008 | P18: =IFERROR('The 3-Statement Projection'!G27/'The 3-Statement Projection'!G$6,0) -> 0.098296639 | Q18: =IFERROR('The 3-Statement Projection'!H27/'The 3-Statement Projection'!H$6,0) -> 0.099232054 | R18: =IFERROR('The 3-Statement Projection'!I27/'The 3-Statement Projection'!I$6,0) -> 0.10015163 | S18: =IFERROR('The 3-Statement Projection'!J27/'The 3-Statement Projection'!J$6,0) -> 0.10105968 | T18: =IFERROR('The 3-Statement Projection'!K27/'The 3-Statement Projection'!K$6,0) -> 0.10195593
A20: # | B20: ='Historical FS'!B47 -> Balance Sheet
B22: Equity & Liabilities | M22: =IFERROR('The 3-Statement Projection'!D34/'The 3-Statement Projection'!D$72,0) -> 0.078366096 | N22: =IFERROR('The 3-Statement Projection'!E34/'The 3-Statement Projection'!E$72,0) -> 0.0807242 | O22: =IFERROR('The 3-Statement Projection'!F34/'The 3-Statement Projection'!F$72,0) -> 0.077571632 | P22: =IFERROR('The 3-Statement Projection'!G34/'The 3-Statement Projection'!G$72,0) -> 0.073643923 | Q22: =IFERROR('The 3-Statement Projection'!H34/'The 3-Statement Projection'!H$72,0) -> 0.070047065 | R22: =IFERROR('The 3-Statement Projection'!I34/'The 3-Statement Projection'!I$72,0) -> 0.066765176 | S22: =IFERROR('The 3-Statement Projection'!J34/'The 3-Statement Projection'!J$72,0) -> 0.063756774 | T22: =IFERROR('The 3-Statement Projection'!K34/'The 3-Statement Projection'!K$72,0) -> 0.06098777
B23: ='Historical FS'!B53 -> Share Capital | C23: =IFERROR('Historical FS'!C53/'Historical FS'!C96,0) -> 0.1498317 | D23: =IFERROR('Historical FS'!D53/'Historical FS'!D96,0) -> 0.148718 | E23: =IFERROR('Historical FS'!E53/'Historical FS'!E96,0) -> 0.16648456 | F23: =IFERROR('Historical FS'!F53/'Historical FS'!F96,0) -> 0.16606701 | G23: =IFERROR('Historical FS'!G53/'Historical FS'!G96,0) -> 0.17204118 | H23: =IFERROR('Historical FS'!H53/'Historical FS'!H96,0) -> 0.17125763 | I23: =IFERROR('Historical FS'!I53/'Historical FS'!I96,0) -> 0.087703878 | J23: =IFERROR('Historical FS'!J53/'Historical FS'!J96,0) -> 0.095026994 | ... L23: =IFERROR('Historical FS'!L53/'Historical FS'!L96,0) -> 0.071825382 | M23: =IFERROR('The 3-Statement Projection'!D35/'The 3-Statement Projection'!D$72,0) -> 0.36607891 | N23: =IFERROR('The 3-Statement Projection'!E35/'The 3-Statement Projection'!E$72,0) -> 0.45426489 | O23: =IFERROR('The 3-Statement Projection'!F35/'The 3-Statement Projection'!F$72,0) -> 0.51493703 | P23: =IFERROR('The 3-Statement Projection'!G35/'The 3-Statement Projection'!G$72,0) -> 0.56539959 | Q23: =IFERROR('The 3-Statement Projection'!H35/'The 3-Statement Projection'!H$72,0) -> 0.61132902 | R23: =IFERROR('The 3-Statement Projection'!I35/'The 3-Statement Projection'!I$72,0) -> 0.65348487 | S23: =IFERROR('The 3-Statement Projection'!J35/'The 3-Statement Projection'!J$72,0) -> 0.69230715 | T23: =IFERROR('The 3-Statement Projection'!K35/'The 3-Statement Projection'!K$72,0) -> 0.72816573
B24: ='Historical FS'!B54 -> Reserves & Surplus | C24: =IFERROR('Historical FS'!C54/'Historical FS'!C96,0) -> -0.0099833339 | D24: =IFERROR('Historical FS'!D54/'Historical FS'!D96,0) -> -0.009571688 | E24: =IFERROR('Historical FS'!E54/'Historical FS'!E96,0) -> 0.1292752 | F24: =IFERROR('Historical FS'!F54/'Historical FS'!F96,0) -> 0.17598181 | G24: =IFERROR('Historical FS'!G54/'Historical FS'!G96,0) -> 0.16797387 | H24: =IFERROR('Historical FS'!H54/'Historical FS'!H96,0) -> 0.2371306 | I24: =IFERROR('Historical FS'!I54/'Historical FS'!I96,0) -> 0.26923339 | J24: =IFERROR('Historical FS'!J54/'Historical FS'!J96,0) -> 0.40231381 | ... L24: =IFERROR('Historical FS'!L54/'Historical FS'!L96,0) -> 0.35300165 | M24: =IFERROR('The 3-Statement Projection'!D36/'The 3-Statement Projection'!D$72,0) -> 0.444445 | N24: =IFERROR('The 3-Statement Projection'!E36/'The 3-Statement Projection'!E$72,0) -> 0.53498909 | O24: =IFERROR('The 3-Statement Projection'!F36/'The 3-Statement Projection'!F$72,0) -> 0.59250867 | P24: =IFERROR('The 3-Statement Projection'!G36/'The 3-Statement Projection'!G$72,0) -> 0.63904351 | Q24: =IFERROR('The 3-Statement Projection'!H36/'The 3-Statement Projection'!H$72,0) -> 0.68137608 | R24: =IFERROR('The 3-Statement Projection'!I36/'The 3-Statement Projection'!I$72,0) -> 0.72025005 | S24: =IFERROR('The 3-Statement Projection'!J36/'The 3-Statement Projection'!J$72,0) -> 0.75606392 | T24: =IFERROR('The 3-Statement Projection'!K36/'The 3-Statement Projection'!K$72,0) -> 0.7891535
B25: ='Historical FS'!B56 -> Total Equity | C25: =IFERROR('Historical FS'!C56/'Historical FS'!C96,0) -> 0.13984837 | D25: =IFERROR('Historical FS'!D56/'Historical FS'!D96,0) -> 0.13914631 | E25: =IFERROR('Historical FS'!E56/'Historical FS'!E96,0) -> 0.29575975 | F25: =IFERROR('Historical FS'!F56/'Historical FS'!F96,0) -> 0.34204882 | G25: =IFERROR('Historical FS'!G56/'Historical FS'!G96,0) -> 0.34001506 | H25: =IFERROR('Historical FS'!H56/'Historical FS'!H96,0) -> 0.40838823 | I25: =IFERROR('Historical FS'!I56/'Historical FS'!I96,0) -> 0.35693727 | J25: =IFERROR('Historical FS'!J56/'Historical FS'!J96,0) -> 0.4973408 | ... L25: =IFERROR('Historical FS'!L56/'Historical FS'!L96,0) -> 0.42482703 | M25: =IFERROR('The 3-Statement Projection'!D39/'The 3-Statement Projection'!D$72,0) -> 0.25064366 | N25: =IFERROR('The 3-Statement Projection'!E39/'The 3-Statement Projection'!E$72,0) -> 0.23759314 | O25: =IFERROR('The 3-Statement Projection'!F39/'The 3-Statement Projection'!F$72,0) -> 0.20237078 | P25: =IFERROR('The 3-Statement Projection'!G39/'The 3-Statement Projection'!G$72,0) -> 0.16738496 | Q25: =IFERROR('The 3-Statement Projection'!H39/'The 3-Statement Projection'!H$72,0) -> 0.13583469 | R25: =IFERROR('The 3-Statement Projection'!I39/'The 3-Statement Projection'!I$72,0) -> 0.10719066 | S25: =IFERROR('The 3-Statement Projection'!J39/'The 3-Statement Projection'!J$72,0) -> 0.081084811 | T25: =IFERROR('The 3-Statement Projection'!K39/'The 3-Statement Projection'!K$72,0) -> 0.057211368
B26: ='Historical FS'!B60 -> LT Borrowings (excl. current portion) | C26: =IFERROR('Historical FS'!C60/'Historical FS'!C96,0) -> 0 | D26: =IFERROR('Historical FS'!D60/'Historical FS'!D96,0) -> 0.51234769 | E26: =IFERROR('Historical FS'!E60/'Historical FS'!E96,0) -> 0.58219073 | F26: =IFERROR('Historical FS'!F60/'Historical FS'!F96,0) -> 0.47821909 | G26: =IFERROR('Historical FS'!G60/'Historical FS'!G96,0) -> 0.47534117 | H26: =IFERROR('Historical FS'!H60/'Historical FS'!H96,0) -> 0.46872545 | I26: =IFERROR('Historical FS'!I60/'Historical FS'!I96,0) -> 0.31087246 | J26: =IFERROR('Historical FS'!J60/'Historical FS'!J96,0) -> 0.21731666 | ... L26: =IFERROR('Historical FS'!L60/'Historical FS'!L96,0) -> 0.14891317 | M26: =IFERROR('The 3-Statement Projection'!D40/'The 3-Statement Projection'!D$72,0) -> 0.043454981 | N26: =IFERROR('The 3-Statement Projection'!E40/'The 3-Statement Projection'!E$72,0) -> 0.045088582 | O26: =IFERROR('The 3-Statement Projection'!F40/'The 3-Statement Projection'!F$72,0) -> 0.042969969 | P26: =IFERROR('The 3-Statement Projection'!G40/'The 3-Statement Projection'!G$72,0) -> 0.039893972 | Q26: =IFERROR('The 3-Statement Projection'!H40/'The 3-Statement Projection'!H$72,0) -> 0.036617471 | R26: =IFERROR('The 3-Statement Projection'!I40/'The 3-Statement Projection'!I$72,0) -> 0.033236067 | S26: =IFERROR('The 3-Statement Projection'!J40/'The 3-Statement Projection'!J$72,0) -> 0.029805865 | T26: =IFERROR('The 3-Statement Projection'!K40/'The 3-Statement Projection'!K$72,0) -> 0.026367992
B27: ='Historical FS'!B61 -> Deferred Tax Liability | C27: =IFERROR('Historical FS'!C61/'Historical FS'!C96,0) -> 0 | D27: =IFERROR('Historical FS'!D61/'Historical FS'!D96,0) -> 0 | E27: =IFERROR('Historical FS'!E61/'Historical FS'!E96,0) -> 0.039688414 | F27: =IFERROR('Historical FS'!F61/'Historical FS'!F96,0) -> 0.051765561 | G27: =IFERROR('Historical FS'!G61/'Historical FS'!G96,0) -> 0.051223836 | H27: =IFERROR('Historical FS'!H61/'Historical FS'!H96,0) -> 0.064144558 | I27: =IFERROR('Historical FS'!I61/'Historical FS'!I96,0) -> 0.03968927 | J27: =IFERROR('Historical FS'!J61/'Historical FS'!J96,0) -> 0.044324469 | ... L27: =IFERROR('Historical FS'!L61/'Historical FS'!L96,0) -> 0.038828849 | M27: =IFERROR('The 3-Statement Projection'!D41/'The 3-Statement Projection'!D$72,0) -> 0.0016480194 | N27: =IFERROR('The 3-Statement Projection'!E41/'The 3-Statement Projection'!E$72,0) -> 0.00179101 | O27: =IFERROR('The 3-Statement Projection'!F41/'The 3-Statement Projection'!F$72,0) -> 0.0017210647 | P27: =IFERROR('The 3-Statement Projection'!G41/'The 3-Statement Projection'!G$72,0) -> 0.0016339215 | Q27: =IFERROR('The 3-Statement Projection'!H41/'The 3-Statement Projection'!H$72,0) -> 0.0015541188 | R27: =IFERROR('The 3-Statement Projection'!I41/'The 3-Statement Projection'!I$72,0) -> 0.0014813042 | S27: =IFERROR('The 3-Statement Projection'!J41/'The 3-Statement Projection'!J$72,0) -> 0.0014145575 | T27: =IFERROR('The 3-Statement Projection'!K41/'The 3-Statement Projection'!K$72,0) -> 0.0013531222
B28: ='Historical FS'!B62 -> Long-term Provisions | C28: =IFERROR('Historical FS'!C62/'Historical FS'!C96,0) -> 0.00057187674 | D28: =IFERROR('Historical FS'!D62/'Historical FS'!D96,0) -> 0.00072417376 | E28: =IFERROR('Historical FS'!E62/'Historical FS'!E96,0) -> 0.0011396614 | F28: =IFERROR('Historical FS'!F62/'Historical FS'!F96,0) -> 0.0012305601 | G28: =IFERROR('Historical FS'!G62/'Historical FS'!G96,0) -> 0.0016390656 | H28: =IFERROR('Historical FS'!H62/'Historical FS'!H96,0) -> 0.0017404968 | I28: =IFERROR('Historical FS'!I62/'Historical FS'!I96,0) -> 0.0010646529 | J28: =IFERROR('Historical FS'!J62/'Historical FS'!J96,0) -> 0.0012206163 | ... L28: =IFERROR('Historical FS'!L62/'Historical FS'!L96,0) -> 0.0013582108 | M28: =IFERROR('The 3-Statement Projection'!D42/'The 3-Statement Projection'!D$72,0) -> 0.29574666 | N28: =IFERROR('The 3-Statement Projection'!E42/'The 3-Statement Projection'!E$72,0) -> 0.28447273 | O28: =IFERROR('The 3-Statement Projection'!F42/'The 3-Statement Projection'!F$72,0) -> 0.24706182 | P28: =IFERROR('The 3-Statement Projection'!G42/'The 3-Statement Projection'!G$72,0) -> 0.20891286 | Q28: =IFERROR('The 3-Statement Projection'!H42/'The 3-Statement Projection'!H$72,0) -> 0.17400628 | R28: =IFERROR('The 3-Statement Projection'!I42/'The 3-Statement Projection'!I$72,0) -> 0.14190803 | S28: =IFERROR('The 3-Statement Projection'!J42/'The 3-Statement Projection'!J$72,0) -> 0.11230523 | T28: =IFERROR('The 3-Statement Projection'!K42/'The 3-Statement Projection'!K$72,0) -> 0.084932482
B29: ='Historical FS'!B63 -> Total Non-Current Liabilities | C29: =IFERROR('Historical FS'!C63/'Historical FS'!C96,0) -> 0.00057187674 | D29: =IFERROR('Historical FS'!D63/'Historical FS'!D96,0) -> 0.51307186 | E29: =IFERROR('Historical FS'!E63/'Historical FS'!E96,0) -> 0.62301881 | F29: =IFERROR('Historical FS'!F63/'Historical FS'!F96,0) -> 0.53121521 | G29: =IFERROR('Historical FS'!G63/'Historical FS'!G96,0) -> 0.52820407 | H29: =IFERROR('Historical FS'!H63/'Historical FS'!H96,0) -> 0.5346105 | I29: =IFERROR('Historical FS'!I63/'Historical FS'!I96,0) -> 0.35162638 | J29: =IFERROR('Historical FS'!J63/'Historical FS'!J96,0) -> 0.26286174 | ... L29: =IFERROR('Historical FS'!L63/'Historical FS'!L96,0) -> 0.18910023 | M29: =IFERROR(('The 3-Statement Projection'!D45+'The 3-Statement Projection'!D46)/'The 3-Statement Projection'!D$72,0) -> 0.1056504 | N29: =IFERROR(('The 3-Statement Projection'!E45+'The 3-Statement Projection'!E46)/'The 3-Statement Projection'!E$72,0) -> 0.013300612 | O29: =IFERROR(('The 3-Statement Projection'!F45+'The 3-Statement Projection'!F46)/'The 3-Statement Projection'!F$72,0) -> 6.6419491e-18 | P29: =IFERROR(('The 3-Statement Projection'!G45+'The 3-Statement Projection'!G46)/'The 3-Statement Projection'!G$72,0) -> 6.3056452e-18 | Q29: =IFERROR(('The 3-Statement Projection'!H45+'The 3-Statement Projection'!H46)/'The 3-Statement Projection'!H$72,0) -> 5.99767e-18 | R29: =IFERROR(('The 3-Statement Projection'!I45+'The 3-Statement Projection'!I46)/'The 3-Statement Projection'!I$72,0) -> 5.7166633e-18 | S29: =IFERROR(('The 3-Statement Projection'!J45+'The 3-Statement Projection'!J46)/'The 3-Statement Projection'!J$72,0) -> 5.4590737e-18 | T29: =IFERROR(('The 3-Statement Projection'!K45+'The 3-Statement Projection'!K46)/'The 3-Statement Projection'!K$72,0) -> 5.221982e-18
B30: ='Historical FS'!B67 -> Short-term Borrowings | C30: =IFERROR('Historical FS'!C67/'Historical FS'!C96,0) -> 0.0065520735 | D30: =IFERROR('Historical FS'!D67/'Historical FS'!D96,0) -> 0.085830333 | E30: =IFERROR('Historical FS'!E67/'Historical FS'!E96,0) -> 0 | F30: =IFERROR('Historical FS'!F67/'Historical FS'!F96,0) -> 0 | G30: =IFERROR('Historical FS'!G67/'Historical FS'!G96,0) -> 0 | H30: =IFERROR('Historical FS'!H67/'Historical FS'!H96,0) -> 0 | I30: =IFERROR('Historical FS'!I67/'Historical FS'!I96,0) -> 0.0026492526 | J30: =IFERROR('Historical FS'!J67/'Historical FS'!J96,0) -> 0.022567989 | ... L30: =IFERROR('Historical FS'!L67/'Historical FS'!L96,0) -> 0.058056853 | M30: =IFERROR('The 3-Statement Projection'!D47/'The 3-Statement Projection'!D$72,0) -> 0.10216376 | N30: =IFERROR('The 3-Statement Projection'!E47/'The 3-Statement Projection'!E$72,0) -> 0.11367884 | O30: =IFERROR('The 3-Statement Projection'!F47/'The 3-Statement Projection'!F$72,0) -> 0.10896245 | P30: =IFERROR('The 3-Statement Projection'!G47/'The 3-Statement Projection'!G$72,0) -> 0.10318251 | Q30: =IFERROR('The 3-Statement Projection'!H47/'The 3-Statement Projection'!H$72,0) -> 0.098142957 | R30: =IFERROR('The 3-Statement Projection'!I47/'The 3-Statement Projection'!I$72,0) -> 0.093544701 | S30: =IFERROR('The 3-Statement Projection'!J47/'The 3-Statement Projection'!J$72,0) -> 0.089329629 | T30: =IFERROR('The 3-Statement Projection'!K47/'The 3-Statement Projection'!K$72,0) -> 0.085449976
B31: ='Historical FS'!B68 -> Trade Payables & Acceptances | C31: =IFERROR('Historical FS'!C68/'Historical FS'!C96,0) -> 0.21638182 | D31: =IFERROR('Historical FS'!D68/'Historical FS'!D96,0) -> 0.24822368 | E31: =IFERROR('Historical FS'!E68/'Historical FS'!E96,0) -> 0.058451705 | F31: =IFERROR('Historical FS'!F68/'Historical FS'!F96,0) -> 0.076365043 | G31: =IFERROR('Historical FS'!G68/'Historical FS'!G96,0) -> 0.092224758 | H31: =IFERROR('Historical FS'!H68/'Historical FS'!H96,0) -> 0.013065813 | I31: =IFERROR('Historical FS'!I68/'Historical FS'!I96,0) -> 0.22130544 | J31: =IFERROR('Historical FS'!J68/'Historical FS'!J96,0) -> 0.20031521 | ... L31: =IFERROR('Historical FS'!L68/'Historical FS'!L96,0) -> 0.19661033 | M31: =IFERROR('The 3-Statement Projection'!D48/'The 3-Statement Projection'!D$72,0) -> 0.051994176 | N31: =IFERROR('The 3-Statement Projection'!E48/'The 3-Statement Projection'!E$72,0) -> 0.053558726 | O31: =IFERROR('The 3-Statement Projection'!F48/'The 3-Statement Projection'!F$72,0) -> 0.051467066 | P31: =IFERROR('The 3-Statement Projection'!G48/'The 3-Statement Projection'!G$72,0) -> 0.048861118 | Q31: =IFERROR('The 3-Statement Projection'!H48/'The 3-Statement Projection'!H$72,0) -> 0.046474682 | R31: =IFERROR('The 3-Statement Projection'!I48/'The 3-Statement Projection'!I$72,0) -> 0.044297221 | S31: =IFERROR('The 3-Statement Projection'!J48/'The 3-Statement Projection'!J$72,0) -> 0.042301213 | T31: =IFERROR('The 3-Statement Projection'!K48/'The 3-Statement Projection'!K$72,0) -> 0.04046404
B32: ='Historical FS'!B69 -> Other Current Liabilities | C32: =IFERROR('Historical FS'!C69/'Historical FS'!C96,0) -> 0.63664586 | D32: =IFERROR('Historical FS'!D69/'Historical FS'!D96,0) -> 0.013727816 | E32: =IFERROR('Historical FS'!E69/'Historical FS'!E96,0) -> 0.02276973 | F32: =IFERROR('Historical FS'!F69/'Historical FS'!F96,0) -> 0.050370926 | G32: =IFERROR('Historical FS'!G69/'Historical FS'!G96,0) -> 0.039556117 | H32: =IFERROR('Historical FS'!H69/'Historical FS'!H96,0) -> 0.043935457 | I32: =IFERROR('Historical FS'!I69/'Historical FS'!I96,0) -> 0.067481663 | J32: =IFERROR('Historical FS'!J69/'Historical FS'!J96,0) -> 0.016914255 | ... L32: =IFERROR('Historical FS'!L69/'Historical FS'!L96,0) -> 0.13140556 | M32: =IFERROR('The 3-Statement Projection'!D49/'The 3-Statement Projection'!D$72,0) -> 0.25980834 | N32: =IFERROR('The 3-Statement Projection'!E49/'The 3-Statement Projection'!E$72,0) -> 0.18053818 | O32: =IFERROR('The 3-Statement Projection'!F49/'The 3-Statement Projection'!F$72,0) -> 0.16042952 | P32: =IFERROR('The 3-Statement Projection'!G49/'The 3-Statement Projection'!G$72,0) -> 0.15204363 | Q32: =IFERROR('The 3-Statement Projection'!H49/'The 3-Statement Projection'!H$72,0) -> 0.14461764 | R32: =IFERROR('The 3-Statement Projection'!I49/'The 3-Statement Projection'!I$72,0) -> 0.13784192 | S32: =IFERROR('The 3-Statement Projection'!J49/'The 3-Statement Projection'!J$72,0) -> 0.13163084 | T32: =IFERROR('The 3-Statement Projection'!K49/'The 3-Statement Projection'!K$72,0) -> 0.12591402
B33: ='Historical FS'!B70 -> Total Current Liabilities | C33: =IFERROR('Historical FS'!C70/'Historical FS'!C96,0) -> 0.85957975 | D33: =IFERROR('Historical FS'!D70/'Historical FS'!D96,0) -> 0.34778182 | E33: =IFERROR('Historical FS'!E70/'Historical FS'!E96,0) -> 0.081221435 | F33: =IFERROR('Historical FS'!F70/'Historical FS'!F96,0) -> 0.12673597 | G33: =IFERROR('Historical FS'!G70/'Historical FS'!G96,0) -> 0.13178088 | H33: =IFERROR('Historical FS'!H70/'Historical FS'!H96,0) -> 0.057001269 | I33: =IFERROR('Historical FS'!I70/'Historical FS'!I96,0) -> 0.29143635 | J33: =IFERROR('Historical FS'!J70/'Historical FS'!J96,0) -> 0.23979746 | ... L33: =IFERROR('Historical FS'!L70/'Historical FS'!L96,0) -> 0.38607275 | M33: =IFERROR('The 3-Statement Projection'!D51/'The 3-Statement Projection'!D$72,0) -> 0.555555 | N33: =IFERROR('The 3-Statement Projection'!E51/'The 3-Statement Projection'!E$72,0) -> 0.46501091 | O33: =IFERROR('The 3-Statement Projection'!F51/'The 3-Statement Projection'!F$72,0) -> 0.40749133 | P33: =IFERROR('The 3-Statement Projection'!G51/'The 3-Statement Projection'!G$72,0) -> 0.36095649 | Q33: =IFERROR('The 3-Statement Projection'!H51/'The 3-Statement Projection'!H$72,0) -> 0.31862392 | R33: =IFERROR('The 3-Statement Projection'!I51/'The 3-Statement Projection'!I$72,0) -> 0.27974995 | S33: =IFERROR('The 3-Statement Projection'!J51/'The 3-Statement Projection'!J$72,0) -> 0.24393608 | T33: =IFERROR('The 3-Statement Projection'!K51/'The 3-Statement Projection'!K$72,0) -> 0.2108465
B34: ='Historical FS'!B72 -> Total Liabilities | C34: =IFERROR('Historical FS'!C72/'Historical FS'!C96,0) -> 0.86015163 | D34: =IFERROR('Historical FS'!D72/'Historical FS'!D96,0) -> 0.86085369 | E34: =IFERROR('Historical FS'!E72/'Historical FS'!E96,0) -> 0.70424025 | F34: =IFERROR('Historical FS'!F72/'Historical FS'!F96,0) -> 0.65795118 | G34: =IFERROR('Historical FS'!G72/'Historical FS'!G96,0) -> 0.65998494 | H34: =IFERROR('Historical FS'!H72/'Historical FS'!H96,0) -> 0.59161177 | I34: =IFERROR('Historical FS'!I72/'Historical FS'!I96,0) -> 0.64306273 | J34: =IFERROR('Historical FS'!J72/'Historical FS'!J96,0) -> 0.5026592 | ... L34: =IFERROR('Historical FS'!L72/'Historical FS'!L96,0) -> 0.57517297 | M34: =IFERROR('The 3-Statement Projection'!D52/'The 3-Statement Projection'!D$72,0) -> 1 | N34: =IFERROR('The 3-Statement Projection'!E52/'The 3-Statement Projection'!E$72,0) -> 1 | O34: =IFERROR('The 3-Statement Projection'!F52/'The 3-Statement Projection'!F$72,0) -> 1 | P34: =IFERROR('The 3-Statement Projection'!G52/'The 3-Statement Projection'!G$72,0) -> 1 | Q34: =IFERROR('The 3-Statement Projection'!H52/'The 3-Statement Projection'!H$72,0) -> 1 | R34: =IFERROR('The 3-Statement Projection'!I52/'The 3-Statement Projection'!I$72,0) -> 1 | S34: =IFERROR('The 3-Statement Projection'!J52/'The 3-Statement Projection'!J$72,0) -> 1 | T34: =IFERROR('The 3-Statement Projection'!K52/'The 3-Statement Projection'!K$72,0) -> 1
B35: ='Historical FS'!B74 -> Total Equity + Liabilities | C35: =IFERROR('Historical FS'!C74/'Historical FS'!C96,0) -> 1 | D35: =IFERROR('Historical FS'!D74/'Historical FS'!D96,0) -> 1 | E35: =IFERROR('Historical FS'!E74/'Historical FS'!E96,0) -> 1 | F35: =IFERROR('Historical FS'!F74/'Historical FS'!F96,0) -> 1 | G35: =IFERROR('Historical FS'!G74/'Historical FS'!G96,0) -> 1 | H35: =IFERROR('Historical FS'!H74/'Historical FS'!H96,0) -> 1 | I35: =IFERROR('Historical FS'!I74/'Historical FS'!I96,0) -> 1 | J35: =IFERROR('Historical FS'!J74/'Historical FS'!J96,0) -> 1 | ... L35: =IFERROR('Historical FS'!L74/'Historical FS'!L96,0) -> 1
B37: Assets
